Workbook
Name AC: AC!$B$2:$C$15
Name AC_LM: AC_LM!$B$2:$C$3
Name AC_LMD: AC_LM!$H$3:$T$3
Name AC_LMI: AC_LM!$H$2:$T$2
Name ACD_1: AC!$H$35:$DQ$42
Name ACD_2: AC!$H$43:$DQ$43
Name ACD_3: AC!$H$44:$DQ$45
Name ACF: AC!$H$24:$DQ$34
Name ACI: AC!$H$2:$DQ$2
Name ACT: AC!$G$24
Name CTAX_D: EMI!$K$3:$K$3
Name FC: FC!$B$2:$C$6
Name FC_LD: FC_LD!$B$2:$C$3
Name FC_LDD: FC_LD!$H$7:$LYE$8
Name FC_LDI: FC_LD!$H$4:$LYE$6
Name FCD: FC!$H$12:$H$13
Name FCD_2: FC!$L$12:$L$13
Name FCF: FC!$H$4:$H$4
Name FCI: FC!$H$3:$H$3
Name FCS: FC!$H$8:$H$10
Name ID: IND!$B$1:$B$17
Name ID_AC: IND!$AA$2:$AA$115
Name ID_ACM: IND!$AC$2:$AC$115
Name ID_DCR: IND!$BI$2:$BI$2
Name ID_DM: IND!$BN$2:$BN$366
Name ID_DY: IND!$BL$2:$BL$366
Name ID_FC: IND!$AV$2:$AV$2
Name ID_IK: IND!$AL$2:$AL$6
Name ID_IKL: IND!$AQ$2:$AQ$5
Name ID_IT: IND!$T$2:$T$50
Name ID_ITM: IND!$W$2:$W$50
Name ID_ND: IND!$G$2:$G$3
Name ID_NDPD: IND!$K$2:$K$3
Name ID_NDTM: IND!$J$2:$J$3
Name ID_NDTY: IND!$I$2:$I$3
Name ID_NK: IND!$AG$2:$AG$51
Name ID_OTF: IND!$B$18:$B$19
Name ID_RG: IND!$O$2:$O$2
Name ID_RS: IND!$BA$2:$BA$6
Name ID_SIG: IND!$V$2:$V$50
Name ID_TM: IND!$BW$2:$BW$25
Name ID_TZD: IND!$CB$2:$CB$3
Name ID_WR: IND!$BR$2:$BR$2
Name ID_WRP: IND!$BT$2
Name ID_YR: IND!$BE$2:$BE$2
Name ID_YRD: IND!$BG$2:$BG$2
Name ID_YRD2: IND!$BH$2:$BH$2
Name IK: IK!$B$2:$C$7
Name IK_DK: IK_DK!$B$2:$C$8
Name IK_DKI: IK_DK!$H$4:$H$5
Name IK_DSD: IK_DK!$H$6:$H$7
Name IK_DSI: IK_DK!$G$6:$G$7
Name IK_EKD: IK_DK!$H$8:$H$10
Name IK_EKI: IK_DK!$G$8:$G$10
Name IK_MKD: IK_DK!$H$11:$H$13
Name IK_MKI: IK_DK!$G$11:$G$13
Name IKC: IK!$G$11:$K$11
Name IKD_1: IK!$G$12:$K$16
Name IKD_2: IK!$G$17:$K$21
Name IKF: IK!$G$6:$K$8

Sheet CASE
G3: AC_LM sheet | H3: LH2 | I3: MTS | J3: MTS2 | K3: AMS | L3: MCS | M3: NG_IS | N3: H2_IS | O3: LA_IS | P3: MC_IS | Q3: NGF | R3: H2F | S3: AMF | U3: NK_TP sheet
B4: Case | C4: 1 | H4: {=INDEX(H5:H10,$C$4)} -> 0 | I4: {=INDEX(I5:I10,$C$4)} -> -1 | J4: {=INDEX(J5:J10,$C$4)} -> 0 | K4: {=INDEX(K5:K10,$C$4)} -> 0 | L4: {=INDEX(L5:L10,$C$4)} -> 0 | M4: {=INDEX(M5:M10,$C$4)} -> -1 | N4: {=INDEX(N5:N10,$C$4)} -> 0 | O4: {=INDEX(O5:O10,$C$4)} -> 0 | ... S4: {=INDEX(S5:S10,$C$4)} -> 0 | U4: {=INDEX(U5:U10,$C$4)} -> 1
C5: 1: Synthetic methane (conv.) | G5: 1 | H5: 0 | I5: -1 | J5: 0 | K5: 0 | L5: 0 | M5: -1 | N5: 0 | O5: 0 | P5: 0 | Q5: -1 | R5: 0 | S5: 0 | U5: 1
C6: 2: LH2 | G6: 2 | H6: -1 | I6: 0 | J6: 0 | K6: 0 | L6: 0 | M6: 0 | N6: -1 | O6: 0 | P6: 0 | Q6: 0 | R6: -1 | S6: 0 | U6: 2
C7: 3: MCH | G7: 3 | H7: 0 | I7: 0 | J7: 0 | K7: -1 | L7: -1 | M7: 0 | N7: 0 | O7: 0 | P7: -1 | Q7: 0 | R7: -1 | S7: 0 | U7: 3
C8: 4: NH3 (cracking) | G8: 4 | H8: 0 | I8: 0 | J8: 0 | K8: -1 | L8: 0 | M8: 0 | N8: 0 | O8: -1 | P8: 0 | Q8: 0 | R8: -1 | S8: 0 | U8: 3
C9: 5: NH3 (direct consumption) | G9: 5 | H9: 0 | I9: 0 | J9: 0 | K9: -1 | L9: 0 | M9: 0 | N9: 0 | O9: -1 | P9: 0 | Q9: 0 | R9: 0 | S9: -1 | U9: 3
C10: 6: Synthetic methane (innov.) | G10: 6 | H10: 0 | I10: 0 | J10: -1 | K10: 0 | L10: 0 | M10: -1 | N10: 0 | O10: 0 | P10: 0 | Q10: -1 | R10: 0 | S10: 0 | U10: 1
B13: Emissions | C13: 0 | E13: Natural gas | F13: =IND!B25*FC!H13 -> 0.48045 | G13: tc/toe
C14: tC/toe
C15: ="-1: without constraint" -> -1: without constraint
B18: Grid electricity | C18: 0
C19: 0: without
C20: ="-1: with (importing country)" -> -1: with (importing country)

Sheet IND
A1: Node [ND] | B1: =ROWS(ID_ND) -> 2 | F1: =A1 -> Node [ND] | G1: Abb. | H1: ID | I1: Type | J1: Time zone | K1: Distance to port [km] | N1: =A2 -> Region [RG] | O1: Abb. | P1: ID | S1: =A3 -> Item [IT] | T1: Abb. | U1: ID | V1: Sign | W1: Mode | Z1: =A4 -> Activity [AC] | AA1: Abb. | AB1: ID | AC1: Mode | AF1: =A5 -> Nodal facility [NK] | AG1: Abb. | AH1: ID | AK1: =A6 -> Maritime trade facility [IK] | AL1: Abb. | AM1: ID | AP1: =A7 -> Land trade facility [IKL] | AQ1: Abb. | AR1: ID | AU1: Final consumption [FC] | AV1: Abb. | AW1: ID | AZ1: Resource [RS] | BA1: Abb. | BB1: ID | BE1: Year [YR] | BF1: ID | BG1: Duration | BH1: Number of years from the base year | BI1: Discount factor | BL1: Day [DY] | BM1: ID | BN1: Month | BR1: Weather [WE] | BS1: ID | BT1: Prob | BW1: Time [TM] | BX1: ID | CA1: Time zone ID | CB1: UTC zone
A2: Region [RG] | B2: =ROWS(ID_RG) -> 1 | F2: Export region | G2: EXP | H2: 0 | I2: 1 | J2: 1 | K2: 0 | N2: All | O2: ALL | P2: 1 | S2: Fuel cost | T2: FLC | U2: 0 | V2: G | W2: 0 | Z2: Direct Air Capture - Electricity (low temperature) | AA2: DACE1 | AB2: 0 | AC2: 2 | AF2: Direct Air Capture - Electricity (low temperature) | AG2: DACE1 | AH2: 0 | AK2: CO2 tanker | AL2: CXT | AM2: 0 | AP2: CO2 pipeline | AQ2: CXP | AR2: 0 | AU2: Fuel demand | AV2: SFF | AW2: 0 | AZ2: Hydro resource | BA2: HYR | BB2: 0 | BE2: YR2050 | BF2: 0 | BG2: 1 | BH2: 0 | BI2: 1 | BL2: DY1 | BM2: 0 | BN2: 0 | BR2: WR1 | BS2: 0 | BT2: 1 | BW2: TM1 | BX2: 0 | CA2: 0 | CB2: 0
A3: Item [IT] | B3: =ROWS(ID_IT) -> 49 | F3: Import region | G3: IMP | H3: =H2+1 -> 1 | I3: 1 | J3: 1 | K3: 0 | S3: Other variable cost | T3: OMC | U3: =U2+1 -> 1 | V3: G | W3: 0 | Z3: Direct Air Capture - Electricity (high temperature) | AA3: DACE2 | AB3: =AB2+1 -> 1 | AC3: 2 | AF3: Direct Air Capture - Electricity (high temperature) | AG3: DACE2 | AH3: =AH2+1 -> 1 | AK3: Methane gas tanker | AL3: LGT | AM3: =AM2+1 -> 1 | AP3: Methane gas pipeline | AQ3: NGP | AR3: =AR2+1 -> 1 | AZ3: Solar resource | BA3: SOR | BB3: =BB2+1 -> 1 | BL3: DY2 | BM3: =BM2+1 -> 1 | BN3: 0 | BW3: TM2 | BX3: =BX2+1 -> 1 | CA3: 1 | CB3: 9
A4: Activity [AC] | B4: =ROWS(ID_AC) -> 114 | S4: Saving penalty | T4: SVC | U4: =U3+1 -> 2 | V4: G | W4: 0 | Z4: CO2 liquefaction | AA4: CXL | AB4: =AB3+1 -> 2 | AC4: 2 | AF4: CO2 Liquefaction | AG4: CXL | AH4: =AH3+1 -> 2 | AK4: Hydrogen tanker | AL4: H2T | AM4: =AM3+1 -> 2 | AP4: Hydrogen pipeline | AQ4: H2P | AR4: =AR3+1 -> 2 | AZ4: Wind resource 1 (onshore) | BA4: WIR1 | BB4: =BB3+1 -> 2 | BE4: Discount rate | BL4: DY3 | BM4: =BM3+1 -> 2 | BN4: 0 | BW4: TM3 | BX4: =BX3+1 -> 2
A5: Nodal facility [NK] | B5: =ROWS(ID_NK) -> 50 | S5: Total electricity consumption | T5: TEC | U5: =U4+1 -> 3 | V5: N | W5: 2 | Z5: CO2 regasification | AA5: CXV | AB5: =AB4+1 -> 3 | AC5: 2 | AF5: Methane gas liquefaction | AG5: NGL | AH5: =AH4+1 -> 3 | AK5: Liquefied ammonia tanker | AL5: LAT | AM5: =AM4+1 -> 3 | AP5: HVAC line | AQ5: HVA | AR5: =AR4+1 -> 3 | AZ5: Wind resource 2 (offshore) | BA5: WIR2 | BB5: =BB4+1 -> 3 | BE5: 0.08 | BL5: DY4 | BM5: =BM4+1 -> 3 | BN5: 0 | BW5: TM4 | BX5: =BX4+1 -> 3
A6: Maritime trade facility [IK] | B6: =ROWS(ID_IK) -> 5 | S6: Emitted CO2 into atmosphere | T6: CO2 | U6: =U5+1 -> 4 | V6: N | W6: 0 | Z6: Methane gas liquefaction | AA6: NGL | AB6: =AB5+1 -> 4 | AC6: 2 | AF6: Methane gas rregasification | AG6: NGV | AH6: =AH5+1 -> 4 | AK6: MCH tanker | AL6: MCT | AM6: =AM5+1 -> 4 | AZ6: Fuel demand saving potential | BA6: SSV1 | BB6: =BB5+1 -> 4 | BL6: DY5 | BM6: =BM5+1 -> 4 | BN6: 0 | BW6: TM5 | BX6: =BX5+1 -> 4
A7: Land trade facility [IKL] | B7: =ROWS(ID_IKL) -> 4 | S7: CO2 emission from biomass-fired power plants | T7: CEPBD | U7: =U6+1 -> 5 | V7: G | W7: 2 | Z7: Methane gas regasification | AA7: NGV | AB7: =AB6+1 -> 5 | AC7: 2 | AF7: Methane storage | AG7: NGS | AH7: =AH6+1 -> 5 | BL7: DY6 | BM7: =BM6+1 -> 5 | BN7: 0 | BW7: TM6 | BX7: =BX6+1 -> 5
A8: Final consumption [FC] | B8: =ROWS(ID_FC) -> 1 | S8: CO2 recovered | T8: CRV | U8: =U7+1 -> 6 | V8: G | W8: 2 | Z8: Methane charge | AA8: NCH | AB8: =AB7+1 -> 6 | AC8: 2 | AF8: Methane storage tank | AG8: NGT | AH8: =AH7+1 -> 6 | BL8: DY7 | BM8: =BM7+1 -> 6 | BN8: 0 | BW8: TM7 | BX8: =BX7+1 -> 6
A9: Resource [RS] | B9: =ROWS(ID_RS) -> 5 | S9: Liquefied CO2 | T9: LCO | U9: =U8+1 -> 7 | V9: G | W9: 2 | Z9: Methane discharge | AA9: NDC | AB9: =AB8+1 -> 7 | AC9: 2 | AF9: Liquefied methane storage | AG9: LNGS | AH9: =AH8+1 -> 7 | BL9: DY8 | BM9: =BM8+1 -> 7 | BN9: 0 | BW9: TM8 | BX9: =BX8+1 -> 7
A10: Year [YR] | B10: =ROWS(ID_YR) -> 1 | S10: Methane | T10: MTN | U10: =U9+1 -> 8 | V10: E | W10: 2 | Z10: Methane charge/discharge activity | AA10: NSA | AB10: =AB9+1 -> 8 | AC10: 2 | AF10: Liquefied methane storage tank | AG10: LNGT | AH10: =AH9+1 -> 8 | BL10: DY9 | BM10: =BM9+1 -> 8 | BN10: 0 | BW10: TM9 | BX10: =BX9+1 -> 8
A11: Day [DY] | B11: =ROWS(ID_DY) -> 365 | S11: Methane storage | T11: NSE | U11: =U10+1 -> 9 | V11: E | W11: 2 | Z11: Methane storage at t-1 | AA11: NS1 | AB11: =AB10+1 -> 9 | AC11: 2 | AF11: Gas turbine power plant | AG11: GTG | AH11: =AH10+1 -> 9 | BL11: DY10 | BM11: =BM10+1 -> 9 | BN11: 0 | BW11: TM10 | BX11: =BX10+1 -> 9
A12: Month [MN] | B12: =MAX(ID_DM)+1 -> 37 | S12: Charge/discharge for CH4 storage | T12: NCD | U12: =U11+1 -> 10 | V12: E | W12: 2 | Z12: Methane storage at t | AA12: NS2 | AB12: =AB11+1 -> 10 | AC12: 2 | AF12: Hydro power plant | AG12: HYG | AH12: =AH11+1 -> 10 | BL12: DY11 | BM12: =BM11+1 -> 10 | BN12: 1 | BW12: TM11 | BX12: =BX11+1 -> 10
A13: Weather [WE] | B13: =ROWS(ID_WR) -> 1 | S13: Liquefied methane gas | T13: LNG | U13: =U12+1 -> 11 | V13: E | W13: 2 | Z13: Liquefied methane charge | AA13: LNCH | AB13: =AB12+1 -> 11 | AC13: 2 | AF13: Solar photovoltaics | AG13: SPG | AH13: =AH12+1 -> 11 | BL13: DY12 | BM13: =BM12+1 -> 11 | BN13: 1 | BW13: TM12 | BX13: =BX12+1 -> 11
A14: Time [TM] | B14: =ROWS(ID_TM) -> 24 | S14: Liquefied methane storage | T14: LNSE | U14: =U13+1 -> 12 | V14: E | W14: 2 | Z14: Liquefied methane discharge | AA14: LNDC | AB14: =AB13+1 -> 12 | AC14: 2 | AF14: Wind power 1 (onshore) | AG14: WIG1 | AH14: =AH13+1 -> 12 | BL14: DY13 | BM14: =BM13+1 -> 12 | BN14: 1 | BW14: TM13 | BX14: =BX13+1 -> 12
A15: Time zone [TZD] | B15: =ROWS(ID_TZD) -> 2 | S15: Charge/discharge for LCH4 storage | T15: LNCD | U15: =U14+1 -> 13 | V15: E | W15: 2 | Z15: Liquefied methane charge/discharge activity | AA15: LNSA | AB15: =AB14+1 -> 13 | AC15: 2 | AF15: Wind power 2 (offshore) | AG15: WIG2 | AH15: =AH14+1 -> 13 | BL15: DY14 | BM15: =BM14+1 -> 13 | BN15: 1 | BW15: TM14 | BX15: =BX14+1 -> 13
A16: # of item 2 | B16: =COUNTIF(ID_ITM,2) -> 33 | S16: Liquefied methane gas (loaded on the tanker) | T16: LNG2 | U16: =U15+1 -> 14 | V16: E | W16: 0 | Z16: Liquefied methane storage at t-1 | AA16: LNS1 | AB16: =AB15+1 -> 14 | AC16: 2 | AF16: Biomass direct fired power plant | AG16: BDG | AH16: =AH15+1 -> 14 | BL16: DY15 | BM16: =BM15+1 -> 14 | BN16: 1 | BW16: TM15 | BX16: =BX15+1 -> 14
A17: # of activity 2 | B17: =COUNTIF(ID_ACM,2) -> 94 | S17: Hydro power resource | T17: HYR | U17: =U16+1 -> 15 | V17: G | W17: 0 | Z17: Liquefied methane storage at t | AA17: LNS2 | AB17: =AB16+1 -> 15 | AC17: 2 | AF17: Light water reactor | AG17: LWR | AH17: =AH16+1 -> 15 | BL17: DY16 | BM17: =BM16+1 -> 15 | BN17: 1 | BW17: TM16 | BX17: =BX16+1 -> 15
A18: Output file column1 | B18: =SUBSTITUTE(ADDRESS(1,B10*(B56+B3)+1,4),"1","") -> BJ | S18: Solar power resource | T18: SOR | U18: =U17+1 -> 16 | V18: G | W18: 0 | Z18: Liquefied methane loading | AA18: LNLD | AB18: =AB17+1 -> 16 | AC18: 2 | AF18: Battery storage 1 | AG18: PPS | AH18: =AH17+1 -> 16 | BL18: DY17 | BM18: =BM17+1 -> 16 | BN18: 1 | BW18: TM17 | BX18: =BX17+1 -> 16
A19: Output file column2 | B19: =SUBSTITUTE(ADDRESS(1,B11*B13*B14+2,4),"1","") -> LXZ | S19: Wind power resource 1 (onshore) | T19: WIR1 | U19: =U18+1 -> 17 | V19: G | W19: 0 | Z19: Liquefied methane unloading | AA19: LNUL | AB19: =AB18+1 -> 17 | AC19: 2 | AF19: Battery storage 2 | AG19: BTSS | AH19: =AH18+1 -> 17 | BL19: DY18 | BM19: =BM18+1 -> 17 | BN19: 1 | BW19: TM18 | BX19: =BX18+1 -> 17
S20: Wind power resource 2 (offshore) | T20: WIR2 | U20: =U19+1 -> 18 | V20: G | W20: 0 | Z20: Grid electricity procurement | AA20: GELP | AB20: =AB19+1 -> 18 | AC20: 2 | AF20: Battery storage 3 | AG20: BTSL | AH20: =AH19+1 -> 18 | BL20: DY19 | BM20: =BM19+1 -> 18 | BN20: 1 | BW20: TM19 | BX20: =BX19+1 -> 18
S21: Biomass for direct fired power and/or heat generation | T21: BDG | U21: =U20+1 -> 19 | V21: G | W21: 0 | Z21: Natural gas procurement | AA21: NGSP | AB21: =AB20+1 -> 19 | AC21: 2 | AF21: Electrolyzer | AG21: WEL | AH21: =AH20+1 -> 19 | BL21: DY20 | BM21: =BM20+1 -> 19 | BN21: 1 | BW21: TM20 | BX21: =BX20+1 -> 19
S22: Electricity | T22: ELC | U22: =U21+1 -> 20 | V22: E | W22: 2 | Z22: Fuel oil procurement (for seaborne transportation) | AA22: FOLP | AB22: =AB21+1 -> 20 | AC22: 0 | AF22: Hydrogen storage | AG22: H2S | AH22: =AH21+1 -> 20 | BL22: DY21 | BM22: =BM21+1 -> 20 | BN22: 2 | BW22: TM21 | BX22: =BX21+1 -> 20
A23: Carbon content [t-C/toe] | S23: Stored electricity at battery 1 | T23: PSE | U23: =U22+1 -> 21 | V23: E | W23: 2 | Z23: Ammonia procurement (for seaborne transportation) | AA23: AMMP | AB23: =AB22+1 -> 21 | AC23: 0 | AF23: Hydrogen storage tank | AG23: H2T | AH23: =AH22+1 -> 21 | BL23: DY22 | BM23: =BM22+1 -> 21 | BN23: 2 | BW23: TM22 | BX23: =BX22+1 -> 21
A24: Coal | B24: 1.0802 | S24: Charge/discharge at battery 1 | T24: PCD | U24: =U23+1 -> 22 | V24: E | W24: 2 | Z24: Gas turbine power generation | AA24: GTG | AB24: =AB23+1 -> 22 | AC24: 2 | AF24: Liquefied hydrogen storage | AG24: LH2S | AH24: =AH23+1 -> 22 | BL24: DY23 | BM24: =BM23+1 -> 22 | BN24: 2 | BW24: TM23 | BX24: =BX23+1 -> 22
A25: Methane | B25: 0.6406 | S25: Stored electricity at battery 2 | T25: BSES | U25: =U24+1 -> 23 | V25: E | W25: 2 | Z25: Hydro power generation | AA25: HYG | AB25: =AB24+1 -> 23 | AC25: 2 | AF25: Liquefied hydrogen storage tank | AG25: LH2T | AH25: =AH24+1 -> 23 | BL25: DY24 | BM25: =BM24+1 -> 23 | BN25: 2 | BW25: TM24 | BX25: =BX24+1 -> 23
A26: Crude oil | B26: 0.8374 | S26: Charge/discharge at battery 2 | T26: BCDS | U26: =U25+1 -> 24 | V26: E | W26: 2 | Z26: Suppressed hydro | AA26: HYD | AB26: =AB25+1 -> 24 | AC26: 2 | AF26: Hydrogen Liquefaction | AG26: H2L | AH26: =AH25+1 -> 24 | BL26: DY25 | BM26: =BM25+1 -> 24 | BN26: 2
A27: Gasoline | B27: =69.3*12/44/0.0000238845897/10^6 -> 0.7913052 | S27: Stored electricity at battery 3 | T27: BSEL | U27: =U26+1 -> 25 | V27: E | W27: 2 | Z27: Solar photovoltaics power generation | AA27: SPG | AB27: =AB26+1 -> 25 | AC27: 2 | AF27: Hydrogen Regasification | AG27: H2V | AH27: =AH26+1 -> 25 | BL27: DY26 | BM27: =BM26+1 -> 25 | BN27: 2
A28: Diesel | B28: =67.8*12/44/0.0000238845897/10^6 -> 0.77417738 | S28: Charge/discharge at battery 3 | T28: BCDL | U28: =U27+1 -> 26 | V28: E | W28: 2 | Z28: Suppressed PV | AA28: SPD | AB28: =AB27+1 -> 26 | AC28: 2 | AF28: Methane synthesis | AG28: MTS | AH28: =AH27+1 -> 26 | BL28: DY27 | BM28: =BM27+1 -> 26 | BN28: 2
A29: Other oil products | S29: Non-synchronous electricity | T29: NSC | U29: =U28+1 -> 27 | V29: CL | W29: 2 | Z29: Wind power generation 1 (onshore) | AA29: WIG1 | AB29: =AB28+1 -> 27 | AC29: 2 | AF29: Methane synthesis 2 - high efficiency | AG29: MTS2 | AH29: =AH28+1 -> 27 | BL29: DY28 | BM29: =BM28+1 -> 27 | BN29: 2
A30: Biomass | B30: 1.124 | S30: Hydrogen | T30: HYN | U30: =U29+1 -> 28 | V30: E | W30: 2 | Z30: Wind power generation 2 (offshore) | AA30: WIG2 | AB30: =AB29+1 -> 28 | AC30: 2 | AF30: Ammonia synthesis | AG30: AMS | AH30: =AH29+1 -> 28 | BL30: DY29 | BM30: =BM29+1 -> 28 | BN30: 2
A31: Methanol | B31: 0.7866 | S31: Liquefied hydrogen | T31: LHY | U31: =U30+1 -> 29 | V31: E | W31: 2 | Z31: Suppressed wind 1 | AA31: WID1 | AB31: =AB30+1 -> 29 | AC31: 2 | AF31: Hydrogen separation | AG31: HSP | AH31: =AH30+1 -> 29 | BL31: DY30 | BM31: =BM30+1 -> 29 | BN31: 2
S32: Liquefied hydrogen (loaded on the tanker) | T32: LHY2 | U32: =U31+1 -> 30 | V32: E | W32: 0 | Z32: Suppressed wind 2 | AA32: WID2 | AB32: =AB31+1 -> 30 | AC32: 2 | AF32: Ammonia storage | AG32: AMMS | AH32: =AH31+1 -> 30 | BL32: DY31 | BM32: =BM31+1 -> 30 | BN32: 3
S33: Hydrogen storage | T33: HSE | U33: =U32+1 -> 31 | V33: E | W33: 2 | Z33: Biomass direct fired power generation | AA33: BDG | AB33: =AB32+1 -> 31 | AC33: 2 | AF33: Ammonia storage tank | AG33: AMMT | AH33: =AH32+1 -> 31 | BL33: DY32 | BM33: =BM32+1 -> 31 | BN33: 3
A34: Case | S34: Charge/discharge for H2 storage | T34: HCD | U34: =U33+1 -> 32 | V34: E | W34: 2 | Z34: Light water reactor power generation | AA34: LWR | AB34: =AB33+1 -> 32 | AC34: 2 | AF34: Hydrogenation of toluene | AG34: MCS | AH34: =AH33+1 -> 32 | BL34: DY33 | BM34: =BM33+1 -> 32 | BN34: 3
A35: Max. share of non-synchronous generation | S35: LH2 storage | T35: LHSE | U35: =U34+1 -> 33 | V35: E | W35: 2 | Z35: Battery charge 1 | AA35: PCH | AB35: =AB34+1 -> 33 | AC35: 2 | AF35: Dehydrogenation (MCH) | AG35: DHG | AH35: =AH34+1 -> 33 | BL35: DY34 | BM35: =BM34+1 -> 33 | BN35: 3
A36: PV+Wind+NetImp(DC)+NetDcha | S36: Charge/discharge for LH2 storage | T36: LHCD | U36: =U35+1 -> 34 | V36: E | W36: 2 | Z36: Battery discharge 1 | AA36: PDC | AB36: =AB35+1 -> 34 | AC36: 2 | AF36: MCH storage | AG36: MCHS | AH36: =AH35+1 -> 34 | BL36: DY35 | BM36: =BM35+1 -> 34 | BN36: 3
A37: ="no constraint=-1" -> no constraint=-1 | B37: -1 | S37: Ammonia | T37: AMM | U37: =U36+1 -> 35 | V37: E | W37: 2 | Z37: Battery 1 charge/discharge activity | AA37: PSA | AB37: =AB36+1 -> 35 | AC37: 2 | AF37: MCH storage tank | AG37: MCHT | AH37: =AH36+1 -> 35 | BL37: DY36 | BM37: =BM36+1 -> 35 | BN37: 3
S38: Ammonia (loaded on the tanker) | T38: AMM2 | U38: =U37+1 -> 36 | V38: E | W38: 0 | Z38: Battery 1 storage at t-1 | AA38: PS1 | AB38: =AB37+1 -> 36 | AC38: 2 | AF38: Gas boiler | AG38: GBL | AH38: =AH37+1 -> 36 | BL38: DY37 | BM38: =BM37+1 -> 36 | BN38: 3
S39: Ammonia storage | T39: AMSE | U39: =U38+1 -> 37 | V39: E | W39: 2 | Z39: Battery 1 storage at t | AA39: PS2 | AB39: =AB38+1 -> 37 | AC39: 2 | AF39: Ammonia boiler | AG39: ABL | AH39: =AH38+1 -> 37 | BL39: DY38 | BM39: =BM38+1 -> 37 | BN39: 3
S40: Charge/discharge for NH3 storage | T40: AMCD | U40: =U39+1 -> 38 | V40: E | W40: 2 | Z40: Battery 2 charge | AA40: BCHS | AB40: =AB39+1 -> 38 | AC40: 2 | AF40: Hydrogen boiler | AG40: HBL | AH40: =AH39+1 -> 38 | BL40: DY39 | BM40: =BM39+1 -> 38 | BN40: 3
S41: Toluene | T41: TOL | U41: =U40+1 -> 39 | V41: G | W41: 0 | Z41: Battery 2 discharge | AA41: BDCS | AB41: =AB40+1 -> 39 | AC41: 2 | AF41: Heat pump | AG41: HPP | AH41: =AH40+1 -> 39 | BL41: DY40 | BM41: =BM40+1 -> 39 | BN41: 3
S42: Methylcyclohexane | T42: MCH | U42: =U41+1 -> 40 | V42: E | W42: 2 | Z42: Battery 2 charge/discharge activity | AA42: BSAS | AB42: =AB41+1 -> 40 | AC42: 2 | AF42: Hydrogen carrier loading for tankers | AG42: HCLD | AH42: =AH41+1 -> 40 | BL42: DY41 | BM42: =BM41+1 -> 40 | BN42: 4
S43: Methylcyclohexane (loaded on the tanker) | T43: MCH2 | U43: =U42+1 -> 41 | V43: E | W43: 0 | Z43: Battery 2 storage at t-1 | AA43: BS1S | AB43: =AB42+1 -> 41 | AC43: 2 | AF43: Hydrogen carrier unloading for tankers | AG43: HCUL | AH43: =AH42+1 -> 41 | BL43: DY42 | BM43: =BM42+1 -> 41 | BN43: 4
S44: MCH storage | T44: MCSE | U44: =U43+1 -> 42 | V44: E | W44: 2 | Z44: Battery 2 storage at t | AA44: BS2S | AB44: =AB43+1 -> 42 | AC44: 2 | AF44: Liquefied methane gas import terminal facilities (port) | AG44: NG_IS | AH44: =AH43+1 -> 42 | BL44: DY43 | BM44: =BM43+1 -> 42 | BN44: 4
S45: Charge/discharge for MCH storage | T45: MCCD | U45: =U44+1 -> 43 | V45: E | W45: 2 | Z45: Battery 3 charge | AA45: BCHL | AB45: =AB44+1 -> 43 | AC45: 2 | AF45: Liquefied methane gas export terminal facilities (port) | AG45: NG_ES | AH45: =AH44+1 -> 43 | BL45: DY44 | BM45: =BM44+1 -> 43 | BN45: 4
S46: Heat | T46: HEA | U46: =U45+1 -> 44 | V46: G | W46: 0 | Z46: Battery 3 discharge | AA46: BDCL | AB46: =AB45+1 -> 44 | AC46: 2 | AF46: LH2 import terminal facilities (port) | AG46: H2_IS | AH46: =AH45+1 -> 44 | BL46: DY45 | BM46: =BM45+1 -> 44 | BN46: 4
S47: Low temperature heat | T47: LTH | U47: =U46+1 -> 45 | V47: G | W47: 2 | Z47: Battery 3 charge/discharge activity | AA47: BSAL | AB47: =AB46+1 -> 45 | AC47: 2 | AF47: LH2 export terminal facilities (port) | AG47: H2_ES | AH47: =AH46+1 -> 45 | BL47: DY46 | BM47: =BM46+1 -> 45 | BN47: 4
S48: Fuel for seaborne transportation | T48: FSBT | U48: =U47+1 -> 46 | V48: G | W48: 0 | Z48: Battery 3 storage at t-1 | AA48: BS1L | AB48: =AB47+1 -> 46 | AC48: 2 | AF48: Liquefied ammonia import terminal facilities (port) | AG48: LA_IS | AH48: =AH47+1 -> 46 | BL48: DY47 | BM48: =BM47+1 -> 46 | BN48: 4
S49: Fuel demand saving potential 1 | T49: SSV1 | U49: =U48+1 -> 47 | V49: E | W49: 2 | Z49: Battery 3 storage at t | AA49: BS2L | AB49: =AB48+1 -> 47 | AC49: 2 | AF49: Liquefied ammonia export terminal facilities (port) | AG49: LA_ES | AH49: =AH48+1 -> 47 | BL49: DY48 | BM49: =BM48+1 -> 47 | BN49: 4
S50: Final fuel demand | T50: SFF | U50: =U49+1 -> 48 | V50: G | W50: 2 | Z50: Water electrolysis | AA50: WEL | AB50: =AB49+1 -> 48 | AC50: 2 | AF50: MCH import terminal facilities (port) | AG50: MC_IS | AH50: =AH49+1 -> 48 | BL50: DY49 | BM50: =BM49+1 -> 48 | BN50: 4
Z51: Hydrogen charge | AA51: HCH | AB51: =AB50+1 -> 49 | AC51: 2 | AF51: MCH export terminal facilities (port) | AG51: MC_ES | AH51: =AH50+1 -> 49 | BL51: DY50 | BM51: =BM50+1 -> 49 | BN51: 4
Z52: Hydrogen discharge | AA52: HDC | AB52: =AB51+1 -> 50 | AC52: 2 | BL52: DY51 | BM52: =BM51+1 -> 50 | BN52: 5
Z53: Hydeogen charge/discharge activity | AA53: HSA | AB53: =AB52+1 -> 51 | AC53: 2 | BL53: DY52 | BM53: =BM52+1 -> 51 | BN53: 5
Z54: Hydrogen storage at t-1 | AA54: HS1 | AB54: =AB53+1 -> 52 | AC54: 2 | BL54: DY53 | BM54: =BM53+1 -> 52 | BN54: 5
A55: Output file | Z55: Hydrogen storage at t | AA55: HS2 | AB55: =AB54+1 -> 53 | AC55: 2 | BL55: DY54 | BM55: =BM54+1 -> 53 | BN55: 5
A56: OTH | B56: 12 | Z56: Liquefied hydrogen charge | AA56: LHCH | AB56: =AB55+1 -> 54 | AC56: 2 | BL56: DY55 | BM56: =BM55+1 -> 54 | BN56: 5
B57: 0.. | C57: 0.. | Z57: Liquefied hydrogen discharge | AA57: LHDC | AB57: =AB56+1 -> 55 | AC57: 2 | BL57: DY56 | BM57: =BM56+1 -> 55 | BN57: 5
A58: R_Z0 | B58: =B1+B2-1 -> 2 | C58: =B10*(B56+B3)-1 -> 60 | Z58: Liquefied hydeogen charge/discharge activity | AA58: LHSA | AB58: =AB57+1 -> 56 | AC58: 2 | BL58: DY57 | BM58: =BM57+1 -> 56 | BN58: 5
A59: R_AC | B59: =B10*B4*(B1+B2)-1 -> 341 | C59: =B11*B13*B14 -> 8760 | Z59: Liquefied hydrogen storage at t-1 | AA59: LHS1 | AB59: =AB58+1 -> 57 | AC59: 2 | BL59: DY58 | BM59: =BM58+1 -> 57 | BN59: 5
A60: R_NK | B60: =B10*B5*(B1+B2)-1 -> 149 | Z60: Liquefied hydrogen storage at t | AA60: LHS2 | AB60: =AB59+1 -> 58 | AC60: 2 | BL60: DY59 | BM60: =BM59+1 -> 58 | BN60: 5
A61: R_IR1 | B61: =B10*B6*IK_DK!C2-1 -> 4 | Z61: Hydrogen Liquefaction | AA61: H2L | AB61: =AB60+1 -> 59 | AC61: 2 | BL61: DY60 | BM61: =BM60+1 -> 59 | BN61: 5
A62: R_IR2 | B62: =B10*B7*IKL_DK!C2-1 -> 3 | Z62: Hydrogen Regasification | AA62: H2V | AB62: =AB61+1 -> 60 | AC62: 2 | BL62: DY61 | BM62: =BM61+1 -> 60 | BN62: 6
Z63: Liquefied hydrogen loading | AA63: LHLD | AB63: =AB62+1 -> 61 | AC63: 2 | BL63: DY62 | BM63: =BM62+1 -> 61 | BN63: 6
A64: R_Z0_Dual | B64: =B10*B3*B1-1 -> 97 | C64: =C59 -> 8760 | Z64: Liquefied hydrogen unloading | AA64: LHUL | AB64: =AB63+1 -> 62 | AC64: 2 | BL64: DY63 | BM64: =BM63+1 -> 62 | BN64: 6
Z65: Methane synthesis | AA65: MTS | AB65: =AB64+1 -> 63 | AC65: 2 | BL65: DY64 | BM65: =BM64+1 -> 63 | BN65: 6
Z66: Methane synthesis 2 | AA66: MTS2 | AB66: =AB65+1 -> 64 | AC66: 2 | BL66: DY65 | BM66: =BM65+1 -> 64 | BN66: 6
Z67: Ammonia synthesis | AA67: AMS | AB67: =AB66+1 -> 65 | AC67: 2 | BL67: DY66 | BM67: =BM66+1 -> 65 | BN67: 6
Z68: Hydrogen separation | AA68: HSP | AB68: =AB67+1 -> 66 | AC68: 2 | BL68: DY67 | BM68: =BM67+1 -> 66 | BN68: 6
Z69: Ammonia charge | AA69: AMCH | AB69: =AB68+1 -> 67 | AC69: 2 | BL69: DY68 | BM69: =BM68+1 -> 67 | BN69: 6
Z70: Ammonia discharge | AA70: AMDC | AB70: =AB69+1 -> 68 | AC70: 2 | BL70: DY69 | BM70: =BM69+1 -> 68 | BN70: 6
Z71: Ammonia charge/discharge activity | AA71: AMSA | AB71: =AB70+1 -> 69 | AC71: 2 | BL71: DY70 | BM71: =BM70+1 -> 69 | BN71: 6
Z72: Ammonia storage at t-1 | AA72: AMS1 | AB72: =AB71+1 -> 70 | AC72: 2 | BL72: DY71 | BM72: =BM71+1 -> 70 | BN72: 7
Z73: Ammonia storage at t | AA73: AMS2 | AB73: =AB72+1 -> 71 | AC73: 2 | BL73: DY72 | BM73: =BM72+1 -> 71 | BN73: 7
Z74: Ammonia loading | AA74: AMLD | AB74: =AB73+1 -> 72 | AC74: 2 | BL74: DY73 | BM74: =BM73+1 -> 72 | BN74: 7
Z75: Ammonia unloading | AA75: AMUL | AB75: =AB74+1 -> 73 | AC75: 2 | BL75: DY74 | BM75: =BM74+1 -> 73 | BN75: 7
Z76: Hydrogenation of toluene | AA76: MCS | AB76: =AB75+1 -> 74 | AC76: 2 | AY76: X | BL76: DY75 | BM76: =BM75+1 -> 74 | BN76: 7
Z77: Dehydrogenation (MCH) | AA77: DHG | AB77: =AB76+1 -> 75 | AC77: 2 | AY77: X | BL77: DY76 | BM77: =BM76+1 -> 75 | BN77: 7
Z78: MCH charge | AA78: MCCH | AB78: =AB77+1 -> 76 | AC78: 2 | BL78: DY77 | BM78: =BM77+1 -> 76 | BN78: 7
Z79: MCH discharge | AA79: MCDC | AB79: =AB78+1 -> 77 | AC79: 2 | BL79: DY78 | BM79: =BM78+1 -> 77 | BN79: 7
Z80: MCH charge/discharge activity | AA80: MCSA | AB80: =AB79+1 -> 78 | AC80: 2 | BL80: DY79 | BM80: =BM79+1 -> 78 | BN80: 7
Z81: MCH storage at t-1 | AA81: MCS1 | AB81: =AB80+1 -> 79 | AC81: 2 | BL81: DY80 | BM81: =BM80+1 -> 79 | BN81: 7
Z82: MCH storage at t | AA82: MCS2 | AB82: =AB81+1 -> 80 | AC82: 2 | BL82: DY81 | BM82: =BM81+1 -> 80 | BN82: 8
Z83: MCH loading | AA83: MCLD | AB83: =AB82+1 -> 81 | AC83: 2 | BL83: DY82 | BM83: =BM82+1 -> 81 | BN83: 8
Z84: MCH unloading | AA84: MCUL | AB84: =AB83+1 -> 82 | AC84: 2 | BL84: DY83 | BM84: =BM83+1 -> 82 | BN84: 8
Z85: Gas boiler | AA85: GBL | AB85: =AB84+1 -> 83 | AC85: 2 | BL85: DY84 | BM85: =BM84+1 -> 83 | BN85: 8
Z86: Ammonia boiler | AA86: ABL | AB86: =AB85+1 -> 84 | AC86: 2 | BL86: DY85 | BM86: =BM85+1 -> 84 | BN86: 8
Z87: Hydrogen boiler | AA87: HBL | AB87: =AB86+1 -> 85 | AC87: 2 | BL87: DY86 | BM87: =BM86+1 -> 85 | BN87: 8
Z88: Heat pump | AA88: HPP | AB88: =AB87+1 -> 86 | AC88: 2 | BL88: DY87 | BM88: =BM87+1 -> 86 | BN88: 8
Z89: Total fuel demand saving | AA89: SSV | AB89: =AB88+1 -> 87 | AC89: 0 | BL89: DY88 | BM89: =BM88+1 -> 87 | BN89: 8
... Z115: Methane gas loss through transportation (pipeline) | AA115: NG_LLS | AB115: =AB114+1 -> 113 | AC115: 0 | BL115: DY114 | BM115: =BM114+1 -> 113 | BN115: 11
BL116: DY115 | BM116: =BM115+1 -> 114 | BN116: 11
BL117: DY116 | BM117: =BM116+1 -> 115 | BN117: 11
BL118: DY117 | BM118: =BM117+1 -> 116 | BN118: 11
BL119: DY118 | BM119: =BM118+1 -> 117 | BN119: 11
BL120: DY119 | BM120: =BM119+1 -> 118 | BN120: 11
BL121: DY120 | BM121: =BM120+1 -> 119 | BN121: 11
BL122: DY121 | BM122: =BM121+1 -> 120 | BN122: 12
BL123: DY122 | BM123: =BM122+1 -> 121 | BN123: 12
BL124: DY123 | BM124: =BM123+1 -> 122 | BN124: 12
BL125: DY124 | BM125: =BM124+1 -> 123 | BN125: 12
...

Sheet RG
A1: =IND!A2 -> Region [RG] | B1: RGD | C1: 1
A2: =ROWS(RGD) -> 2 | B2: =COLUMNS(RGD) -> 1 | C2: =INDEX(ID_RG,C1) -> ALL | D2: For IK_DK sheet
A3: 1 | B3: =INDEX(ID_ND,A3) -> EXP | C3: 1 | D3: =IFERROR(MATCH(1,C3:C3),"") -> 1
A4: =A3+1 -> 2 | B4: =INDEX(ID_ND,A4) -> IMP | C4: 1 | D4: =IFERROR(MATCH(1,C4:C4),"") -> 1

Sheet EMI
A1: Emission constraint [RGE] | D1: 1 | I1: Carbon price [Ctax] $/t-C
A2: =ROWS(RGE_D) -> 1 | B2: =COLUMNS(RGE_D) -> 1 | D2: =INDEX(ID_YR,D1) -> YR2050 | K2: =D2 -> YR2050
A3: 1 | B3: Case 1 | C3: =INDEX(ID_RG,A3) -> ALL | D3: =IF(CASE!C13=-1,-1,CASE!C13) -> 0 | I3: =B3 -> Case 1 | J3: =C3 -> ALL | K3: -1
Q66: YR2070
Q67: =#REF!+(#REF!-#REF!) -> #REF!
Q68: =#REF!*Q67/#REF! -> #REF!
Q69: =Q67-Q68 -> #REF!
Q70: =#REF!+(#REF!-#REF!) -> #REF!
Q71: =Q69+Q70 -> #REF!
Q72: =#REF!*Q71/#REF! -> #REF!
Q73: =Q70-Q72 -> #REF!

Sheet AC
B1: Row | C1: Column | F1: =IND!A4 -> Activity [AC] | H1: DACE1 | I1: DACE2 | J1: CXL | K1: CXV | L1: NGL | M1: NGV | N1: NCH | O1: NDC | P1: NSA | Q1: NS1 | R1: NS2 | S1: LNCH | T1: LNDC | U1: LNSA | V1: LNS1 | W1: LNS2 | X1: LNLD | Y1: LNUL | Z1: GELP | AA1: NGSP | AB1: FOLP | AC1: AMMP | AD1: GTG | AE1: HYG | AF1: HYD | AG1: SPG | AH1: SPD | AI1: WIG1 | AJ1: WIG2 | AK1: WID1 | AL1: WID2 | AM1: BDG | AN1: LWR | AO1: PCH | AP1: PDC | AQ1: PSA | AR1: PS1 | AS1: PS2 | AT1: BCHS | AU1: BDCS | AV1: BSAS | AW1: BS1S | AX1: BS2S | AY1: BCHL | AZ1: BDCL | BA1: BSAL | BB1: BS1L | BC1: BS2L | BD1: WEL | BE1: HCH | BF1: HDC | BG1: HSA | BH1: HS1 | BI1: HS2 | BJ1: LHCH | BK1: LHDC | BL1: LHSA | BM1: LHS1 | BN1: LHS2 | BO1: H2L | BP1: H2V | BQ1: LHLD | BR1: LHUL | BS1: MTS | BT1: MTS2 | BU1: AMS | BV1: HSP | BW1: AMCH | BX1: AMDC | BY1: AMSA | BZ1: AMS1 | CA1: AMS2 | CB1: AMLD | CC1: AMUL | CD1: MCS | CE1: DHG | CF1: MCCH | CG1: MCDC | CH1: MCSA | CI1: MCS1 | CJ1: MCS2 | CK1: MCLD | CL1: MCUL | CM1: GBL | CN1: ABL | CO1: HBL | CP1: HPP | CQ1: SSV | CR1: SSV1 | CS1: NGF | CT1: H2F | CU1: AMF | CV1: CX_IS | CW1: CX_ES | CX1: CX_IL | CY1: CX_EL | CZ1: NG_IS | DA1: NG_ES | DB1: NG_IL | DC1: NG_EL | DD1: H2_IS | DE1: H2_ES | DF1: H2_IL | DG1: H2_EL | DH1: LA_IS | DI1: LA_ES | DJ1: MC_IS | DK1: MC_ES | DL1: EL_IA | DM1: EL_EA | DN1: CX_SLS | DO1: CX_LLS | DP1: NG_SLS | DQ1: NG_LLS
A2: ACI | B2: =ROWS(ACI) -> 1 | C2: =COLUMNS(ACI) -> 114 | F2: ID | H2: =MATCH(H1,ID_AC,0)-1 -> 0 | I2: =MATCH(I1,ID_AC,0)-1 -> 1 | J2: =MATCH(J1,ID_AC,0)-1 -> 2 | K2: =MATCH(K1,ID_AC,0)-1 -> 3 | L2: =MATCH(L1,ID_AC,0)-1 -> 4 | M2: =MATCH(M1,ID_AC,0)-1 -> 5 | N2: =MATCH(N1,ID_AC,0)-1 -> 6 | O2: =MATCH(O1,ID_AC,0)-1 -> 7 | ... DQ2: =MATCH(DQ1,ID_AC,0)-1 -> 113
A3: ACF | B3: =ROWS(ACF) -> 11 | C3: =COLUMNS(ACF) -> 114 | F3: Base | AM3: ELC | BD3: ELC
A4: ACD_1 | B4: =ROWS(ACD_1) -> 8 | C4: =COLUMNS(ACD_1) -> 114 | F4: 0 | H4: CRV | I4: CRV | J4: ELC | K4: CRV | L4: MTN | M4: MTN | N4: MTN | O4: MTN | P4: NCD | Q4: NSE | R4: NSE | S4: LNG | T4: LNG | U4: LNCD | V4: LNSE | W4: LNSE | X4: LNG | Y4: LNG | Z4: ELC | AA4: MTN | AB4: FLC | AC4: AMM | AD4: MTN | AE4: ELC | AF4: HYR | AG4: ELC | AH4: SOR | AI4: ELC | AJ4: ELC | AK4: WIR1 | AL4: WIR2 | AM4: BDG | AN4: ELC | AO4: ELC | AP4: ELC | AQ4: PCD | AR4: PSE | AS4: PSE | AT4: ELC | AU4: ELC | AV4: BCDS | AW4: BSES | AX4: BSES | AY4: ELC | AZ4: ELC | BA4: BCDL | BB4: BSEL | BC4: BSEL | BD4: ELC | BE4: HYN | BF4: HYN | BG4: HCD | BH4: HSE | BI4: HSE | BJ4: LHY | BK4: LHY | BL4: LHCD | BM4: LHSE | BN4: LHSE | BO4: HYN | BP4: HYN | BQ4: LHY | BR4: LHY | BS4: MTN | BT4: MTN | BU4: AMM | BV4: ELC | BW4: AMM | BX4: AMM | BY4: AMCD | BZ4: AMSE | CA4: AMSE | CB4: AMM | CC4: AMM | CD4: ELC | CE4: HYN | CF4: MCH | CG4: MCH | CH4: MCCD | CI4: MCSE | CJ4: MCSE | CK4: MCH | CL4: MCH | CM4: MTN | CN4: AMM | CO4: HYN | CP4: ELC | CQ4: SFF | CR4: SSV1 | CS4: MTN | CT4: HYN | CU4: AMM | CV4: LCO | CW4: LCO | CX4: CRV | CY4: CRV | CZ4: LNG2 | DA4: LNG2 | DB4: MTN | DC4: MTN | DD4: LHY2 | DE4: LHY2 | DF4: HYN | DG4: HYN | DH4: AMM2 | DI4: AMM2 | DJ4: MCH2 | DK4: MCH2 | DL4: ELC | DM4: ELC | DN4: CO2 | DO4: CO2 | DP4: CO2 | DQ4: CO2
A5: ACD_2 | B5: =ROWS(ACD_2) -> 1 | C5: =COLUMNS(ACD_2) -> 114 | F5: 1 | H5: LTH | I5: ELC | J5: CRV | K5: LCO | L5: LNG | M5: LNG | N5: NSE | O5: NSE | S5: LNSE | T5: LNSE | X5: LNG2 | Y5: LNG2 | AA5: CO2 | AB5: FSBT | AC5: FSBT | AD5: ELC | AE5: HYR | AG5: SOR | AI5: WIR1 | AJ5: WIR2 | AM5: CEPBD | AN5: FLC | AO5: PSE | AP5: PSE | AT5: BSES | AU5: BSES | AY5: BSEL | AZ5: BSEL | BD5: HYN | BE5: HSE | BF5: HSE | BJ5: LHSE | BK5: LHSE | BO5: LHY | BP5: LHY | BQ5: LHY2 | BR5: LHY2 | BS5: HYN | BT5: CRV | BU5: HYN | BV5: HYN | BW5: AMSE | BX5: AMSE | CB5: AMM2 | CC5: AMM2 | CD5: TEC | CE5: MCH | CF5: MCSE | CG5: MCSE | CK5: MCH2 | CL5: MCH2 | CM5: HEA | CN5: HEA | CO5: HEA | CP5: LTH | CS5: SFF | CT5: SFF | CU5: SFF | CV5: CO2 | CW5: CO2 | CX5: CO2 | CY5: CO2 | CZ5: CO2 | DA5: CO2 | DB5: CO2 | DC5: CO2 | DK5: FSBT | DL5: TEC | DM5: TEC
A6: ACD_3 | B6: =ROWS(ACD_3) -> 2 | C6: =COLUMNS(ACD_3) -> 114 | F6: 2 | H6: ELC | I6: TEC | J6: LCO | L6: ELC | M6: ELC | N6: NCD | O6: NCD | S6: LNCD | T6: LNCD | AB6: CO2 | AG6: NSC | AI6: NSC | AJ6: NSC | AM6: ELC | AO6: PCD | AP6: PCD | AT6: BCDS | AU6: BCDS | AY6: BCDL | AZ6: BCDL | BD6: NSC | BE6: HCD | BF6: HCD | BJ6: LHCD | BK6: LHCD | BO6: ELC | BS6: CRV | BT6: ELC | BU6: ELC | BV6: AMM | BW6: AMCD | BX6: AMCD | CD6: HEA | CE6: ELC | CF6: MCCD | CG6: MCCD | CV6: OMC | CW6: OMC
A7: Battery 1 - stored energy | B7: =MATCH("PS1",ID_AC,0)-1 -> 36 | C7: =MATCH("PS2",ID_AC,0)-1 -> 37 | F7: 3 | H7: TEC | J7: TEC | L7: OMC | M7: OMC | N7: ELC | S7: ELC | AO7: OMC | AT7: OMC | AU7: NSC | AY7: OMC | AZ7: NSC | BD7: TEC | BE7: ELC | BJ7: ELC | BK7: ELC | BO7: TEC | BS7: ELC | BT7: TEC | BU7: TEC | BV7: HEA | BW7: ELC | BX7: ELC | CD7: HYN | CE7: HEA | CF7: ELC | CG7: ELC
A8: Battery 2 - stored energy | B8: =MATCH("BS1S",ID_AC,0)-1 -> 41 | C8: =MATCH("BS2S",ID_AC,0)-1 -> 42 | F8: 4 | L8: TEC | M8: TEC | N8: TEC | S8: TEC | AO8: NSC | AT8: NSC | AY8: NSC | BD8: OMC | BE8: TEC | BJ8: TEC | BK8: TEC | BS8: TEC | BT8: OMC | BV8: TEC | BW8: TEC | BX8: TEC | CD8: MCH | CE8: TEC | CF8: TEC | CG8: TEC
A9: Battery 3 - stored energy | B9: =MATCH("BS1L",ID_AC,0)-1 -> 46 | C9: =MATCH("BS2L",ID_AC,0)-1 -> 47 | F9: 5 | CD9: OMC
A10: Hydrogen - stored energy | B10: =MATCH("HS1",ID_AC,0)-1 -> 52 | C10: =MATCH("HS2",ID_AC,0)-1 -> 53 | F10: 6
A11: Liquefied hydrogen - stored energy | B11: =MATCH("LHS1",ID_AC,0)-1 -> 57 | C11: =MATCH("LHS2",ID_AC,0)-1 -> 58 | F11: 7
A12: Methane - stored energy | B12: =MATCH("NS1",ID_AC,0)-1 -> 9 | C12: =MATCH("NS2",ID_AC,0)-1 -> 10 | F12: 10
A13: Liquefied methane - stored energy | B13: =MATCH("LNS1",ID_AC,0)-1 -> 14 | C13: =MATCH("LNS2",ID_AC,0)-1 -> 15 | F13: 20 | Z13: OMC | AA13: FLC | CR13: SVC
A14: MCH - stored energy | B14: =MATCH("MCS1",ID_AC,0)-1 -> 79 | C14: =MATCH("MCS2",ID_AC,0)-1 -> 80 | F14: Unit | H14: Mt-C | I14: Mt-C | J14: TWh/Mt-C | K14: Mt-C | L14: Mtoe | M14: Mtoe | N14: Mtoe | O14: Mtoe | P14: Mtoe | Q14: Mtoe | R14: Mtoe | S14: Mtoe | T14: Mtoe | U14: Mtoe | V14: Mtoe | W14: Mtoe | X14: Mtoe | Y14: Mtoe | Z14: TWh | AA14: Mtoe | AB14: M$/Mtoe | AC14: Mtoe | AD14: Mtoe | AE14: TWh | AF14: TWh | AG14: TWh | AH14: TWh | AI14: TWh | AJ14: TWh | AK14: TWh | AL14: TWh | AM14: Mtoe | AN14: TWh | AO14: TWh | AP14: TWh | AQ14: TWh | AR14: TWh | AS14: TWh | AT14: TWh | AU14: TWh | AV14: TWh | AW14: TWh | AX14: TWh | AY14: TWh | AZ14: TWh | BA14: TWh | BB14: TWh | BC14: TWh | BD14: TWh | BE14: Mtoe | BF14: Mtoe | BG14: Mtoe | BH14: Mtoe | BI14: Mtoe | BJ14: Mtoe | BK14: Mtoe | BL14: Mtoe | BM14: Mtoe | BN14: Mtoe | BO14: Mtoe | BP14: Mtoe | BQ14: Mtoe | BR14: Mtoe | BS14: Mtoe | BT14: Mtoe | BU14: Mtoe | BV14: TWh | BW14: Mtoe | BX14: Mtoe | BY14: Mtoe | BZ14: Mtoe | CA14: Mtoe | CB14: Mtoe | CC14: Mtoe | CD14: TWh | CE14: Mtoe | CF14: Mton-MCH | CG14: Mton-MCH | CH14: Mton-MCH | CI14: Mton-MCH | CJ14: Mton-MCH | CK14: Mton | CL14: Mton | CM14: Mtoe | CN14: Mtoe | CO14: Mtoe | CP14: TWh | CQ14: Mtoe | CR14: Mtoe | CS14: Mtoe | CT14: Mtoe | CU14: Mtoe | CV14: Mt-C | CW14: Mt-C | CX14: Mt-C | CY14: Mt-C | CZ14: Mtoe | DA14: Mtoe | DB14: Mtoe | DC14: Mtoe | DD14: Mtoe | DE14: Mtoe | DF14: Mtoe | DG14: Mtoe | DH14: Mtoe | DI14: Mtoe | DJ14: Mton | DK14: Mton | DL14: TWh | DM14: TWh | DN14: Mt-C/Mtoe | DO14: Mt-C/Mtoe | DP14: Mt-C/Mtoe | DQ14: Mt-C/Mtoe
A15: Ammonia - stored energy | B15: =MATCH("AMS1",ID_AC,0)-1 -> 70 | C15: =MATCH("AMS2",ID_AC,0)-1 -> 71 | F15: =F5 -> 1 | H15: TWh/Mt-C | I15: TWh/Mt-C | J15: Mt-C | K15: Mt-C | L15: Mtoe | M15: Mtoe | N15: Mtoe | O15: Mtoe | S15: Mtoe | T15: Mtoe | X15: Mtoe | Y15: Mtoe | AA15: Mt-C/Mtoe | AB15: Mtoe | AC15: Mtoe | AD15: TWh | AE15: TWh | AG15: TWh | AI15: TWh | AJ15: TWh | AM15: t-C/Mtoe | AN15: M$/TWh | AO15: TWh | AP15: TWh | AT15: TWh | AU15: TWh | AY15: TWh | AZ15: TWh | BD15: Mtoe | BE15: Mtoe | BF15: Mtoe | BJ15: Mtoe | BK15: Mtoe | BO15: Mtoe | BP15: Mtoe | BQ15: Mtoe | BR15: Mtoe | BS15: Mtoe | BT15: Mt-C | BU15: Mtoe | BV15: Mtoe | BW15: Mtoe | BX15: Mtoe | CB15: Mtoe | CC15: Mtoe | CD15: TWh | CE15: Mton-MCH | CF15: Mton-MCH | CG15: Mton-MCH | CK15: Mton | CL15: Mton | CM15: Mtoe | CN15: Mtoe | CO15: Mtoe | CP15: TWh | CS15: Mtoe | CT15: Mtoe | CU15: Mtoe | CV15: Mt-C | CW15: Mt-C | CX15: Mt-C | CY15: Mt-C | CZ15: Mt-C/Mtoe | DA15: Mt-C/Mtoe | DB15: Mt-C/Mtoe | DC15: Mt-C/Mtoe | DK15: Mtoe | DL15: TWh | DM15: TWh
F16: =F6 -> 2 | H16: TWh/Mt-C | I16: TWh/Mt-C | J16: Mt-C | L16: TWh/Mtoe | M16: M$/Mtoe | N16: Mtoe | O16: Mtoe | S16: Mtoe | T16: Mtoe | AB16: MtC/Mtoe | AG16: TWh | AI16: TWh | AJ16: TWh | AM16: TWh | AO16: TWh | AP16: TWh | AT16: TWh | AU16: TWh | AY16: TWh | AZ16: TWh | BD16: TWh | BE16: Mtoe | BF16: Mtoe | BJ16: Mtoe | BK16: Mtoe | BO16: TWh/Mtoe | BS16: Mt-C | BT16: TWh/Mtoe | BU16: TWh/Mtoe | BV16: Mtoe | BW16: Mtoe | BX16: Mtoe | CD16: Mtoe | CE16: TWh | CF16: Mton-MCH | CG16: Mton-MCH | CV16: M$/Mt-C | CW16: M$/Mt-C
F17: =F7 -> 3 | H17: TWh/Mt-C | J17: TWh/Mt-C | L17: M$/Mtoe | N17: TWh | S17: TWh | AO17: M$/TWh | AT17: M$/TWh | AU17: TWh | AY17: M$/TWh | AZ17: TWh | BD17: TWh | BE17: TWh | BJ17: TWh | BK17: TWh | BO17: TWh/Mtoe | BS17: TWh/Mtoe | BT17: TWh/Mtoe | BU17: TWh/Mtoe | BV17: Mtoe | BW17: TWh | BX17: TWh | CD17: Mtoe | CE17: Mtoe | CF17: TWh | CG17: TWh
F18: =F8 -> 4 | L18: TWh/Mtoe | N18: TWh | S18: TWh | AO18: TWh | AT18: TWh | AY18: TWh | BD18: M$/Mtoe | BE18: TWh | BJ18: TWh | BK18: TWh | BS18: TWh/Mtoe | BT18: M$/Mtoe | BV18: TWh | BW18: TWh | BX18: TWh | CD18: Mton-MCH | CF18: TWh | CG18: TWh
F19: =F9 -> 5 | CD19: M$/Mtoe
F20: =F10 -> 6
F21: =F11 -> 7
F22: 10
F23: =F13 -> 20 | Z23: M$/TWh | CR23: M$/Mtoe
F24: =F3 -> Base | G24: =COUNTA(H4:DQ13) -> 271 | H24: =IF(H3="",-1,MATCH(H3,ID_IT,0)-1) -> -1 | I24: =IF(I3="",-1,MATCH(I3,ID_IT,0)-1) -> -1 | J24: =IF(J3="",-1,MATCH(J3,ID_IT,0)-1) -> -1 | K24: =IF(K3="",-1,MATCH(K3,ID_IT,0)-1) -> -1 | L24: =IF(L3="",-1,MATCH(L3,ID_IT,0)-1) -> -1 | M24: =IF(M3="",-1,MATCH(M3,ID_IT,0)-1) -> -1 | N24: =IF(N3="",-1,MATCH(N3,ID_IT,0)-1) -> -1 | O24: =IF(O3="",-1,MATCH(O3,ID_IT,0)-1) -> -1 | ... DQ24: =IF(DQ3="",-1,MATCH(DQ3,ID_IT,0)-1) -> -1
F25: =F4 -> 0 | H25: =IF(H4="",-1,MATCH(H4,ID_IT,0)-1) -> 6 | I25: =IF(I4="",-1,MATCH(I4,ID_IT,0)-1) -> 6 | J25: =IF(J4="",-1,MATCH(J4,ID_IT,0)-1) -> 20 | K25: =IF(K4="",-1,MATCH(K4,ID_IT,0)-1) -> 6 | L25: =IF(L4="",-1,MATCH(L4,ID_IT,0)-1) -> 8 | M25: =IF(M4="",-1,MATCH(M4,ID_IT,0)-1) -> 8 | N25: =IF(N4="",-1,MATCH(N4,ID_IT,0)-1) -> 8 | O25: =IF(O4="",-1,MATCH(O4,ID_IT,0)-1) -> 8 | ... DQ25: =IF(DQ4="",-1,MATCH(DQ4,ID_IT,0)-1) -> 4
F26: =F5 -> 1 | H26: =IF(H5="",-1,MATCH(H5,ID_IT,0)-1) -> 45 | I26: =IF(I5="",-1,MATCH(I5,ID_IT,0)-1) -> 20 | J26: =IF(J5="",-1,MATCH(J5,ID_IT,0)-1) -> 6 | K26: =IF(K5="",-1,MATCH(K5,ID_IT,0)-1) -> 7 | L26: =IF(L5="",-1,MATCH(L5,ID_IT,0)-1) -> 11 | M26: =IF(M5="",-1,MATCH(M5,ID_IT,0)-1) -> 11 | N26: =IF(N5="",-1,MATCH(N5,ID_IT,0)-1) -> 9 | O26: =IF(O5="",-1,MATCH(O5,ID_IT,0)-1) -> 9 | ... DQ26: =IF(DQ5="",-1,MATCH(DQ5,ID_IT,0)-1) -> -1
F27: =F6 -> 2 | H27: =IF(H6="",-1,MATCH(H6,ID_IT,0)-1) -> 20 | I27: =IF(I6="",-1,MATCH(I6,ID_IT,0)-1) -> 3 | J27: =IF(J6="",-1,MATCH(J6,ID_IT,0)-1) -> 7 | K27: =IF(K6="",-1,MATCH(K6,ID_IT,0)-1) -> -1 | L27: =IF(L6="",-1,MATCH(L6,ID_IT,0)-1) -> 20 | M27: =IF(M6="",-1,MATCH(M6,ID_IT,0)-1) -> 20 | N27: =IF(N6="",-1,MATCH(N6,ID_IT,0)-1) -> 10 | O27: =IF(O6="",-1,MATCH(O6,ID_IT,0)-1) -> 10 | ... DQ27: =IF(DQ6="",-1,MATCH(DQ6,ID_IT,0)-1) -> -1
F28: =F7 -> 3 | H28: =IF(H7="",-1,MATCH(H7,ID_IT,0)-1) -> 3 | I28: =IF(I7="",-1,MATCH(I7,ID_IT,0)-1) -> -1 | J28: =IF(J7="",-1,MATCH(J7,ID_IT,0)-1) -> 3 | K28: =IF(K7="",-1,MATCH(K7,ID_IT,0)-1) -> -1 | L28: =IF(L7="",-1,MATCH(L7,ID_IT,0)-1) -> 1 | M28: =IF(M7="",-1,MATCH(M7,ID_IT,0)-1) -> 1 | N28: =IF(N7="",-1,MATCH(N7,ID_IT,0)-1) -> 20 | O28: =IF(O7="",-1,MATCH(O7,ID_IT,0)-1) -> -1 | ... DQ28: =IF(DQ7="",-1,MATCH(DQ7,ID_IT,0)-1) -> -1
F29: =F8 -> 4 | H29: =IF(H8="",-1,MATCH(H8,ID_IT,0)-1) -> -1 | I29: =IF(I8="",-1,MATCH(I8,ID_IT,0)-1) -> -1 | J29: =IF(J8="",-1,MATCH(J8,ID_IT,0)-1) -> -1 | K29: =IF(K8="",-1,MATCH(K8,ID_IT,0)-1) -> -1 | L29: =IF(L8="",-1,MATCH(L8,ID_IT,0)-1) -> 3 | M29: =IF(M8="",-1,MATCH(M8,ID_IT,0)-1) -> 3 | N29: =IF(N8="",-1,MATCH(N8,ID_IT,0)-1) -> 3 | O29: =IF(O8="",-1,MATCH(O8,ID_IT,0)-1) -> -1 | ... DQ29: =IF(DQ8="",-1,MATCH(DQ8,ID_IT,0)-1) -> -1
F30: =F9 -> 5 | H30: =IF(H9="",-1,MATCH(H9,ID_IT,0)-1) -> -1 | I30: =IF(I9="",-1,MATCH(I9,ID_IT,0)-1) -> -1 | J30: =IF(J9="",-1,MATCH(J9,ID_IT,0)-1) -> -1 | K30: =IF(K9="",-1,MATCH(K9,ID_IT,0)-1) -> -1 | L30: =IF(L9="",-1,MATCH(L9,ID_IT,0)-1) -> -1 | M30: =IF(M9="",-1,MATCH(M9,ID_IT,0)-1) -> -1 | N30: =IF(N9="",-1,MATCH(N9,ID_IT,0)-1) -> -1 | O30: =IF(O9="",-1,MATCH(O9,ID_IT,0)-1) -> -1 | ... DQ30: =IF(DQ9="",-1,MATCH(DQ9,ID_IT,0)-1) -> -1
F31: =F10 -> 6 | H31: =IF(H10="",-1,MATCH(H10,ID_IT,0)-1) -> -1 | I31: =IF(I10="",-1,MATCH(I10,ID_IT,0)-1) -> -1 | J31: =IF(J10="",-1,MATCH(J10,ID_IT,0)-1) -> -1 | K31: =IF(K10="",-1,MATCH(K10,ID_IT,0)-1) -> -1 | L31: =IF(L10="",-1,MATCH(L10,ID_IT,0)-1) -> -1 | M31: =IF(M10="",-1,MATCH(M10,ID_IT,0)-1) -> -1 | N31: =IF(N10="",-1,MATCH(N10,ID_IT,0)-1) -> -1 | O31: =IF(O10="",-1,MATCH(O10,ID_IT,0)-1) -> -1 | ... DQ31: =IF(DQ10="",-1,MATCH(DQ10,ID_IT,0)-1) -> -1
F32: =F11 -> 7 | H32: =IF(H11="",-1,MATCH(H11,ID_IT,0)-1) -> -1 | I32: =IF(I11="",-1,MATCH(I11,ID_IT,0)-1) -> -1 | J32: =IF(J11="",-1,MATCH(J11,ID_IT,0)-1) -> -1 | K32: =IF(K11="",-1,MATCH(K11,ID_IT,0)-1) -> -1 | L32: =IF(L11="",-1,MATCH(L11,ID_IT,0)-1) -> -1 | M32: =IF(M11="",-1,MATCH(M11,ID_IT,0)-1) -> -1 | N32: =IF(N11="",-1,MATCH(N11,ID_IT,0)-1) -> -1 | O32: =IF(O11="",-1,MATCH(O11,ID_IT,0)-1) -> -1 | ... DQ32: =IF(DQ11="",-1,MATCH(DQ11,ID_IT,0)-1) -> -1
F33: 10 | H33: =IF(H12="",-1,MATCH(H12,ID_IT,0)-1) -> -1 | I33: =IF(I12="",-1,MATCH(I12,ID_IT,0)-1) -> -1 | J33: =IF(J12="",-1,MATCH(J12,ID_IT,0)-1) -> -1 | K33: =IF(K12="",-1,MATCH(K12,ID_IT,0)-1) -> -1 | L33: =IF(L12="",-1,MATCH(L12,ID_IT,0)-1) -> -1 | M33: =IF(M12="",-1,MATCH(M12,ID_IT,0)-1) -> -1 | N33: =IF(N12="",-1,MATCH(N12,ID_IT,0)-1) -> -1 | O33: =IF(O12="",-1,MATCH(O12,ID_IT,0)-1) -> -1 | ... DQ33: =IF(DQ12="",-1,MATCH(DQ12,ID_IT,0)-1) -> -1
F34: =F13 -> 20 | H34: =IF(H13="",-1,MATCH(H13,ID_IT,0)-1) -> -1 | I34: =IF(I13="",-1,MATCH(I13,ID_IT,0)-1) -> -1 | J34: =IF(J13="",-1,MATCH(J13,ID_IT,0)-1) -> -1 | K34: =IF(K13="",-1,MATCH(K13,ID_IT,0)-1) -> -1 | L34: =IF(L13="",-1,MATCH(L13,ID_IT,0)-1) -> -1 | M34: =IF(M13="",-1,MATCH(M13,ID_IT,0)-1) -> -1 | N34: =IF(N13="",-1,MATCH(N13,ID_IT,0)-1) -> -1 | O34: =IF(O13="",-1,MATCH(O13,ID_IT,0)-1) -> -1 | ... DQ34: =IF(DQ13="",-1,MATCH(DQ13,ID_IT,0)-1) -> -1
F35: =F4 -> 0 | H35: 1 | I35: 1 | J35: -0.733 | K35: 1 | L35: -1 | M35: 1 | N35: -1 | O35: 1 | P35: 1 | Q35: 0.9999 | R35: -1 | S35: -1 | T35: 1 | U35: 1 | V35: 0.99995831 | W35: -1 | X35: -1 | Y35: 1 | Z35: 1 | AA35: 1 | AB35: 185 | AC35: -1 | AD35: -1 | AE35: 1 | AF35: 1 | AG35: 1 | AH35: 1 | AI35: 1 | AJ35: 1 | AK35: 1 | AL35: 1 | AM35: -1 | AN35: 1 | AO35: -1 | AP35: 1 | AQ35: 1 | AR35: 0.999 | AS35: -1 | AT35: -1 | AU35: 1 | AV35: 1 | AW35: 0.999 | AX35: -1 | AY35: -1 | AZ35: 1 | BA35: 1 | BB35: 0.999 | BC35: -1 | BD35: -15.716216 | BE35: -1 | BF35: 1 | BG35: 1 | BH35: 0.9999 | BI35: -1 | BJ35: -1 | BK35: 1 | BL35: 1 | BM35: 0.99995831 | BN35: -1 | BO35: -1 | BP35: 1 | BQ35: -1 | BR35: 1 | BS35: 1 | BT35: 1 | BU35: 1 | BV35: -0.52199 | BW35: -1 | BX35: 1 | BY35: 1 | BZ35: 0.9999 | CA35: -1 | CB35: -1 | CC35: 1 | CD35: -0.522 | CE35: 1 | CF35: -1 | CG35: 1 | CH35: 1 | CI35: 1 | CJ35: -1 | CK35: -1 | CL35: 1 | CM35: -1 | CN35: -1 | CO35: -1 | CP35: -0.28490028 | CQ35: 1 | CR35: 1 | CS35: -1 | CT35: -1 | CU35: -1 | CV35: 1 | CW35: -1 | CX35: 1 | CY35: -1 | CZ35: 1 | DA35: -1 | DB35: 1 | DC35: -1 | DD35: 1 | DE35: -1 | DF35: 1 | DG35: -1 | DH35: 1 | DI35: -1 | DJ35: 1 | DK35: -1 | DL35: 1 | DM35: -1 | DN35: 1 | DO35: 1 | DP35: 0.6406 | DQ35: 0.6406
F36: =F5 -> 1 | H36: -4.0406667 | I36: -4.8253333 | J36: -1 | K36: -1 | L36: 1 | M36: -1 | N36: 1 | O36: -1 | S36: 0.999 | T36: -1 | X36: 1 | Y36: -1 | AA36: 0.6406 | AB36: 1 | AC36: 1 | AD36: 4.8846 | AE36: 1 | AG36: 1 | AI36: 1 | AJ36: 1 | AM36: 1.124 | AN36: 16.041667 | AO36: 0.97467943 | AP36: -1.0259784 | AT36: 0.97467943 | AU36: -1.0259784 | AY36: 0.9486833 | AZ36: -1.0540926 | BD36: 1 | BE36: 1 | BF36: -1 | BJ36: 0.999 | BK36: -1 | BO36: 1 | BP36: -1 | BQ36: 1 | BR36: -1 | BS36: -1.2987151 | BT36: -0.60145571 | BU36: -1.1522 | BV36: 1 | BW36: 1 | BX36: -1 | CB36: 1 | CC36: -1 | CD36: 0.522 | CE36: -6.444 | CF36: 1 | CG36: -1 | CK36: 1 | CL36: -1 | CM36: 1 | CN36: 1 | CO36: 1 | CP36: 1 | CS36: 1 | CT36: 1 | CU36: 1 | CV36: 1 | CW36: -1 | CX36: 1 | CY36: -1 | CZ36: 0.6406 | DA36: -0.6406 | DB36: 0.6406 | DC36: -0.6406 | DK36: -0.016144033 | DL36: -1 | DM36: 1
F37: =F6 -> 2 | H37: -0.66733333 | I37: 4.8253333 | J37: 1 | L37: -0.43271397 | M37: 0 | N37: -1 | O37: 0 | S37: -1 | T37: 0 | AB37: 0.8834148 | AG37: 0 | AI37: 0 | AJ37: 0 | AM37: 4.0705 | AO37: -1 | AP37: -1 | AT37: -1 | AU37: -1 | AY37: -1 | AZ37: -1 | BD37: 0 | BE37: -1 | BF37: 0 | BJ37: -1 | BK37: -1 | BO37: -2.1228 | BS37: -0.62651636 | BT37: -14.384816 | BU37: -1.3506 | BV37: -1.04106 | BW37: -1 | BX37: -1 | CD37: -0.006 | CE37: -0.52199 | CF37: -1 | CG37: -1 | CV37: 11 | CW37: 11
F38: =F7 -> 3 | H38: 0.66733333 | J38: 0.733 | L38: 0 | M38: 0 | N38: -0.80247 | S38: -0.12 | AO38: 0 | AT38: 0 | AU38: 0 | AY38: 0 | AZ38: 0 | BD38: 15.716216 | BE38: -0.86763677 | BJ38: -0.10615 | BK38: -0.10615 | BO38: 2.1228 | BS38: -0.1511926 | BT38: 14.384816 | BU38: 1.3506 | BV38: -0.29025 | BW38: -0.00174 | BX38: 0 | CD38: -1 | CE38: -0.40694 | CF38: -0.00061 | CG38: 0
F39: =F8 -> 4 | L39: 0.43271397 | M39: 0 | N39: 0.80247 | S39: 0.12 | AO39: 0 | AT39: 0 | AY39: 0 | BD39: 4.7049113 | BE39: 0.86763677 | BJ39: 0.10615 | BK39: 0.10615 | BS39: 0.1511926 | BT39: 1.663025 | BV39: 0.52199 | BW39: 0.00174 | BX39: 0 | CD39: 5.6839 | CE39: 0.52199 | CF39: 0.00061 | CG39: 0
F40: =F9 -> 5 | CD40: 56.46
C41: 1 | F41: =F10 -> 6
C42: 1 | F42: =F11 -> 7
C43: =IF(D45=1,C42+1,C42) -> 1 | E43: =INDEX(ID_YR,C41) -> YR2050 | F43: All
D44: 1 | E44: =INDEX(ID_YR,C42) -> YR2050 | F44: =INDEX(ID_ND,D44) -> EXP | Z44: 9999 | AA44: 87.307678 | CR44: 0
D45: =IF(D44+1>COUNTA(ID_ND),1,D44+1) -> 2 | E45: =INDEX(ID_YR,C43) -> YR2050 | F45: =INDEX(ID_ND,D45) -> IMP | Z45: 9999 | AA45: 194.45801 | CR45: 0

Sheet AC_LM
B1: Row | C1: Column | F1: Activity_UpperLimit [AC_LM] | H1: GELP | I1: H2L | J1: MTS | K1: MTS2 | L1: AMS | M1: MCS | N1: =CASE!M3 -> NG_IS | O1: =CASE!N3 -> H2_IS | P1: =CASE!O3 -> LA_IS | Q1: =CASE!P3 -> MC_IS | R1: NGF | S1: H2F | T1: AMF
A2: AC_LMI | B2: =ROWS(AC_LMI) -> 1 | C2: =COLUMNS(AC_LMI) -> 13 | F2: ID | H2: =MATCH(H1,ID_AC,0)-1 -> 18 | I2: =MATCH(I1,ID_AC,0)-1 -> 59 | J2: =MATCH(J1,ID_AC,0)-1 -> 63 | K2: =MATCH(K1,ID_AC,0)-1 -> 64 | L2: =MATCH(L1,ID_AC,0)-1 -> 65 | M2: =MATCH(M1,ID_AC,0)-1 -> 74 | N2: =MATCH(N1,ID_AC,0)-1 -> 96 | O2: =MATCH(O1,ID_AC,0)-1 -> 100 | ... T2: =MATCH(T1,ID_AC,0)-1 -> 91
A3: AC_LMD | B3: =ROWS(AC_LMD) -> 1 | C3: =COLUMNS(AC_LMD) -> 13 | D3: 1 | E3: 1 | F3: =INDEX(ID_YR,D3) -> YR2050 | G3: =INDEX(ID_RG,E3) -> ALL | H3: =CASE!C18 -> 0 | I3: =CASE!H4 -> 0 | J3: =CASE!I4 -> -1 | K3: =CASE!J4 -> 0 | L3: =CASE!K4 -> 0 | M3: =CASE!L4 -> 0 | N3: =CASE!M4 -> -1 | O3: =CASE!N4 -> 0 | P3: =CASE!O4 -> 0 | ... T3: =CASE!S4 -> 0

Sheet NK
B1: Row | C1: Column | G1: =IND!A5 -> Nodal facility [NK] | I1: DACE1 | J1: DACE2 | K1: CXL | L1: NGL | M1: NGV | N1: NGS | O1: NGT | P1: LNGS | Q1: LNGT | R1: GTG | S1: HYG | T1: SPG | U1: WIG1 | V1: WIG2 | W1: BDG | X1: LWR | Y1: PPS | Z1: BTSS | AA1: BTSL | AB1: WEL | AC1: H2S | AD1: H2T | AE1: LH2S | AF1: LH2T | AG1: H2L | AH1: H2V | AI1: MTS | AJ1: MTS2 | AK1: AMS | AL1: HSP | AM1: AMMS | AN1: AMMT | AO1: MCS | AP1: DHG | AQ1: MCHS | AR1: MCHT | AS1: GBL | AT1: ABL | AU1: HBL | AV1: HPP | AW1: HCLD | AX1: HCUL | AY1: NG_IS | AZ1: NG_ES | BA1: H2_IS | BB1: H2_ES | BC1: LA_IS | BD1: LA_ES | BE1: MC_IS | BF1: MC_ES
A2: NKI | B2: 1 | C2: =COLUMNS(NKI) -> 50 | G2: ID | I2: =MATCH(I1,ID_NK,0)-1 -> 0 | J2: =MATCH(J1,ID_NK,0)-1 -> 1 | K2: =MATCH(K1,ID_NK,0)-1 -> 2 | L2: =MATCH(L1,ID_NK,0)-1 -> 3 | M2: =MATCH(M1,ID_NK,0)-1 -> 4 | N2: =MATCH(N1,ID_NK,0)-1 -> 5 | O2: =MATCH(O1,ID_NK,0)-1 -> 6 | P2: =MATCH(P1,ID_NK,0)-1 -> 7 | ... BF2: =MATCH(BF1,ID_NK,0)-1 -> 49
A3: NKF | B3: =ROWS(NKF) -> 6 | C3: =COLUMNS(NKF) -> 50 | G3: 0 | I3: DACE1 | J3: DACE2 | K3: CXL | L3: NGL | M3: NGV | N3: NSA | P3: LNSA | R3: GTG | S3: HYG | T3: SPG | U3: WIG1 | V3: WIG2 | W3: BDG | X3: LWR | Y3: PSA | Z3: BSAS | AA3: BSAL | AB3: WEL | AC3: HSA | AE3: LHSA | AG3: H2L | AH3: H2V | AI3: MTS | AJ3: MTS2 | AK3: AMS | AL3: HSP | AM3: AMSA | AO3: MCS | AP3: DHG | AQ3: MCSA | AS3: GBL | AT3: ABL | AU3: HBL | AV3: HPP | AW3: LNLD | AX3: LNUL | AY3: NG_IS | AZ3: NG_ES | BA3: H2_IS | BB3: H2_ES | BC3: LA_IS | BD3: LA_ES | BE3: MC_IS | BF3: MC_ES
A4: NKD_1 | B4: =ROWS(NKD_1) -> 2 | C4: =COLUMNS(NKD_2) -> 50 | G4: 1 | S4: HYD | T4: SPD | U4: WID1 | V4: WID2 | AW4: LHLD | AX4: LHUL | BD4: AMMP
A5: NKD_2 | B5: =ROWS(NKD_2) -> 7 | C5: =COLUMNS(NKD_2) -> 50 | G5: 2 | AW5: AMLD | AX5: AMUL
A6: NKD_3 | B6: =ROWS(NKD_3) -> 1 | C6: =COLUMNS(NKD_3) -> 50 | G6: 3 | AW6: MCLD | AX6: MCUL
A7: Hydro | B7: =MATCH("HYG",ID_NK,0)-1 -> 10 | G7: 4
A8: Solar Wind | B8: =MATCH("SPG",ID_NK,0)-1 -> 11 | C8: =MATCH("WIG2",ID_NK,0)-1 -> 13 | G8: 5
A9: Storage (battery 1,2) | B9: =MATCH("PPS",ID_NK,0)-1 -> 16 | C9: =MATCH("BTSS",ID_NK,0)-1 -> 17 | G9: 0 | H9: =COUNT(NKF)-COUNTIF(NKF,-1) -> 55 | I9: =IF(I3="",-1,MATCH(I3,ID_AC,0)-1) -> 0 | J9: =IF(J3="",-1,MATCH(J3,ID_AC,0)-1) -> 1 | K9: =IF(K3="",-1,MATCH(K3,ID_AC,0)-1) -> 2 | L9: =IF(L3="",-1,MATCH(L3,ID_AC,0)-1) -> 4 | M9: =IF(M3="",-1,MATCH(M3,ID_AC,0)-1) -> 5 | N9: =IF(N3="",-1,MATCH(N3,ID_AC,0)-1) -> 8 | O9: =IF(O3="",-1,MATCH(O3,ID_AC,0)-1) -> -1 | P9: =IF(P3="",-1,MATCH(P3,ID_AC,0)-1) -> 13 | ... BF9: =IF(BF3="",-1,MATCH(BF3,ID_AC,0)-1) -> 107
A10: Storage (battery3) | B10: =MATCH("BTSL",ID_NK,0)-1 -> 18 | G10: 1 | I10: =IF(I4="",-1,MATCH(I4,ID_AC,0)-1) -> -1 | J10: =IF(J4="",-1,MATCH(J4,ID_AC,0)-1) -> -1 | K10: =IF(K4="",-1,MATCH(K4,ID_AC,0)-1) -> -1 | L10: =IF(L4="",-1,MATCH(L4,ID_AC,0)-1) -> -1 | M10: =IF(M4="",-1,MATCH(M4,ID_AC,0)-1) -> -1 | N10: =IF(N4="",-1,MATCH(N4,ID_AC,0)-1) -> -1 | O10: =IF(O4="",-1,MATCH(O4,ID_AC,0)-1) -> -1 | P10: =IF(P4="",-1,MATCH(P4,ID_AC,0)-1) -> -1 | ... BF10: =IF(BF4="",-1,MATCH(BF4,ID_AC,0)-1) -> -1
A11: Storage (H2, LH2) | B11: =MATCH("H2T",ID_NK,0)-1 -> 21 | C11: =MATCH("LH2T",ID_NK,0)-1 -> 23 | G11: 2 | I11: =IF(I5="",-1,MATCH(I5,ID_AC,0)-1) -> -1 | J11: =IF(J5="",-1,MATCH(J5,ID_AC,0)-1) -> -1 | K11: =IF(K5="",-1,MATCH(K5,ID_AC,0)-1) -> -1 | L11: =IF(L5="",-1,MATCH(L5,ID_AC,0)-1) -> -1 | M11: =IF(M5="",-1,MATCH(M5,ID_AC,0)-1) -> -1 | N11: =IF(N5="",-1,MATCH(N5,ID_AC,0)-1) -> -1 | O11: =IF(O5="",-1,MATCH(O5,ID_AC,0)-1) -> -1 | P11: =IF(P5="",-1,MATCH(P5,ID_AC,0)-1) -> -1 | ... BF11: =IF(BF5="",-1,MATCH(BF5,ID_AC,0)-1) -> -1
A12: Storage (CH4, LCH4) | B12: =MATCH("NGT",ID_NK,0)-1 -> 6 | C12: =MATCH("LNGT",ID_NK,0)-1 -> 8 | G12: 3 | I12: =IF(I6="",-1,MATCH(I6,ID_AC,0)-1) -> -1 | J12: =IF(J6="",-1,MATCH(J6,ID_AC,0)-1) -> -1 | K12: =IF(K6="",-1,MATCH(K6,ID_AC,0)-1) -> -1 | L12: =IF(L6="",-1,MATCH(L6,ID_AC,0)-1) -> -1 | M12: =IF(M6="",-1,MATCH(M6,ID_AC,0)-1) -> -1 | N12: =IF(N6="",-1,MATCH(N6,ID_AC,0)-1) -> -1 | O12: =IF(O6="",-1,MATCH(O6,ID_AC,0)-1) -> -1 | P12: =IF(P6="",-1,MATCH(P6,ID_AC,0)-1) -> -1 | ... BF12: =IF(BF6="",-1,MATCH(BF6,ID_AC,0)-1) -> -1
A13: Storage (MCH tank, NH3 tank) | B13: =MATCH("MCHT",ID_NK,0)-1 -> 35 | C13: =MATCH("AMMT",ID_NK,0)-1 -> 31 | G13: 4 | I13: =IF(I7="",-1,MATCH(I7,ID_AC,0)-1) -> -1 | J13: =IF(J7="",-1,MATCH(J7,ID_AC,0)-1) -> -1 | K13: =IF(K7="",-1,MATCH(K7,ID_AC,0)-1) -> -1 | L13: =IF(L7="",-1,MATCH(L7,ID_AC,0)-1) -> -1 | M13: =IF(M7="",-1,MATCH(M7,ID_AC,0)-1) -> -1 | N13: =IF(N7="",-1,MATCH(N7,ID_AC,0)-1) -> -1 | O13: =IF(O7="",-1,MATCH(O7,ID_AC,0)-1) -> -1 | P13: =IF(P7="",-1,MATCH(P7,ID_AC,0)-1) -> -1 | ... BF13: =IF(BF7="",-1,MATCH(BF7,ID_AC,0)-1) -> -1
A14: Hydrogen carrier loading/unloading | B14: =MATCH("HCLD",ID_NK,0)-1 -> 40 | C14: =MATCH("HCUL",ID_NK,0)-1 -> 41 | G14: 5 | I14: =IF(I8="",-1,MATCH(I8,ID_AC,0)-1) -> -1 | J14: =IF(J8="",-1,MATCH(J8,ID_AC,0)-1) -> -1 | K14: =IF(K8="",-1,MATCH(K8,ID_AC,0)-1) -> -1 | L14: =IF(L8="",-1,MATCH(L8,ID_AC,0)-1) -> -1 | M14: =IF(M8="",-1,MATCH(M8,ID_AC,0)-1) -> -1 | N14: =IF(N8="",-1,MATCH(N8,ID_AC,0)-1) -> -1 | O14: =IF(O8="",-1,MATCH(O8,ID_AC,0)-1) -> -1 | P14: =IF(P8="",-1,MATCH(P8,ID_AC,0)-1) -> -1 | ... BF14: =IF(BF8="",-1,MATCH(BF8,ID_AC,0)-1) -> -1
A15: Nuclear | B15: =MATCH("LWR",ID_NK,0)-1 -> 15 | G15: Unit | I15: Mt-C/yr | J15: Mt-C/yr | K15: Mt-C/yr | L15: Mtoe/yr | M15: Mtoe/yr | N15: GW | O15: GWh | P15: GW | Q15: GWh | R15: GW | S15: GW | T15: GW | U15: GW | V15: GW | W15: GW | X15: GW | Y15: GW | Z15: GW | AA15: GW | AB15: GWe | AC15: GW | AD15: GWh | AE15: GW | AF15: GWh | AG15: Mtoe/yr | AH15: Mtoe/yr | AI15: Mtoe/yr | AJ15: Mtoe/yr | AK15: Mtoe/yr | AL15: Mtoe-H2out/yr | AM15: GW | AN15: GWh | AO15: Mtoe-H2in/yr | AP15: Mtoe/yr | AQ15: MtMCH/yr | AR15: MtMCH | AS15: Mtoe/yr | AT15: Mtoe/yr | AU15: Mtoe/yr | AV15: kW-th | AW15: Mtoe/yr | AX15: Mtoe/yr | AY15: Mtoe/yr | AZ15: Mtoe/yr | BA15: Mtoe/yr | BB15: Mtoe/yr | BC15: Mtoe/yr | BD15: Mtoe/yr | BE15: MtMCH/yr | BF15: MtMCH/yr
A16: NK_LAF | B16: =ROWS(NK_LAF) -> 2 | C16: =COLUMNS(NK_LAF) -> 3 | G16: Time profile [positive: renewable power plants, 0: dispatchable power plants, -1: other plants] | H16: =MAX(I16:BF16) -> 6 | I16: -1 | J16: -1 | K16: -1 | L16: 0 | M16: -1 | N16: -1 | O16: -1 | P16: -1 | Q16: -1 | R16: 0 | S16: 1 | T16: 2 | U16: 3 | V16: 4 | W16: 0 | X16: 0 | Y16: =-1 -> -1 | Z16: -1 | AA16: -1 | AB16: 0 | AC16: -1 | AD16: -1 | AE16: -1 | AF16: -1 | AG16: 0 | AH16: -1 | AI16: 0 | AJ16: 0 | AK16: 0 | AL16: -1 | AM16: -1 | AN16: -1 | AO16: 0 | AP16: -1 | AQ16: -1 | AR16: -1 | AS16: -1 | AT16: -1 | AU16: -1 | AV16: -1 | AW16: 5 | AX16: 6 | AY16: -1 | AZ16: -1 | BA16: -1 | BB16: -1 | BC16: -1 | BD16: -1 | BE16: -1 | BF16: -1
A17: NK_LCC | B17: =ROWS(NK_LCC) -> 2 | C17: =COLUMNS(NK_LCC) -> 4 | G17: Operational info | I17: =IF(I16=0,IFERROR(MATCH(I2,NK_OPI,0)-1,"Error"),-1) -> -1 | J17: =IF(J16=0,IFERROR(MATCH(J2,NK_OPI,0)-1,"Error"),-1) -> -1 | K17: =IF(K16=0,IFERROR(MATCH(K2,NK_OPI,0)-1,"Error"),-1) -> -1 | L17: =IF(L16=0,IFERROR(MATCH(L2,NK_OPI,0)-1,"Error"),-1) -> 0 | M17: =IF(M16=0,IFERROR(MATCH(M2,NK_OPI,0)-1,"Error"),-1) -> -1 | N17: =IF(N16=0,IFERROR(MATCH(N2,NK_OPI,0)-1,"Error"),-1) -> -1 | O17: =IF(O16=0,IFERROR(MATCH(O2,NK_OPI,0)-1,"Error"),-1) -> -1 | P17: =IF(P16=0,IFERROR(MATCH(P2,NK_OPI,0)-1,"Error"),-1) -> -1 | ... BF17: =IF(BF16=0,IFERROR(MATCH(BF2,NK_OPI,0)-1,"Error"),-1) -> -1
A18: NK_KI | B18: =ROWS(NK_KI) -> 1 | C18: =COLUMNS(NK_KI) -> 14 | G18: Unit conversion | I18: 1 | J18: 1 | K18: 1 | L18: 1 | M18: 1 | N18: =8.76/B35 -> 0.75322442 | O18: 1 | P18: =8.76/B35 -> 0.75322442 | Q18: 1 | R18: 8.76 | S18: 8.76 | T18: 8.76 | U18: 8.76 | V18: 8.76 | W18: 8.76 | X18: 8.76 | Y18: 8.76 | Z18: 8.76 | AA18: 8.76 | AB18: 8.76 | AC18: =8.76/B35 -> 0.75322442 | AD18: 1 | AE18: =8.76/B35 -> 0.75322442 | AF18: 1 | AG18: 1 | AH18: 1 | AI18: 1 | AJ18: 1 | AK18: 1 | AL18: 1 | AM18: =8.76/B35 -> 0.75322442 | AN18: 1 | AO18: 1 | AP18: 1 | AQ18: 1 | AR18: 1 | AS18: 1 | AT18: 1 | AU18: 1 | AV18: 8.76 | AW18: 1 | AX18: 1 | AY18: 1 | AZ18: 1 | BA18: 1 | BB18: 1 | BC18: 1 | BD18: 1 | BE18: 1 | BF18: 1
A19: NK_EKD | B19: =ROWS(NK_EKD) -> 2 | C19: =COLUMNS(NK_EKD) -> 14 | G19: Max. capacity factor | I19: 0.95 | J19: 0.95 | K19: 0.95 | L19: 0.95 | M19: 0.95 | N19: 0.95 | O19: 1 | P19: 0.95 | Q19: 1 | R19: 1 | S19: 1 | T19: 1 | U19: 1 | V19: 1 | W19: 1 | X19: 0.7 | Y19: 0.95 | Z19: 0.95 | AA19: 0.95 | AB19: 0.95 | AC19: 0.95 | AD19: 1 | AE19: 0.95 | AF19: 1 | AG19: 0.95 | AH19: 0.95 | AI19: 0.95 | AJ19: 0.95 | AK19: 0.95 | AL19: 0.95 | AM19: 0.95 | AN19: 1 | AO19: 0.95 | AP19: 0.95 | AQ19: 0.95 | AR19: 1 | AS19: 0.95 | AT19: 0.95 | AU19: 0.95 | AV19: 0.95 | AW19: 1 | AX19: 1 | AY19: 0.95 | AZ19: 0.95 | BA19: 0.95 | BB19: 0.95 | BC19: 0.95 | BD19: 0.95 | BE19: 0.95 | BF19: 0.95
A20: NK_MKD | B20: =ROWS(NK_MKD) -> 2 | C20: =COLUMNS(NK_MKD) -> 14 | G20: Hourly min. capacity factor | I20: 0 | J20: 0 | K20: 0 | L20: 0.3 | M20: 0 | N20: 0 | O20: 0 | P20: 0 | Q20: 0 | R20: 0 | S20: 0 | T20: 0 | U20: 0 | V20: 0 | W20: 0 | X20: 0 | Y20: 0 | Z20: 0 | AA20: 0 | AB20: 0.1 | AC20: 0 | AD20: 0 | AE20: 0 | AF20: 0 | AG20: 0.3 | AH20: 0 | AI20: 0.3 | AJ20: 0.7 | AK20: 0.3 | AL20: 0.3 | AM20: 0 | AN20: 0 | AO20: 0.3 | AP20: 0.3 | AQ20: 0 | AR20: 0 | AS20: 0 | AT20: 0 | AU20: 0 | AV20: 0 | AW20: 0 | AX20: 0 | AY20: 0 | AZ20: 0 | BA20: 0 | BB20: 0 | BC20: 0 | BD20: 0 | BE20: 0 | BF20: 0
A21: Water electrolysis | B21: =MATCH("WEL",ID_NK,0)-1 -> 19 | G21: Annualize factor | I21: =IND!$BE$5/(1-(1+IND!$BE$5)^-I24)+I26 -> 0.13367878 | J21: =IND!$BE$5/(1-(1+IND!$BE$5)^-J24)+J26 -> 0.13067878 | K21: 1 | L21: =IND!$BE$5/(1-(1+IND!$BE$5)^-L24)+L26 -> 0.12882743 | M21: =IND!$BE$5/(1-(1+IND!$BE$5)^-M24)+M26 -> 0.12882743 | N21: =IND!$BE$5/(1-(1+IND!$BE$5)^-N24)+N26 -> 0.12682954 | O21: =IND!$BE$5/(1-(1+IND!$BE$5)^-O24)+O26 -> 0.12682954 | P21: =IND!$BE$5/(1-(1+IND!$BE$5)^-P24)+P26 -> 0.098827433 | Q21: =IND!$BE$5/(1-(1+IND!$BE$5)^-Q24)+Q26 -> 0.098827433 | R21: =IND!$BE$5/(1-(1+IND!$BE$5)^-R24)+R26 -> 0.12386016 | S21: =IND!$BE$5/(1-(1+IND!$BE$5)^-S24)+S26 -> 0.10979795 | ... BF21: =IND!$BE$5/(1-(1+IND!$BE$5)^-BF24)+BF26 -> 0.12882743
A22: Importing and exporting terminal | B22: =MATCH("NG_IS",ID_NK,0)-1 -> 42 | C22: =MATCH("MC_ES",ID_NK,0)-1 -> 49 | G22: Location type (availability factor) | I22: 0 | J22: 0 | K22: 0 | L22: 0 | M22: 0 | N22: 0 | O22: 0 | P22: 0 | Q22: 0 | R22: 0 | S22: 0 | T22: 0 | U22: 0 | V22: 0 | W22: 0 | X22: 0 | Y22: 0 | Z22: 0 | AA22: 0 | AB22: 0 | AC22: 0 | AD22: 0 | AE22: 0 | AF22: 0 | AG22: 0 | AH22: 0 | AI22: 0 | AJ22: 0 | AK22: 0 | AL22: 0 | AM22: 0 | AN22: 0 | AO22: 0 | AP22: 0 | AQ22: 0 | AR22: 0 | AS22: 0 | AT22: 0 | AU22: 0 | AV22: 0 | AW22: 0 | AX22: 0 | AY22: 0 | AZ22: 0 | BA22: 0 | BB22: 0 | BC22: 0 | BD22: 0 | BE22: 0 | BF22: 0
A23: Direct air capture | B23: =MATCH("DACE1",ID_NK,0)-1 -> 0 | C23: =MATCH("DACE2",ID_NK,0)-1 -> 1 | G23: Location type (capital cost) | I23: 0 | J23: 0 | K23: 0 | L23: 0 | M23: 0 | N23: 0 | O23: 0 | P23: 0 | Q23: 0 | R23: 0 | S23: 0 | T23: 1 | U23: 2 | V23: 3 | W23: 0 | X23: 0 | Y23: 0 | Z23: 0 | AA23: 0 | AB23: 0 | AC23: 0 | AD23: 0 | AE23: 0 | AF23: 0 | AG23: 0 | AH23: 0 | AI23: 0 | AJ23: 0 | AK23: 0 | AL23: 0 | AM23: 0 | AN23: 0 | AO23: 0 | AP23: 0 | AQ23: 0 | AR23: 0 | AS23: 0 | AT23: 0 | AU23: 0 | AV23: 0 | AW23: 0 | AX23: 0 | AY23: 0 | AZ23: 0 | BA23: 0 | BB23: 0 | BC23: 0 | BD23: 0 | BE23: 0 | BF23: 0
A24: H2 carrier conversion CH4 | B24: =MATCH("NGL",ID_NK,0)-1 -> 3 | C24: =MATCH("NGV",ID_NK,0)-1 -> 4 | G24: Lifetime | I24: 25 | J24: 25 | K24: 30 | L24: 30 | M24: 30 | N24: 15 | O24: 15 | P24: 30 | Q24: 30 | R24: 40 | S24: 60 | T24: 25 | U24: 25 | V24: 25 | W24: 40 | X24: 40 | Y24: 15 | Z24: 15 | AA24: 15 | AB24: 15 | AC24: 15 | AD24: 15 | AE24: 30 | AF24: 30 | AG24: 30 | AH24: 30 | AI24: 30 | AJ24: 30 | AK24: 30 | AL24: 30 | AM24: 30 | AN24: 30 | AO24: 30 | AP24: 30 | AQ24: 30 | AR24: 30 | AS24: 30 | AT24: 30 | AU24: 30 | AV24: 30 | AW24: 30 | AX24: 30 | AY24: 30 | AZ24: 30 | BA24: 30 | BB24: 30 | BC24: 30 | BD24: 30 | BE24: 30 | BF24: 30
A25: H2 carrier conversion CH4 | B25: =MATCH("MTS",ID_NK,0)-1 -> 26 | F25: 1 | G25: Capital cost | H25: =INDEX(ID_YR,F25) -> YR2050 | I25: 933.13141 | J25: 1040.9808 | K25: 46.44 | L25: 808.06287 | M25: 0 | N25: 728.05672 | O25: 15.556768 | P25: 0.0001 | Q25: 0.20132365 | R25: 408.91984 | S25: 999999 | T25: 179.92473 | U25: 948.69404 | V25: 1570.2522 | W25: 999999 | X25: 999999 | Y25: 601.39645 | Z25: 877.57726 | AA25: 1429.9372 | AB25: 450 | AC25: 728.05672 | AD25: 15.556768 | AE25: 0.0001 | AF25: 2.72 | AG25: 1873.8204 | AH25: 0 | AI25: 750 | AJ25: 1313.6818 | AK25: 1386.6 | AL25: 718.64 | AM25: 0.0001 | AN25: 0.38596159 | AO25: 488.6846 | AP25: 965.088 | AQ25: 0.0001 | AR25: 761.90476 | AS25: 149.5 | AT25: 149.5 | AU25: 149.5 | AV25: 704.9 | AW25: 0.0001 | AX25: 0.0001 | AY25: 0 | AZ25: 0 | BA25: 0 | BB25: 0 | BC25: 0 | BD25: 0 | BE25: 0 | BF25: 0
A26: H2 carrier conversion CH4 | B26: =MATCH("MTS2",ID_NK,0)-1 -> 27 | G26: Fixed O&M ratio | I26: 0.04 | J26: 0.037 | L26: 0.04 | M26: 0.04 | N26: =AC26 -> 0.01 | O26: =AD26 -> 0.01 | P26: 0.01 | Q26: 0.01 | R26: 0.04 | S26: 0.029 | T26: =8/T25 -> 0.044463037 | U26: =30/U25 -> 0.031622419 | V26: =60/V25 -> 0.038210422 | W26: 0.035 | X26: 0.063 | Y26: =14.62/Y25 -> 0.024310087 | Z26: =22.481/Z25 -> 0.025617118 | AA26: =38.205/AA25 -> 0.026717957 | AB26: 0.015 | AC26: 0.01 | AD26: 0.01 | AE26: 0.04 | AF26: 0.04 | AG26: 0.04 | AH26: 0.04 | AI26: 0.05 | AJ26: 0.05 | AK26: 0.029 | AL26: 0.05 | AM26: 0.04 | AN26: 0.04 | AO26: 0.02391772 | AP26: 0.04 | AQ26: 0.04 | AR26: 0.04 | AS26: 0.04 | AT26: 0.04 | AU26: 0.04 | AV26: =2/530 -> 0.0037735849 | AW26: 0.04 | AX26: 0.04 | AY26: 0.04 | AZ26: 0.04 | BA26: 0.04 | BB26: 0.04 | BC26: 0.04 | BD26: 0.04 | BE26: 0.04 | BF26: 0.04
A27: H2 carrier conversion LH2 | B27: =MATCH("H2L",ID_NK,0)-1 -> 24 | C27: =MATCH("H2V",ID_NK,0)-1 -> 25
A28: H2 carrier conversion NH3 | B28: =MATCH("AMS",ID_NK,0)-1 -> 28 | C28: =MATCH("HSP",ID_NK,0)-1 -> 29 | G28: Location Factor (Availability factor/Capital cost) | I28: Type0 | J28: Type1 | K28: Type2 | L28: Type0 | M28: Type1 | N28: Type2 | O28: Type3
A29: H2 carrier conversion MCH | B29: =MATCH("MCS",ID_NK,0)-1 -> 32 | C29: =MATCH("DHG",ID_NK,0)-1 -> 33 | F29: 1 | G29: =INDEX(ID_ND,F29) -> EXP | I29: 1 | J29: 1 | K29: 1 | L29: 1 | M29: 1 | N29: 1 | O29: 1
A30: H2 and CH4 storage compressor | B30: =MATCH("NGS",ID_NK,0)-1 -> 5 | C30: =MATCH("H2S",ID_NK,0)-1 -> 20 | F30: =IF(F29+1>COUNTA(ID_ND),1,F29+1) -> 2 | G30: =INDEX(ID_ND,F30) -> IMP | I30: 1 | J30: 1 | K30: 1 | L30: 1 | M30: =880/T25 -> 4.8909341 | N30: =2070/U25 -> 2.1819469 | O30: =2380/V25 -> 1.5156801
A34: Conversion factor | G34: Existing/maximum capacity | I34: NGL | J34: NGV | K34: HYG | L34: SPG | M34: WIG1 | N34: WIG2 | O34: BDG | P34: LWR | Q34: WEL | R34: H2L | S34: MTS | T34: MTS2 | U34: AMS | V34: MCS
A35: Mtoe->TWh | B35: 11.63 | G35: ID | I35: =MATCH(I34,ID_NK,0)-1 -> 3 | J35: =MATCH(J34,ID_NK,0)-1 -> 4 | K35: =MATCH(K34,ID_NK,0)-1 -> 10 | L35: =MATCH(L34,ID_NK,0)-1 -> 11 | M35: =MATCH(M34,ID_NK,0)-1 -> 12 | N35: =MATCH(N34,ID_NK,0)-1 -> 13 | O35: =MATCH(O34,ID_NK,0)-1 -> 14 | P35: =MATCH(P34,ID_NK,0)-1 -> 15 | ... V35: =MATCH(V34,ID_NK,0)-1 -> 32
A36: TWh->PJ | B36: 3.6 | G36: Unit | I36: Mtoe/year | J36: Mtoe/year | K36: GW | L36: GW | M36: GW | N36: GW | O36: GW | P36: GW
E37: 1 | F37: 1 | G37: =INDEX(ID_YR,E37) -> YR2050 | H37: =INDEX(ID_ND,F37) -> EXP | I37: 0 | J37: 0 | K37: 0 | L37: 0 | M37: 0 | N37: 0 | O37: 0 | P37: 0 | Q37: 0 | R37: 0 | S37: 0 | T37: 0 | U37: 0 | V37: 0
E38: =IF(F38=1,E37+1,E37) -> 1 | F38: =IF(F37+1>COUNTA(ID_ND),1,F37+1) -> 2 | G38: =INDEX(ID_YR,E38) -> YR2050 | H38: =INDEX(ID_ND,F38) -> IMP | I38: 0 | J38: 0 | K38: 0 | L38: 0 | M38: 0 | N38: 0 | O38: 0 | P38: 0 | Q38: 0 | R38: 0 | S38: 0 | T38: 0 | U38: 0 | V38: 0
I39: -1 | J39: 0 | K39: -1 | L39: -1 | M39: -1 | N39: 0 | O39: 0 | P39: 0 | Q39: -1 | R39: -1 | S39: -1 | T39: -1 | U39: -1 | V39: -1
I40: 0 | J40: -1 | K40: 0 | L40: -1 | M40: -1 | N40: 0 | O40: 0 | P40: 0 | Q40: 0 | R40: 0 | S40: 0 | T40: 0 | U40: 0 | V40: 0

Sheet NK_OP
B1: Row | C1: Column | G1: Nodal Facility Maintenance Schedule [NK_MS] | H1: DY1 | I1: DY2 | J1: DY3 | K1: DY4 | L1: DY5 | M1: DY6 | N1: DY7 | O1: DY8 | P1: DY9 | Q1: DY10 | R1: DY11 | S1: DY12 | T1: DY13 | U1: DY14 | V1: DY15 | W1: DY16 | X1: DY17 | Y1: DY18 | Z1: DY19 | AA1: DY20 | AB1: DY21 | AC1: DY22 | AD1: DY23 | AE1: DY24 | AF1: DY25 | AG1: DY26 | AH1: DY27 | AI1: DY28 | AJ1: DY29 | AK1: DY30 | AL1: DY31 | AM1: DY32 | AN1: DY33 | AO1: DY34 | AP1: DY35 | AQ1: DY36 | AR1: DY37 | AS1: DY38 | AT1: DY39 | AU1: DY40 | AV1: DY41 | AW1: DY42 | AX1: DY43 | AY1: DY44 | AZ1: DY45 | BA1: DY46 | BB1: DY47 | BC1: DY48 | BD1: DY49 | BE1: DY50 | BF1: DY51 | BG1: DY52 | BH1: DY53 | BI1: DY54 | BJ1: DY55 | BK1: DY56 | BL1: DY57 | BM1: DY58 | BN1: DY59 | BO1: DY60 | BP1: DY61 | BQ1: DY62 | BR1: DY63 | BS1: DY64 | BT1: DY65 | BU1: DY66 | BV1: DY67 | BW1: DY68 | BX1: DY69 | BY1: DY70 | BZ1: DY71 | CA1: DY72 | CB1: DY73 | CC1: DY74 | CD1: DY75 | CE1: DY76 | CF1: DY77 | CG1: DY78 | CH1: DY79 | CI1: DY80 | CJ1: DY81 | CK1: DY82 | CL1: DY83 | CM1: DY84 | CN1: DY85 | CO1: DY86 | CP1: DY87 | CQ1: DY88 | CR1: DY89 | CS1: DY90 | CT1: DY91 | CU1: DY92 | CV1: DY93 | CW1: DY94 | CX1: DY95 | CY1: DY96 | CZ1: DY97 | DA1: DY98 | DB1: DY99 | DC1: DY100 | DD1: DY101 | DE1: DY102 | DF1: DY103 | DG1: DY104 | DH1: DY105 | DI1: DY106 | DJ1: DY107 | DK1: DY108 | DL1: DY109 | DM1: DY110 | DN1: DY111 | DO1: DY112 | DP1: DY113 | DQ1: DY114 | DR1: DY115 | DS1: DY116 | DT1: DY117 | DU1: DY118 | DV1: DY119 | DW1: DY120 | DX1: DY121 | DY1: DY122 | DZ1: DY123 | EA1: DY124 | EB1: DY125 | EC1: DY126 | ED1: DY127 | EE1: DY128 | EF1: DY129 | EG1: DY130 | EH1: DY131 | EI1: DY132 | EJ1: DY133 | EK1: DY134 | EL1: DY135 | EM1: DY136 | EN1: DY137 | EO1: DY138 | EP1: DY139 | EQ1: DY140 | ER1: DY141 | ES1: DY142 | ET1: DY143 | EU1: DY144 | EV1: DY145 | EW1: DY146 | EX1: DY147 | EY1: DY148 | EZ1: DY149 | FA1: DY150 | FB1: DY151 | FC1: DY152 | FD1: DY153 | FE1: DY154 | FF1: DY155 | FG1: DY156 | FH1: DY157 | FI1: DY158 | FJ1: DY159 | FK1: DY160 | FL1: DY161 | FM1: DY162 | FN1: DY163 | FO1: DY164 | FP1: DY165 | FQ1: DY166 | FR1: DY167 | FS1: DY168 | FT1: DY169 | FU1: DY170 | FV1: DY171 | FW1: DY172 | FX1: DY173 | FY1: DY174 | FZ1: DY175 | GA1: DY176 | GB1: DY177 | GC1: DY178 | GD1: DY179 | GE1: DY180 | GF1: DY181 | GG1: DY182 | GH1: DY183 | GI1: DY184 | GJ1: DY185 | GK1: DY186 | GL1: DY187 | GM1: DY188 | GN1: DY189 | GO1: DY190 | GP1: DY191 | GQ1: DY192 | GR1: DY193 | GS1: DY194 | GT1: DY195 | GU1: DY196 | GV1: DY197 | GW1: DY198 | GX1: DY199 | GY1: DY200 | GZ1: DY201 | HA1: DY202 | HB1: DY203 | HC1: DY204 | HD1: DY205 | HE1: DY206 | HF1: DY207 | HG1: DY208 | HH1: DY209 | HI1: DY210 | HJ1: DY211 | HK1: DY212 | HL1: DY213 | HM1: DY214 | HN1: DY215 | HO1: DY216 | HP1: DY217 | HQ1: DY218 | HR1: DY219 | HS1: DY220 | HT1: DY221 | HU1: DY222 | HV1: DY223 | HW1: DY224 | HX1: DY225 | HY1: DY226 | HZ1: DY227 | IA1: DY228 | IB1: DY229 | IC1: DY230 | ID1: DY231 | IE1: DY232 | IF1: DY233 | IG1: DY234 | IH1: DY235 | II1: DY236 | IJ1: DY237 | IK1: DY238 | IL1: DY239 | IM1: DY240 | IN1: DY241 | IO1: DY242 | IP1: DY243 | IQ1: DY244 | IR1: DY245 | IS1: DY246 | IT1: DY247 | IU1: DY248 | IV1: DY249 | IW1: DY250 | IX1: DY251 | IY1: DY252 | IZ1: DY253 | JA1: DY254 | JB1: DY255 | JC1: DY256 | JD1: DY257 | JE1: DY258 | JF1: DY259 | JG1: DY260 | JH1: DY261 | JI1: DY262 | JJ1: DY263 | JK1: DY264 | JL1: DY265 | JM1: DY266 | JN1: DY267 | JO1: DY268 | JP1: DY269 | JQ1: DY270 | JR1: DY271 | JS1: DY272 | JT1: DY273 | JU1: DY274 | JV1: DY275 | JW1: DY276 | JX1: DY277 | JY1: DY278 | JZ1: DY279 | KA1: DY280 | KB1: DY281 | KC1: DY282 | KD1: DY283 | KE1: DY284 | KF1: DY285 | KG1: DY286 | KH1: DY287 | KI1: DY288 | KJ1: DY289 | KK1: DY290 | KL1: DY291 | KM1: DY292 | KN1: DY293 | KO1: DY294 | KP1: DY295 | KQ1: DY296 | KR1: DY297 | KS1: DY298 | KT1: DY299 | KU1: DY300 | KV1: DY301 | KW1: DY302 | KX1: DY303 | KY1: DY304 | KZ1: DY305 | LA1: DY306 | LB1: DY307 | LC1: DY308 | LD1: DY309 | LE1: DY310 | LF1: DY311 | LG1: DY312 | LH1: DY313 | LI1: DY314 | LJ1: DY315 | LK1: DY316 | LL1: DY317 | LM1: DY318 | LN1: DY319 | LO1: DY320 | LP1: DY321 | LQ1: DY322 | LR1: DY323 | LS1: DY324 | LT1: DY325 | LU1: DY326 | LV1: DY327 | LW1: DY328 | LX1: DY329 | LY1: DY330 | LZ1: DY331 | MA1: DY332 | MB1: DY333 | MC1: DY334 | MD1: DY335 | ME1: DY336 | MF1: DY337 | MG1: DY338 | MH1: DY339 | MI1: DY340 | MJ1: DY341 | MK1: DY342 | ML1: DY343 | MM1: DY344 | MN1: DY345 | MO1: DY346 | MP1: DY347 | MQ1: DY348 | MR1: DY349 | MS1: DY350 | MT1: DY351 | MU1: DY352 | MV1: DY353 | MW1: DY354 | MX1: DY355 | MY1: DY356 | MZ1: DY357 | NA1: DY358 | NB1: DY359 | NC1: DY360 | ND1: DY361 | NE1: DY362 | NF1: DY363 | NG1: DY364 | NH1: DY365
A2: NK_MSI | B2: =ROWS(NK_MSI) -> 1 | C2: =COLUMNS(NK_MSI) -> 365 | G2: Day ID | H2: =MATCH(H1,ID_DY,0)-1 -> 0 | I2: =MATCH(I1,ID_DY,0)-1 -> 1 | J2: =MATCH(J1,ID_DY,0)-1 -> 2 | K2: =MATCH(K1,ID_DY,0)-1 -> 3 | L2: =MATCH(L1,ID_DY,0)-1 -> 4 | M2: =MATCH(M1,ID_DY,0)-1 -> 5 | N2: =MATCH(N1,ID_DY,0)-1 -> 6 | O2: =MATCH(O1,ID_DY,0)-1 -> 7 | ... NH2: =MATCH(NH1,ID_DY,0)-1 -> 364
A3: NK_MSD | B3: =ROWS(NK_MSD) -> 4 | C3: =COLUMNS(NK_MSD) -> 365 | G3: Maintenance 1 | H3: 1 | I3: 1 | J3: 1 | K3: 1 | L3: 1 | M3: 1 | N3: 1 | O3: 1 | P3: 1 | Q3: 1 | R3: 1 | S3: 1 | T3: 1 | U3: 1 | V3: 1 | W3: 1 | X3: 1 | Y3: 1 | Z3: 1 | AA3: 1 | AB3: 1 | AC3: 1 | AD3: 1 | AE3: 1 | AF3: 1 | AG3: 1 | AH3: 1 | AI3: 1 | AJ3: 1 | AK3: 1 | AL3: 1 | AM3: 1 | AN3: 1 | AO3: 1 | AP3: 1 | AQ3: 1 | AR3: 1 | AS3: 1 | AT3: 1 | AU3: 1 | AV3: 1 | AW3: 1 | AX3: 1 | AY3: 1 | AZ3: 1 | BA3: 1 | BB3: 1 | BC3: 1 | BD3: 1 | BE3: 1 | BF3: 1 | BG3: 1 | BH3: 1 | BI3: 1 | BJ3: 1 | BK3: 1 | BL3: 1 | BM3: 1 | BN3: 1 | BO3: 1 | BP3: 0.96666667 | BQ3: 0.93333333 | BR3: 0.9 | BS3: 0.86666667 | BT3: 0.83333333 | BU3: 0.8 | BV3: 0.76666667 | BW3: 0.73333333 | BX3: 0.7 | BY3: 0.66666667 | BZ3: 0.63333333 | CA3: 0.6 | CB3: 0.56666667 | CC3: 0.53333333 | CD3: 0.5 | CE3: 0.46666667 | CF3: 0.43333333 | CG3: 0.4 | CH3: 0.36666667 | CI3: 0.33333333 | CJ3: 0.3 | CK3: 0.26666667 | CL3: 0.23333333 | CM3: 0.2 | CN3: 0.16666667 | CO3: 0.13333333 | CP3: 0.1 | CQ3: 0.066666667 | CR3: 0.033333333 | CS3: 2.0816682e-16 | CT3: 0 | CU3: 0 | CV3: 0 | CW3: 0 | CX3: 0 | CY3: 0 | CZ3: 0 | DA3: 0 | DB3: 0 | DC3: 0 | DD3: 0 | DE3: 0 | DF3: 0 | DG3: 0 | DH3: 0 | DI3: 0 | DJ3: 0 | DK3: 0 | DL3: 0 | DM3: 0 | DN3: 0 | DO3: 0 | DP3: 0 | DQ3: 0 | DR3: 0 | DS3: 0 | DT3: 0 | DU3: 0 | DV3: 0 | DW3: 0 | DX3: 0 | DY3: 0 | DZ3: 0 | EA3: 0 | EB3: 0 | EC3: 0 | ED3: 0 | EE3: 0 | EF3: 0 | EG3: 0 | EH3: 0 | EI3: 0 | EJ3: 0 | EK3: 0 | EL3: 0 | EM3: 0 | EN3: 0 | EO3: 0 | EP3: 0 | EQ3: 0 | ER3: 0 | ES3: 0 | ET3: 0 | EU3: 0 | EV3: 0 | EW3: 0 | EX3: 0 | EY3: 0 | EZ3: 0 | FA3: 0 | FB3: 0 | FC3: 0 | FD3: 0 | FE3: 0 | FF3: 0 | FG3: 0 | FH3: 0 | FI3: 0 | FJ3: 0 | FK3: 0 | FL3: 0 | FM3: 0 | FN3: 0 | FO3: 0 | FP3: 0 | FQ3: 0 | FR3: 0 | FS3: 0 | FT3: 0 | FU3: 0 | FV3: 0 | FW3: 0 | FX3: 0 | FY3: 0 | FZ3: 0 | GA3: 0 | GB3: 0 | GC3: 0 | GD3: 0 | GE3: 0 | GF3: 0 | GG3: 0 | GH3: 0 | GI3: 0 | GJ3: 0 | GK3: 0 | GL3: 0 | GM3: 0 | GN3: 0 | GO3: 0 | GP3: 0 | GQ3: 0 | GR3: 0 | GS3: 0 | GT3: 0 | GU3: 0 | GV3: 0 | GW3: 0 | GX3: 0 | GY3: 0 | GZ3: 0 | HA3: 0 | HB3: 0 | HC3: 0 | HD3: 0 | HE3: 0 | HF3: 0 | HG3: 0 | HH3: 0 | HI3: 0 | HJ3: 0 | HK3: 0 | HL3: 0 | HM3: 0 | HN3: 0 | HO3: 0 | HP3: 0 | HQ3: 0 | HR3: 0 | HS3: 0 | HT3: 0 | HU3: 0 | HV3: 0 | HW3: 0 | HX3: 0 | HY3: 0 | HZ3: 0 | IA3: 0 | IB3: 0 | IC3: 0 | ID3: 0 | IE3: 0 | IF3: 0 | IG3: 0 | IH3: 0 | II3: 0 | IJ3: 0 | IK3: 0 | IL3: 0 | IM3: 0 | IN3: 0 | IO3: 0 | IP3: 0 | IQ3: 0 | IR3: 0 | IS3: 0 | IT3: 0 | IU3: 0 | IV3: 0 | IW3: 0 | IX3: 0 | IY3: 0 | IZ3: 0 | JA3: 0 | JB3: 0 | JC3: 0 | JD3: 0 | JE3: 0 | JF3: 0 | JG3: 0 | JH3: 0 | JI3: 0 | JJ3: 0 | JK3: 0 | JL3: 0 | JM3: 0 | JN3: 0 | JO3: 0 | JP3: 0 | JQ3: 0 | JR3: 0 | JS3: 0 | JT3: 0 | JU3: 0 | JV3: 0 | JW3: 0 | JX3: 0 | JY3: 0 | JZ3: 0 | KA3: 0 | KB3: 0 | KC3: 0 | KD3: 0 | KE3: 0 | KF3: 0 | KG3: 0 | KH3: 0 | KI3: 0 | KJ3: 0 | KK3: 0 | KL3: 0 | KM3: 0 | KN3: 0 | KO3: 0 | KP3: 0 | KQ3: 0 | KR3: 0 | KS3: 0 | KT3: 0 | KU3: 0 | KV3: 0 | KW3: 0 | KX3: 0 | KY3: 0 | KZ3: 0 | LA3: 0 | LB3: 0 | LC3: 0 | LD3: 0 | LE3: 0 | LF3: 0 | LG3: 0 | LH3: 0 | LI3: 0 | LJ3: 0 | LK3: 0 | LL3: 0 | LM3: 0 | LN3: 0 | LO3: 0 | LP3: 0 | LQ3: 0 | LR3: 0 | LS3: 0 | LT3: 0 | LU3: 0 | LV3: 0 | LW3: 0 | LX3: 0 | LY3: 0 | LZ3: 0 | MA3: 0 | MB3: 0 | MC3: 0 | MD3: 0 | ME3: 0 | MF3: 0.033333333 | MG3: 0.066666667 | MH3: 0.1 | MI3: 0.13333333 | MJ3: 0.16666667 | MK3: 0.2 | ML3: 0.23333333 | MM3: 0.26666667 | MN3: 0.3 | MO3: 0.33333333 | MP3: 0.36666667 | MQ3: 0.4 | MR3: 0.43333333 | MS3: 0.46666667 | MT3: 0.5 | MU3: 0.53333333 | MV3: 0.56666667 | MW3: 0.6 | MX3: 0.63333333 | MY3: 0.66666667 | MZ3: 0.7 | NA3: 0.73333333 | NB3: 0.76666667 | NC3: 0.8 | ND3: 0.83333333 | NE3: 0.86666667 | NF3: 0.9 | NG3: 0.93333333 | NH3: 0.96666667
A4: NK_OPI | B4: =ROWS(NK_OPI) -> 1 | C4: =COLUMNS(NK_OPI) -> 10 | G4: Maintenance 2 | H4: 0 | I4: 0 | J4: 0 | K4: 0 | L4: 0 | M4: 0 | N4: 0 | O4: 0 | P4: 0 | Q4: 0 | R4: 0 | S4: 0 | T4: 0 | U4: 0 | V4: 0 | W4: 0 | X4: 0 | Y4: 0 | Z4: 0 | AA4: 0 | AB4: 0 | AC4: 0 | AD4: 0 | AE4: 0 | AF4: 0 | AG4: 0 | AH4: 0 | AI4: 0 | AJ4: 0 | AK4: 0 | AL4: 0 | AM4: 0 | AN4: 0 | AO4: 0 | AP4: 0 | AQ4: 0 | AR4: 0 | AS4: 0 | AT4: 0 | AU4: 0 | AV4: 0 | AW4: 0 | AX4: 0 | AY4: 0 | AZ4: 0 | BA4: 0 | BB4: 0 | BC4: 0 | BD4: 0 | BE4: 0 | BF4: 0 | BG4: 0 | BH4: 0 | BI4: 0 | BJ4: 0 | BK4: 0 | BL4: 0 | BM4: 0 | BN4: 0 | BO4: 0 | BP4: 0.033333333 | BQ4: 0.066666667 | BR4: 0.1 | BS4: 0.13333333 | BT4: 0.16666667 | BU4: 0.2 | BV4: 0.23333333 | BW4: 0.26666667 | BX4: 0.3 | BY4: 0.33333333 | BZ4: 0.36666667 | CA4: 0.4 | CB4: 0.43333333 | CC4: 0.46666667 | CD4: 0.5 | CE4: 0.53333333 | CF4: 0.56666667 | CG4: 0.6 | CH4: 0.63333333 | CI4: 0.66666667 | CJ4: 0.7 | CK4: 0.73333333 | CL4: 0.76666667 | CM4: 0.8 | CN4: 0.83333333 | CO4: 0.86666667 | CP4: 0.9 | CQ4: 0.93333333 | CR4: 0.96666667 | CS4: 1 | CT4: 1 | CU4: 1 | CV4: 1 | CW4: 1 | CX4: 1 | CY4: 1 | CZ4: 1 | DA4: 1 | DB4: 1 | DC4: 1 | DD4: 1 | DE4: 1 | DF4: 1 | DG4: 1 | DH4: 1 | DI4: 1 | DJ4: 1 | DK4: 1 | DL4: 1 | DM4: 1 | DN4: 1 | DO4: 1 | DP4: 1 | DQ4: 1 | DR4: 1 | DS4: 1 | DT4: 1 | DU4: 1 | DV4: 1 | DW4: 1 | DX4: 1 | DY4: 1 | DZ4: 1 | EA4: 1 | EB4: 1 | EC4: 1 | ED4: 1 | EE4: 1 | EF4: 1 | EG4: 1 | EH4: 1 | EI4: 1 | EJ4: 1 | EK4: 1 | EL4: 1 | EM4: 1 | EN4: 1 | EO4: 1 | EP4: 1 | EQ4: 1 | ER4: 1 | ES4: 1 | ET4: 1 | EU4: 1 | EV4: 1 | EW4: 1 | EX4: 1 | EY4: 1 | EZ4: 1 | FA4: 1 | FB4: 1 | FC4: 1 | FD4: 1 | FE4: 1 | FF4: 0.96666667 | FG4: 0.93333333 | FH4: 0.9 | FI4: 0.86666667 | FJ4: 0.83333333 | FK4: 0.8 | FL4: 0.76666667 | FM4: 0.73333333 | FN4: 0.7 | FO4: 0.66666667 | FP4: 0.63333333 | FQ4: 0.6 | FR4: 0.56666667 | FS4: 0.53333333 | FT4: 0.5 | FU4: 0.46666667 | FV4: 0.43333333 | FW4: 0.4 | FX4: 0.36666667 | FY4: 0.33333333 | FZ4: 0.3 | GA4: 0.26666667 | GB4: 0.23333333 | GC4: 0.2 | GD4: 0.16666667 | GE4: 0.13333333 | GF4: 0.1 | GG4: 0.066666667 | GH4: 0.033333333 | GI4: 0 | GJ4: 0 | GK4: 0 | GL4: 0 | GM4: 0 | GN4: 0 | GO4: 0 | GP4: 0 | GQ4: 0 | GR4: 0 | GS4: 0 | GT4: 0 | GU4: 0 | GV4: 0 | GW4: 0 | GX4: 0 | GY4: 0 | GZ4: 0 | HA4: 0 | HB4: 0 | HC4: 0 | HD4: 0 | HE4: 0 | HF4: 0 | HG4: 0 | HH4: 0 | HI4: 0 | HJ4: 0 | HK4: 0 | HL4: 0 | HM4: 0 | HN4: 0 | HO4: 0 | HP4: 0 | HQ4: 0 | HR4: 0 | HS4: 0 | HT4: 0 | HU4: 0 | HV4: 0 | HW4: 0 | HX4: 0 | HY4: 0 | HZ4: 0 | IA4: 0 | IB4: 0 | IC4: 0 | ID4: 0 | IE4: 0 | IF4: 0 | IG4: 0 | IH4: 0 | II4: 0 | IJ4: 0 | IK4: 0 | IL4: 0 | IM4: 0 | IN4: 0 | IO4: 0 | IP4: 0 | IQ4: 0 | IR4: 0 | IS4: 0 | IT4: 0 | IU4: 0 | IV4: 0 | IW4: 0 | IX4: 0 | IY4: 0 | IZ4: 0 | JA4: 0 | JB4: 0 | JC4: 0 | JD4: 0 | JE4: 0 | JF4: 0 | JG4: 0 | JH4: 0 | JI4: 0 | JJ4: 0 | JK4: 0 | JL4: 0 | JM4: 0 | JN4: 0 | JO4: 0 | JP4: 0 | JQ4: 0 | JR4: 0 | JS4: 0 | JT4: 0 | JU4: 0 | JV4: 0 | JW4: 0 | JX4: 0 | JY4: 0 | JZ4: 0 | KA4: 0 | KB4: 0 | KC4: 0 | KD4: 0 | KE4: 0 | KF4: 0 | KG4: 0 | KH4: 0 | KI4: 0 | KJ4: 0 | KK4: 0 | KL4: 0 | KM4: 0 | KN4: 0 | KO4: 0 | KP4: 0 | KQ4: 0 | KR4: 0 | KS4: 0 | KT4: 0 | KU4: 0 | KV4: 0 | KW4: 0 | KX4: 0 | KY4: 0 | KZ4: 0 | LA4: 0 | LB4: 0 | LC4: 0 | LD4: 0 | LE4: 0 | LF4: 0 | LG4: 0 | LH4: 0 | LI4: 0 | LJ4: 0 | LK4: 0 | LL4: 0 | LM4: 0 | LN4: 0 | LO4: 0 | LP4: 0 | LQ4: 0 | LR4: 0 | LS4: 0 | LT4: 0 | LU4: 0 | LV4: 0 | LW4: 0 | LX4: 0 | LY4: 0 | LZ4: 0 | MA4: 0 | MB4: 0 | MC4: 0 | MD4: 0 | ME4: 0 | MF4: 0 | MG4: 0 | MH4: 0 | MI4: 0 | MJ4: 0 | MK4: 0 | ML4: 0 | MM4: 0 | MN4: 0 | MO4: 0 | MP4: 0 | MQ4: 0 | MR4: 0 | MS4: 0 | MT4: 0 | MU4: 0 | MV4: 0 | MW4: 0 | MX4: 0 | MY4: 0 | MZ4: 0 | NA4: 0 | NB4: 0 | NC4: 0 | ND4: 0 | NE4: 0 | NF4: 0 | NG4: 0 | NH4: 0
A5: NK_OPD | B5: =ROWS(NK_OPD) -> 4 | C5: =COLUMNS(NK_OPD) -> 10 | G5: Maintenance 3 | H5: 0 | I5: 0 | J5: 0 | K5: 0 | L5: 0 | M5: 0 | N5: 0 | O5: 0 | P5: 0 | Q5: 0 | R5: 0 | S5: 0 | T5: 0 | U5: 0 | V5: 0 | W5: 0 | X5: 0 | Y5: 0 | Z5: 0 | AA5: 0 | AB5: 0 | AC5: 0 | AD5: 0 | AE5: 0 | AF5: 0 | AG5: 0 | AH5: 0 | AI5: 0 | AJ5: 0 | AK5: 0 | AL5: 0 | AM5: 0 | AN5: 0 | AO5: 0 | AP5: 0 | AQ5: 0 | AR5: 0 | AS5: 0 | AT5: 0 | AU5: 0 | AV5: 0 | AW5: 0 | AX5: 0 | AY5: 0 | AZ5: 0 | BA5: 0 | BB5: 0 | BC5: 0 | BD5: 0 | BE5: 0 | BF5: 0 | BG5: 0 | BH5: 0 | BI5: 0 | BJ5: 0 | BK5: 0 | BL5: 0 | BM5: 0 | BN5: 0 | BO5: 0 | BP5: 0 | BQ5: 0 | BR5: 0 | BS5: 0 | BT5: 0 | BU5: 0 | BV5: 0 | BW5: 0 | BX5: 0 | BY5: 0 | BZ5: 0 | CA5: 0 | CB5: 0 | CC5: 0 | CD5: 0 | CE5: 0 | CF5: 0 | CG5: 0 | CH5: 0 | CI5: 0 | CJ5: 0 | CK5: 0 | CL5: 0 | CM5: 0 | CN5: 0 | CO5: 0 | CP5: 0 | CQ5: 0 | CR5: 0 | CS5: 0 | CT5: 0 | CU5: 0 | CV5: 0 | CW5: 0 | CX5: 0 | CY5: 0 | CZ5: 0 | DA5: 0 | DB5: 0 | DC5: 0 | DD5: 0 | DE5: 0 | DF5: 0 | DG5: 0 | DH5: 0 | DI5: 0 | DJ5: 0 | DK5: 0 | DL5: 0 | DM5: 0 | DN5: 0 | DO5: 0 | DP5: 0 | DQ5: 0 | DR5: 0 | DS5: 0 | DT5: 0 | DU5: 0 | DV5: 0 | DW5: 0 | DX5: 0 | DY5: 0 | DZ5: 0 | EA5: 0 | EB5: 0 | EC5: 0 | ED5: 0 | EE5: 0 | EF5: 0 | EG5: 0 | EH5: 0 | EI5: 0 | EJ5: 0 | EK5: 0 | EL5: 0 | EM5: 0 | EN5: 0 | EO5: 0 | EP5: 0 | EQ5: 0 | ER5: 0 | ES5: 0 | ET5: 0 | EU5: 0 | EV5: 0 | EW5: 0 | EX5: 0 | EY5: 0 | EZ5: 0 | FA5: 0 | FB5: 0 | FC5: 0 | FD5: 0 | FE5: 0 | FF5: 0.033333333 | FG5: 0.066666667 | FH5: 0.1 | FI5: 0.13333333 | FJ5: 0.16666667 | FK5: 0.2 | FL5: 0.23333333 | FM5: 0.26666667 | FN5: 0.3 | FO5: 0.33333333 | FP5: 0.36666667 | FQ5: 0.4 | FR5: 0.43333333 | FS5: 0.46666667 | FT5: 0.5 | FU5: 0.53333333 | FV5: 0.56666667 | FW5: 0.6 | FX5: 0.63333333 | FY5: 0.66666667 | FZ5: 0.7 | GA5: 0.73333333 | GB5: 0.76666667 | GC5: 0.8 | GD5: 0.83333333 | GE5: 0.86666667 | GF5: 0.9 | GG5: 0.93333333 | GH5: 0.96666667 | GI5: 1 | GJ5: 1 | GK5: 1 | GL5: 1 | GM5: 1 | GN5: 1 | GO5: 1 | GP5: 1 | GQ5: 1 | GR5: 1 | GS5: 1 | GT5: 1 | GU5: 1 | GV5: 1 | GW5: 1 | GX5: 1 | GY5: 1 | GZ5: 1 | HA5: 1 | HB5: 1 | HC5: 1 | HD5: 1 | HE5: 1 | HF5: 1 | HG5: 1 | HH5: 1 | HI5: 1 | HJ5: 1 | HK5: 1 | HL5: 1 | HM5: 1 | HN5: 1 | HO5: 1 | HP5: 1 | HQ5: 1 | HR5: 1 | HS5: 1 | HT5: 1 | HU5: 1 | HV5: 1 | HW5: 1 | HX5: 1 | HY5: 1 | HZ5: 1 | IA5: 1 | IB5: 1 | IC5: 1 | ID5: 1 | IE5: 1 | IF5: 1 | IG5: 1 | IH5: 1 | II5: 1 | IJ5: 1 | IK5: 1 | IL5: 1 | IM5: 1 | IN5: 1 | IO5: 1 | IP5: 1 | IQ5: 0.96666667 | IR5: 0.93333333 | IS5: 0.9 | IT5: 0.86666667 | IU5: 0.83333333 | IV5: 0.8 | IW5: 0.76666667 | IX5: 0.73333333 | IY5: 0.7 | IZ5: 0.66666667 | JA5: 0.63333333 | JB5: 0.6 | JC5: 0.56666667 | JD5: 0.53333333 | JE5: 0.5 | JF5: 0.46666667 | JG5: 0.43333333 | JH5: 0.4 | JI5: 0.36666667 | JJ5: 0.33333333 | JK5: 0.3 | JL5: 0.26666667 | JM5: 0.23333333 | JN5: 0.2 | JO5: 0.16666667 | JP5: 0.13333333 | JQ5: 0.1 | JR5: 0.066666667 | JS5: 0.033333333 | JT5: 0 | JU5: 0 | JV5: 0 | JW5: 0 | JX5: 0 | JY5: 0 | JZ5: 0 | KA5: 0 | KB5: 0 | KC5: 0 | KD5: 0 | KE5: 0 | KF5: 0 | KG5: 0 | KH5: 0 | KI5: 0 | KJ5: 0 | KK5: 0 | KL5: 0 | KM5: 0 | KN5: 0 | KO5: 0 | KP5: 0 | KQ5: 0 | KR5: 0 | KS5: 0 | KT5: 0 | KU5: 0 | KV5: 0 | KW5: 0 | KX5: 0 | KY5: 0 | KZ5: 0 | LA5: 0 | LB5: 0 | LC5: 0 | LD5: 0 | LE5: 0 | LF5: 0 | LG5: 0 | LH5: 0 | LI5: 0 | LJ5: 0 | LK5: 0 | LL5: 0 | LM5: 0 | LN5: 0 | LO5: 0 | LP5: 0 | LQ5: 0 | LR5: 0 | LS5: 0 | LT5: 0 | LU5: 0 | LV5: 0 | LW5: 0 | LX5: 0 | LY5: 0 | LZ5: 0 | MA5: 0 | MB5: 0 | MC5: 0 | MD5: 0 | ME5: 0 | MF5: 0 | MG5: 0 | MH5: 0 | MI5: 0 | MJ5: 0 | MK5: 0 | ML5: 0 | MM5: 0 | MN5: 0 | MO5: 0 | MP5: 0 | MQ5: 0 | MR5: 0 | MS5: 0 | MT5: 0 | MU5: 0 | MV5: 0 | MW5: 0 | MX5: 0 | MY5: 0 | MZ5: 0 | NA5: 0 | NB5: 0 | NC5: 0 | ND5: 0 | NE5: 0 | NF5: 0 | NG5: 0 | NH5: 0
G6: Maintenance 4 | H6: =1-SUM(H3:H5) -> 0 | I6: =1-SUM(I3:I5) -> 0 | J6: =1-SUM(J3:J5) -> 0 | K6: =1-SUM(K3:K5) -> 0 | L6: =1-SUM(L3:L5) -> 0 | M6: =1-SUM(M3:M5) -> 0 | N6: =1-SUM(N3:N5) -> 0 | O6: =1-SUM(O3:O5) -> 0 | ... NH6: =1-SUM(NH3:NH5) -> 0.033333333
G11: Nodal Facility Operational Information [NK_OP] | H11: NGL | I11: GTG | J11: BDG | K11: LWR | L11: WEL | M11: H2L | N11: MTS | O11: MTS2 | P11: AMS | Q11: MCS
G12: NK ID | H12: =MATCH(H11,ID_NK,0)-1 -> 3 | I12: =MATCH(I11,ID_NK,0)-1 -> 9 | J12: =MATCH(J11,ID_NK,0)-1 -> 14 | K12: =MATCH(K11,ID_NK,0)-1 -> 15 | L12: =MATCH(L11,ID_NK,0)-1 -> 19 | M12: =MATCH(M11,ID_NK,0)-1 -> 24 | N12: =MATCH(N11,ID_NK,0)-1 -> 26 | O12: =MATCH(O11,ID_NK,0)-1 -> 27 | ... Q12: =MATCH(Q11,ID_NK,0)-1 -> 32
G13: Ramping up rate [/hour] | H13: 1 | I13: 1 | J13: 0.31 | K13: 0 | L13: 1 | M13: 1 | N13: 1 | O13: 0.1 | P13: 1 | Q13: 1
G14: Ramping down rate [/hour] | H14: 1 | I14: 1 | J14: 0.58 | K14: 0 | L14: 1 | M14: 1 | N14: 1 | O14: 0.1 | P14: 1 | Q14: 1
G15: Share of DSS | H15: 1 | I15: 0 | J15: 0 | K15: 0 | L15: 1 | M15: 1 | N15: 1 | O15: 1 | P15: 1 | Q15: 1
G16: Minimum output rate | H16: 0 | I16: 0 | J16: 0.3 | K16: 1 | L16: 0 | M16: 0 | N16: 0 | O16: 0 | P16: 0 | Q16: 0

Sheet NK_TP
B1: Row | C1: Column | G1: Nodal Facility Time Profile [NK_TP] | H1: DY1 | I1: DY1 | J1: DY1 | K1: DY1 | L1: DY1 | M1: DY1 | N1: DY1 | O1: DY1 | P1: DY1 | Q1: DY1 | R1: DY1 | S1: DY1 | T1: DY1 | U1: DY1 | V1: DY1 | W1: DY1 | X1: DY1 | Y1: DY1 | Z1: DY1 | AA1: DY1 | AB1: DY1 | AC1: DY1 | AD1: DY1 | AE1: DY1 | AF1: DY2 | AG1: DY2 | AH1: DY2 | AI1: DY2 | AJ1: DY2 | AK1: DY2 | AL1: DY2 | AM1: DY2 | AN1: DY2 | AO1: DY2 | AP1: DY2 | AQ1: DY2 | AR1: DY2 | AS1: DY2 | AT1: DY2 | AU1: DY2 | AV1: DY2 | AW1: DY2 | AX1: DY2 | AY1: DY2 | AZ1: DY2 | BA1: DY2 | BB1: DY2 | BC1: DY2 | BD1: DY3 | BE1: DY3 | BF1: DY3 | BG1: DY3 | BH1: DY3 | BI1: DY3 | BJ1: DY3 | BK1: DY3 | BL1: DY3 | BM1: DY3 | BN1: DY3 | BO1: DY3 | BP1: DY3 | BQ1: DY3 | BR1: DY3 | BS1: DY3 | BT1: DY3 | BU1: DY3 | BV1: DY3 | BW1: DY3 | BX1: DY3 | BY1: DY3 | BZ1: DY3 | CA1: DY3 | CB1: DY4 | CC1: DY4 | CD1: DY4 | CE1: DY4 | CF1: DY4 | CG1: DY4 | CH1: DY4 | CI1: DY4 | CJ1: DY4 | CK1: DY4 | CL1: DY4 | CM1: DY4 | CN1: DY4 | CO1: DY4 | CP1: DY4 | CQ1: DY4 | CR1: DY4 | CS1: DY4 | CT1: DY4 | CU1: DY4 | CV1: DY4 | CW1: DY4 | CX1: DY4 | CY1: DY4 | CZ1: DY5 | DA1: DY5 | DB1: DY5 | DC1: DY5 | DD1: DY5 | DE1: DY5 | DF1: DY5 | DG1: DY5 | DH1: DY5 | DI1: DY5 | DJ1: DY5 | DK1: DY5 | DL1: DY5 | DM1: DY5 | DN1: DY5 | DO1: DY5 | DP1: DY5 | DQ1: DY5 | DR1: DY5 | DS1: DY5 | DT1: DY5 | DU1: DY5 | DV1: DY5 | DW1: DY5 | DX1: DY6 | DY1: DY6 | DZ1: DY6 | EA1: DY6 | EB1: DY6 | EC1: DY6 | ED1: DY6 | EE1: DY6 | EF1: DY6 | EG1: DY6 | EH1: DY6 | EI1: DY6 | EJ1: DY6 | EK1: DY6 | EL1: DY6 | EM1: DY6 | EN1: DY6 | EO1: DY6 | EP1: DY6 | EQ1: DY6 | ER1: DY6 | ES1: DY6 | ET1: DY6 | EU1: DY6 | EV1: DY7 | EW1: DY7 | EX1: DY7 | EY1: DY7 | EZ1: DY7 | FA1: DY7 | FB1: DY7 | FC1: DY7 | FD1: DY7 | FE1: DY7 | FF1: DY7 | FG1: DY7 | FH1: DY7 | FI1: DY7 | FJ1: DY7 | FK1: DY7 | FL1: DY7 | FM1: DY7 | FN1: DY7 | FO1: DY7 | FP1: DY7 | FQ1: DY7 | FR1: DY7 | FS1: DY7 | FT1: DY8 | FU1: DY8 | FV1: DY8 | FW1: DY8 | FX1: DY8 | FY1: DY8 | FZ1: DY8 | GA1: DY8 | GB1: DY8 | GC1: DY8 | GD1: DY8 | GE1: DY8 | GF1: DY8 | GG1: DY8 | GH1: DY8 | GI1: DY8 | GJ1: DY8 | GK1: DY8 | GL1: DY8 | GM1: DY8 | GN1: DY8 | GO1: DY8 | GP1: DY8 | GQ1: DY8 | GR1: DY9 | GS1: DY9 | GT1: DY9 | GU1: DY9 | GV1: DY9 | GW1: DY9 | GX1: DY9 | GY1: DY9 | GZ1: DY9 | HA1: DY9 | HB1: DY9 | HC1: DY9 | HD1: DY9 | HE1: DY9 | HF1: DY9 | HG1: DY9 | HH1: DY9 | HI1: DY9 | HJ1: DY9 | HK1: DY9 | HL1: DY9 | HM1: DY9 | HN1: DY9 | HO1: DY9 | HP1: DY10 | HQ1: DY10 | HR1: DY10 | HS1: DY10 | HT1: DY10 | HU1: DY10 | HV1: DY10 | HW1: DY10 | HX1: DY10 | HY1: DY10 | HZ1: DY10 | IA1: DY10 | IB1: DY10 | IC1: DY10 | ID1: DY10 | IE1: DY10 | IF1: DY10 | IG1: DY10 | IH1: DY10 | II1: DY10 | IJ1: DY10 | IK1: DY10 | IL1: DY10 | IM1: DY10 | IN1: DY11 | IO1: DY11 | IP1: DY11 | IQ1: DY11 | IR1: DY11 | IS1: DY11 | IT1: DY11 | IU1: DY11 | IV1: DY11 | IW1: DY11 | IX1: DY11 | IY1: DY11 | IZ1: DY11 | JA1: DY11 | JB1: DY11 | JC1: DY11 | JD1: DY11 | JE1: DY11 | JF1: DY11 | JG1: DY11 | JH1: DY11 | JI1: DY11 | JJ1: DY11 | JK1: DY11 | JL1: DY12 | JM1: DY12 | JN1: DY12 | JO1: DY12 | JP1: DY12 | JQ1: DY12 | JR1: DY12 | JS1: DY12 | JT1: DY12 | JU1: DY12 | JV1: DY12 | JW1: DY12 | JX1: DY12 | JY1: DY12 | JZ1: DY12 | KA1: DY12 | KB1: DY12 | KC1: DY12 | KD1: DY12 | KE1: DY12 | KF1: DY12 | KG1: DY12 | KH1: DY12 | KI1: DY12 | KJ1: DY13 | KK1: DY13 | KL1: DY13 | KM1: DY13 | KN1: DY13 | KO1: DY13 | KP1: DY13 | KQ1: DY13 | KR1: DY13 | KS1: DY13 | KT1: DY13 | KU1: DY13 | KV1: DY13 | KW1: DY13 | KX1: DY13 | KY1: DY13 | KZ1: DY13 | LA1: DY13 | LB1: DY13 | LC1: DY13 | LD1: DY13 | LE1: DY13 | LF1: DY13 | LG1: DY13 | LH1: DY14 | LI1: DY14 | LJ1: DY14 | LK1: DY14 | LL1: DY14 | LM1: DY14 | LN1: DY14 | LO1: DY14 | LP1: DY14 | LQ1: DY14 | LR1: DY14 | LS1: DY14 | LT1: DY14 | LU1: DY14 | LV1: DY14 | LW1: DY14 | LX1: DY14 | LY1: DY14 | LZ1: DY14 | MA1: DY14 | MB1: DY14 | MC1: DY14 | MD1: DY14 | ME1: DY14 | MF1: DY15 | MG1: DY15 | MH1: DY15 | MI1: DY15 | MJ1: DY15 | MK1: DY15 | ML1: DY15 | MM1: DY15 | MN1: DY15 | MO1: DY15 | MP1: DY15 | MQ1: DY15 | MR1: DY15 | MS1: DY15 | MT1: DY15 | MU1: DY15 | MV1: DY15 | MW1: DY15 | MX1: DY15 | MY1: DY15 | MZ1: DY15 | NA1: DY15 | NB1: DY15 | NC1: DY15 | ND1: DY16 | NE1: DY16 | NF1: DY16 | NG1: DY16 | NH1: DY16 | NI1: DY16 | NJ1: DY16 | NK1: DY16 | NL1: DY16 | NM1: DY16 | NN1: DY16 | NO1: DY16 | NP1: DY16 | NQ1: DY16 | NR1: DY16 | NS1: DY16 | NT1: DY16 | NU1: DY16 | NV1: DY16 | NW1: DY16 | NX1: DY16 | NY1: DY16 | NZ1: DY16 | OA1: DY16 | OB1: DY17 | OC1: DY17 | OD1: DY17 | OE1: DY17 | OF1: DY17 | OG1: DY17 | OH1: DY17 | OI1: DY17 | OJ1: DY17 | OK1: DY17 | OL1: DY17 | OM1: DY17 | ON1: DY17 | OO1: DY17 | OP1: DY17 | OQ1: DY17 | OR1: DY17 | OS1: DY17 | OT1: DY17 | OU1: DY17 | OV1: DY17 | OW1: DY17 | OX1: DY17 | OY1: DY17 | OZ1: DY18 | PA1: DY18 | PB1: DY18 | PC1: DY18 | PD1: DY18 | PE1: DY18 | PF1: DY18 | PG1: DY18 | PH1: DY18 | PI1: DY18 | PJ1: DY18 | PK1: DY18 | PL1: DY18 | PM1: DY18 | PN1: DY18 | PO1: DY18 | PP1: DY18 | PQ1: DY18 | PR1: DY18 | PS1: DY18 | PT1: DY18 | PU1: DY18 | PV1: DY18 | PW1: DY18 | PX1: DY19 | PY1: DY19 | PZ1: DY19 | QA1: DY19 | QB1: DY19 | QC1: DY19 | QD1: DY19 | QE1: DY19 | QF1: DY19 | QG1: DY19 | QH1: DY19 | QI1: DY19 | QJ1: DY19 | QK1: DY19 | QL1: DY19 | QM1: DY19 | QN1: DY19 | QO1: DY19 | QP1: DY19 | QQ1: DY19 | QR1: DY19 | QS1: DY19 | QT1: DY19 | QU1: DY19 | QV1: DY20 | QW1: DY20 | QX1: DY20 | QY1: DY20 | QZ1: DY20 | RA1: DY20 | RB1: DY20 | RC1: DY20 | RD1: DY20 | RE1: DY20 | RF1: DY20 | RG1: DY20 | RH1: DY20 | RI1: DY20 | RJ1: DY20 | RK1: DY20 | RL1: DY20 | RM1: DY20 | RN1: DY20 | RO1: DY20 | RP1: DY20 | RQ1: DY20 | RR1: DY20 | RS1: DY20 | RT1: DY21 | RU1: DY21 | RV1: DY21 | RW1: DY21 | RX1: DY21 | RY1: DY21 | RZ1: DY21 | SA1: DY21 | SB1: DY21 | SC1: DY21 | SD1: DY21 | SE1: DY21 | SF1: DY21 | SG1: DY21 | SH1: DY21 | SI1: DY21 | SJ1: DY21 | SK1: DY21 | SL1: DY21 | SM1: DY21 | SN1: DY21 | SO1: DY21 | SP1: DY21 | SQ1: DY21 | SR1: DY22 | SS1: DY22 | ST1: DY22 | SU1: DY22 | SV1: DY22 | SW1: DY22 | SX1: DY22 | SY1: DY22 | SZ1: DY22 | TA1: DY22 | TB1: DY22 | TC1: DY22 | TD1: DY22 | TE1: DY22 | TF1: DY22 | TG1: DY22 | TH1: DY22 | TI1: DY22 | TJ1: DY22 | TK1: DY22 | TL1: DY22 | TM1: DY22 | TN1: DY22 | TO1: DY22 | TP1: DY23 | TQ1: DY23 | TR1: DY23 | TS1: DY23 | TT1: DY23 | TU1: DY23 | TV1: DY23 | TW1: DY23 | TX1: DY23 | TY1: DY23 | TZ1: DY23 | UA1: DY23 | UB1: DY23 | UC1: DY23 | UD1: DY23 | UE1: DY23 | UF1: DY23 | UG1: DY23 | UH1: DY23 | UI1: DY23 | UJ1: DY23 | UK1: DY23 | UL1: DY23 | UM1: DY23 | UN1: DY24 | UO1: DY24 | UP1: DY24 | UQ1: DY24 | UR1: DY24 | US1: DY24 | UT1: DY24 | UU1: DY24 | UV1: DY24 | UW1: DY24 | UX1: DY24 | UY1: DY24 | UZ1: DY24 | VA1: DY24 | VB1: DY24 | VC1: DY24 | VD1: DY24 | VE1: DY24 | VF1: DY24 | VG1: DY24 | VH1: DY24 | VI1: DY24 | VJ1: DY24 | VK1: DY24 | VL1: DY25 | VM1: DY25 | VN1: DY25 | VO1: DY25 | VP1: DY25 | VQ1: DY25 | VR1: DY25 | VS1: DY25 | VT1: DY25 | VU1: DY25 | VV1: DY25 | VW1: DY25 | VX1: DY25 | VY1: DY25 | VZ1: DY25 | WA1: DY25 | WB1: DY25 | WC1: DY25 | WD1: DY25 | WE1: DY25 | WF1: DY25 | WG1: DY25 | WH1: DY25 | WI1: DY25 | WJ1: DY26 | WK1: DY26 | WL1: DY26 | WM1: DY26 | WN1: DY26 | WO1: DY26 | WP1: DY26 | WQ1: DY26 | WR1: DY26 | WS1: DY26 | WT1: DY26 | WU1: DY26 | WV1: DY26 | WW1: DY26 | WX1: DY26 | WY1: DY26 | WZ1: DY26 | XA1: DY26 | XB1: DY26 | XC1: DY26 | XD1: DY26 | XE1: DY26 | XF1: DY26 | XG1: DY26 | XH1: DY27 | XI1: DY27 | XJ1: DY27 | XK1: DY27 | XL1: DY27 | XM1: DY27 | XN1: DY27 | XO1: DY27 | XP1: DY27 | XQ1: DY27 | XR1: DY27 | XS1: DY27 | XT1: DY27 | XU1: DY27 | XV1: DY27 | XW1: DY27 | XX1: DY27 | XY1: DY27 | XZ1: DY27 | YA1: DY27 | YB1: DY27 | YC1: DY27 | YD1: DY27 | YE1: DY27 | YF1: DY28 | YG1: DY28 | YH1: DY28 | YI1: DY28 | YJ1: DY28 | YK1: DY28 | YL1: DY28 | YM1: DY28 | YN1: DY28 | YO1: DY28 | YP1: DY28 | YQ1: DY28 | YR1: DY28 | YS1: DY28 | YT1: DY28 | YU1: DY28 | YV1: DY28 | YW1: DY28 | YX1: DY28 | YY1: DY28 | YZ1: DY28 | ZA1: DY28 | ZB1: DY28 | ZC1: DY28 | ZD1: DY29 | ZE1: DY29 | ZF1: DY29 | ZG1: DY29 | ZH1: DY29 | ZI1: DY29 | ZJ1: DY29 | ZK1: DY29 | ZL1: DY29 | ZM1: DY29 | ZN1: DY29 | ZO1: DY29 | ZP1: DY29 | ZQ1: DY29 | ZR1: DY29 | ZS1: DY29 | ZT1: DY29 | ZU1: DY29 | ZV1: DY29 | ZW1: DY29 | ZX1: DY29 | ZY1: DY29 | ZZ1: DY29 | AAA1: DY29 | AAB1: DY30 | AAC1: DY30 | AAD1: DY30 | AAE1: DY30 | AAF1: DY30 | AAG1: DY30 | AAH1: DY30 | AAI1: DY30 | AAJ1: DY30 | AAK1: DY30 | AAL1: DY30 | AAM1: DY30 | AAN1: DY30 | AAO1: DY30 | AAP1: DY30 | AAQ1: DY30 | AAR1: DY30 | AAS1: DY30 | AAT1: DY30 | AAU1: DY30 | AAV1: DY30 | AAW1: DY30 | AAX1: DY30 | AAY1: DY30 | AAZ1: DY31 | ABA1: DY31 | ABB1: DY31 | ABC1: DY31 | ABD1: DY31 | ABE1: DY31 | ABF1: DY31 | ABG1: DY31 | ABH1: DY31 | ABI1: DY31 | ABJ1: DY31 | ABK1: DY31 | ABL1: DY31 | ABM1: DY31 | ABN1: DY31 | ABO1: DY31 | ABP1: DY31 | ABQ1: DY31 | ABR1: DY31 | ABS1: DY31 | ABT1: DY31 | ABU1: DY31 | ABV1: DY31 | ABW1: DY31 | ABX1: DY32 | ABY1: DY32 | ABZ1: DY32 | ACA1: DY32 | ACB1: DY32 | ACC1: DY32 | ACD1: DY32 | ACE1: DY32 | ACF1: DY32 | ACG1: DY32 | ACH1: DY32 | ACI1: DY32 | ACJ1: DY32 | ACK1: DY32 | ACL1: DY32 | ACM1: DY32 | ACN1: DY32 | ACO1: DY32 | ACP1: DY32 | ACQ1: DY32 | ACR1: DY32 | ACS1: DY32 | ACT1: DY32 | ACU1: DY32 | ACV1: DY33 | ACW1: DY33 | ACX1: DY33 | ACY1: DY33 | ACZ1: DY33 | ADA1: DY33 | ADB1: DY33 | ADC1: DY33 | ADD1: DY33 | ADE1: DY33 | ADF1: DY33 | ADG1: DY33 | ADH1: DY33 | ADI1: DY33 | ADJ1: DY33 | ADK1: DY33 | ADL1: DY33 | ADM1: DY33 | ADN1: DY33 | ADO1: DY33 | ADP1: DY33 | ADQ1: DY33 | ADR1: DY33 | ADS1: DY33 | ADT1: DY34 | ADU1: DY34 | ADV1: DY34 | ADW1: DY34 | ADX1: DY34 | ADY1: DY34 | ADZ1: DY34 | AEA1: DY34 | AEB1: DY34 | AEC1: DY34 | AED1: DY34 | AEE1: DY34 | AEF1: DY34 | AEG1: DY34 | AEH1: DY34 | AEI1: DY34 | AEJ1: DY34 | AEK1: DY34 | AEL1: DY34 | AEM1: DY34 | AEN1: DY34 | AEO1: DY34 | AEP1: DY34 | AEQ1: DY34 | AER1: DY35 | AES1: DY35 | AET1: DY35 | AEU1: DY35 | AEV1: DY35 | AEW1: DY35 | AEX1: DY35 | AEY1: DY35 | AEZ1: DY35 | AFA1: DY35 | AFB1: DY35 | AFC1: DY35 | AFD1: DY35 | AFE1: DY35 | AFF1: DY35 | AFG1: DY35 | AFH1: DY35 | AFI1: DY35 | AFJ1: DY35 | AFK1: DY35 | AFL1: DY35 | AFM1: DY35 | AFN1: DY35 | AFO1: DY35 | AFP1: DY36 | AFQ1: DY36 | AFR1: DY36 | AFS1: DY36 | AFT1: DY36 | AFU1: DY36 | AFV1: DY36 | AFW1: DY36 | AFX1: DY36 | AFY1: DY36 | AFZ1: DY36 | AGA1: DY36 | AGB1: DY36 | AGC1: DY36 | AGD1: DY36 | AGE1: DY36 | AGF1: DY36 | AGG1: DY36 | AGH1: DY36 | AGI1: DY36 | AGJ1: DY36 | AGK1: DY36 | AGL1: DY36 | AGM1: DY36 | AGN1: DY37 | AGO1: DY37 | AGP1: DY37 | AGQ1: DY37 | AGR1: DY37 | AGS1: DY37 | AGT1: DY37 | AGU1: DY37 | AGV1: DY37 | AGW1: DY37 | AGX1: DY37 | AGY1: DY37 | AGZ1: DY37 | AHA1: DY37 | AHB1: DY37 | AHC1: DY37 | AHD1: DY37 | AHE1: DY37 | AHF1: DY37 | AHG1: DY37 | AHH1: DY37 | AHI1: DY37 | AHJ1: DY37 | AHK1: DY37 | AHL1: DY38 | AHM1: DY38 | AHN1: DY38 | AHO1: DY38 | AHP1: DY38 | AHQ1: DY38 | AHR1: DY38 | AHS1: DY38 | AHT1: DY38 | AHU1: DY38 | AHV1: DY38 | AHW1: DY38 | AHX1: DY38 | AHY1: DY38 | AHZ1: DY38 | AIA1: DY38 | AIB1: DY38 | AIC1: DY38 | AID1: DY38 | AIE1: DY38 | AIF1: DY38 | AIG1: DY38 | AIH1: DY38 | AII1: DY38 | AIJ1: DY39 | AIK1: DY39 | AIL1: DY39 | AIM1: DY39 | AIN1: DY39 | AIO1: DY39 | AIP1: DY39 | AIQ1: DY39 | AIR1: DY39 | AIS1: DY39 | AIT1: DY39 | AIU1: DY39 | AIV1: DY39 | AIW1: DY39 | AIX1: DY39 | AIY1: DY39 | AIZ1: DY39 | AJA1: DY39 | AJB1: DY39 | AJC1: DY39 | AJD1: DY39 | AJE1: DY39 | AJF1: DY39 | AJG1: DY39 | AJH1: DY40 | AJI1: DY40 | AJJ1: DY40 | AJK1: DY40 | AJL1: DY40 | AJM1: DY40 | AJN1: DY40 | AJO1: DY40 | AJP1: DY40 | AJQ1: DY40 | AJR1: DY40 | AJS1: DY40 | AJT1: DY40 | AJU1: DY40 | AJV1: DY40 | AJW1: DY40 | AJX1: DY40 | AJY1: DY40 | AJZ1: DY40 | AKA1: DY40 | AKB1: DY40 | AKC1: DY40 | AKD1: DY40 | AKE1: DY40 | AKF1: DY41 | AKG1: DY41 | AKH1: DY41 | AKI1: DY41 | AKJ1: DY41 | AKK1: DY41 | AKL1: DY41 | AKM1: DY41 | AKN1: DY41 | AKO1: DY41 | AKP1: DY41 | AKQ1: DY41 | AKR1: DY41 | AKS1: DY41 | AKT1: DY41 | AKU1: DY41 | AKV1: DY41 | AKW1: DY41 | AKX1: DY41 | AKY1: DY41 | AKZ1: DY41 | ALA1: DY41 | ALB1: DY41 | ALC1: DY41 | ALD1: DY42 | ALE1: DY42 | ALF1: DY42 | ALG1: DY42 | ALH1: DY42 | ALI1: DY42 | ALJ1: DY42 | ALK1: DY42 | ALL1: DY42 | ALM1: DY42 | ALN1: DY42 | ALO1: DY42 | ALP1: DY42 | ALQ1: DY42 | ALR1: DY42 | ALS1: DY42 | ALT1: DY42 | ALU1: DY42 | ALV1: DY42 | ALW1: DY42 | ALX1: DY42 | ALY1: DY42 | ALZ1: DY42 | AMA1: DY42 | AMB1: DY43 | AMC1: DY43 | AMD1: DY43 | AME1: DY43 | AMF1: DY43 | AMG1: DY43 | AMH1: DY43 | AMI1: DY43 | AMJ1: DY43 | AMK1: DY43 | AML1: DY43 | AMM1: DY43 | AMN1: DY43 | AMO1: DY43 | AMP1: DY43 | AMQ1: DY43 | AMR1: DY43 | AMS1: DY43 | AMT1: DY43 | AMU1: DY43 | AMV1: DY43 | AMW1: DY43 | AMX1: DY43 | AMY1: DY43 | AMZ1: DY44 | ANA1: DY44 | ANB1: DY44 | ANC1: DY44 | AND1: DY44 | ANE1: DY44 | ANF1: DY44 | ANG1: DY44 | ANH1: DY44 | ANI1: DY44 | ANJ1: DY44 | ANK1: DY44 | ANL1: DY44 | ANM1: DY44 | ANN1: DY44 | ANO1: DY44 | ANP1: DY44 | ANQ1: DY44 | ANR1: DY44 | ANS1: DY44 | ANT1: DY44 | ANU1: DY44 | ANV1: DY44 | ANW1: DY44 | ANX1: DY45 | ANY1: DY45 | ANZ1: DY45 | AOA1: DY45 | AOB1: DY45 | AOC1: DY45 | AOD1: DY45 | AOE1: DY45 | AOF1: DY45 | AOG1: DY45 | AOH1: DY45 | AOI1: DY45 | AOJ1: DY45 | AOK1: DY45 | AOL1: DY45 | AOM1: DY45 | AON1: DY45 | AOO1: DY45 | AOP1: DY45 | AOQ1: DY45 | AOR1: DY45 | AOS1: DY45 | AOT1: DY45 | AOU1: DY45 | AOV1: DY46 | AOW1: DY46 | AOX1: DY46 | AOY1: DY46 | AOZ1: DY46 | APA1: DY46 | APB1: DY46 | APC1: DY46 | APD1: DY46 | APE1: DY46 | APF1: DY46 | APG1: DY46 | APH1: DY46 | API1: DY46 | APJ1: DY46 | APK1: DY46 | APL1: DY46 | APM1: DY46 | APN1: DY46 | APO1: DY46 | APP1: DY46 | APQ1: DY46 | APR1: DY46 | APS1: DY46 | APT1: DY47 | APU1: DY47 | APV1: DY47 | APW1: DY47 | APX1: DY47 | APY1: DY47 | APZ1: DY47 | AQA1: DY47 | AQB1: DY47 | AQC1: DY47 | AQD1: DY47 | AQE1: DY47 | AQF1: DY47 | AQG1: DY47 | AQH1: DY47 | AQI1: DY47 | AQJ1: DY47 | AQK1: DY47 | AQL1: DY47 | AQM1: DY47 | AQN1: DY47 | AQO1: DY47 | AQP1: DY47 | AQQ1: DY47 | AQR1: DY48 | AQS1: DY48 | AQT1: DY48 | AQU1: DY48 | AQV1: DY48 | AQW1: DY48 | AQX1: DY48 | AQY1: DY48 | AQZ1: DY48 | ARA1: DY48 | ARB1: DY48 | ARC1: DY48 | ARD1: DY48 | ARE1: DY48 | ARF1: DY48 | ARG1: DY48 | ARH1: DY48 | ARI1: DY48 | ARJ1: DY48 | ARK1: DY48 | ARL1: DY48 | ARM1: DY48 | ARN1: DY48 | ARO1: DY48 | ARP1: DY49 | ARQ1: DY49 | ARR1: DY49 | ARS1: DY49 | ART1: DY49 | ARU1: DY49 | ARV1: DY49 | ARW1: DY49 | ARX1: DY49 | ARY1: DY49 | ARZ1: DY49 | ASA1: DY49 | ASB1: DY49 | ASC1: DY49 | ASD1: DY49 | ASE1: DY49 | ASF1: DY49 | ASG1: DY49 | ASH1: DY49 | ASI1: DY49 | ASJ1: DY49 | ASK1: DY49 | ASL1: DY49 | ASM1: DY49 | ASN1: DY50 | ASO1: DY50 | ASP1: DY50 | ASQ1: DY50 | ASR1: DY50 | ASS1: DY50 | AST1: DY50 | ASU1: DY50 | ASV1: DY50 | ASW1: DY50 | ASX1: DY50 | ASY1: DY50 | ASZ1: DY50 | ATA1: DY50 | ATB1: DY50 | ATC1: DY50 | ATD1: DY50 | ATE1: DY50 | ATF1: DY50 | ATG1: DY50 | ATH1: DY50 | ATI1: DY50 | ATJ1: DY50 | ATK1: DY50 | ATL1: DY51 | ATM1: DY51 | ATN1: DY51 | ATO1: DY51 | ATP1: DY51 | ATQ1: DY51 | ATR1: DY51 | ATS1: DY51 | ATT1: DY51 | ATU1: DY51 | ATV1: DY51 | ATW1: DY51 | ATX1: DY51 | ATY1: DY51 | ATZ1: DY51 | AUA1: DY51 | AUB1: DY51 | AUC1: DY51 | AUD1: DY51 | AUE1: DY51 | AUF1: DY51 | AUG1: DY51 | AUH1: DY51 | AUI1: DY51 | AUJ1: DY52 | AUK1: DY52 | AUL1: DY52 | AUM1: DY52 | AUN1: DY52 | AUO1: DY52 | AUP1: DY52 | AUQ1: DY52 | AUR1: DY52 | AUS1: DY52 | AUT1: DY52 | AUU1: DY52 | AUV1: DY52 | AUW1: DY52 | AUX1: DY52 | AUY1: DY52 | AUZ1: DY52 | AVA1: DY52 | AVB1: DY52 | AVC1: DY52 | AVD1: DY52 | AVE1: DY52 | AVF1: DY52 | AVG1: DY52 | AVH1: DY53 | AVI1: DY53 | AVJ1: DY53 | AVK1: DY53 | AVL1: DY53 | AVM1: DY53 | AVN1: DY53 | AVO1: DY53 | AVP1: DY53 | AVQ1: DY53 | AVR1: DY53 | AVS1: DY53 | AVT1: DY53 | AVU1: DY53 | AVV1: DY53 | AVW1: DY53 | AVX1: DY53 | AVY1: DY53 | AVZ1: DY53 | AWA1: DY53 | AWB1: DY53 | AWC1: DY53 | AWD1: DY53 | AWE1: DY53 | AWF1: DY54 | AWG1: DY54 | AWH1: DY54 | AWI1: DY54 | AWJ1: DY54 | AWK1: DY54 | AWL1: DY54 | AWM1: DY54 | AWN1: DY54 | AWO1: DY54 | AWP1: DY54 | AWQ1: DY54 | AWR1: DY54 | AWS1: DY54 | AWT1: DY54 | AWU1: DY54 | AWV1: DY54 | AWW1: DY54 | AWX1: DY54 | AWY1: DY54 | AWZ1: DY54 | AXA1: DY54 | AXB1: DY54 | AXC1: DY54 | AXD1: DY55 | AXE1: DY55 | AXF1: DY55 | AXG1: DY55 | AXH1: DY55 | AXI1: DY55 | AXJ1: DY55 | AXK1: DY55 | AXL1: DY55 | AXM1: DY55 | AXN1: DY55 | AXO1: DY55 | AXP1: DY55 | AXQ1: DY55 | AXR1: DY55 | AXS1: DY55 | AXT1: DY55 | AXU1: DY55 | AXV1: DY55 | AXW1: DY55 | AXX1: DY55 | AXY1: DY55 | AXZ1: DY55 | AYA1: DY55 | AYB1: DY56 | AYC1: DY56 | AYD1: DY56 | AYE1: DY56 | AYF1: DY56 | AYG1: DY56 | AYH1: DY56 | AYI1: DY56 | AYJ1: DY56 | AYK1: DY56 | AYL1: DY56 | AYM1: DY56 | AYN1: DY56 | AYO1: DY56 | AYP1: DY56 | AYQ1: DY56 | AYR1: DY56 | AYS1: DY56 | AYT1: DY56 | AYU1: DY56 | AYV1: DY56 | AYW1: DY56 | AYX1: DY56 | AYY1: DY56 | AYZ1: DY57 | AZA1: DY57 | AZB1: DY57 | AZC1: DY57 | AZD1: DY57 | AZE1: DY57 | AZF1: DY57 | AZG1: DY57 | AZH1: DY57 | AZI1: DY57 | AZJ1: DY57 | AZK1: DY57 | AZL1: DY57 | AZM1: DY57 | AZN1: DY57 | AZO1: DY57 | AZP1: DY57 | AZQ1: DY57 | AZR1: DY57 | AZS1: DY57 | AZT1: DY57 | AZU1: DY57 | AZV1: DY57 | AZW1: DY57 | AZX1: DY58 | AZY1: DY58 | AZZ1: DY58 | BAA1: DY58 | BAB1: DY58 | BAC1: DY58 | BAD1: DY58 | BAE1: DY58 | BAF1: DY58 | BAG1: DY58 | BAH1: DY58 | BAI1: DY58 | BAJ1: DY58 | BAK1: DY58 | BAL1: DY58 | BAM1: DY58 | BAN1: DY58 | BAO1: DY58 | BAP1: DY58 | BAQ1: DY58 | BAR1: DY58 | BAS1: DY58 | BAT1: DY58 | BAU1: DY58 | BAV1: DY59 | BAW1: DY59 | BAX1: DY59 | BAY1: DY59 | BAZ1: DY59 | BBA1: DY59 | BBB1: DY59 | BBC1: DY59 | BBD1: DY59 | BBE1: DY59 | BBF1: DY59 | BBG1: DY59 | BBH1: DY59 | BBI1: DY59 | BBJ1: DY59 | BBK1: DY59 | BBL1: DY59 | BBM1: DY59 | BBN1: DY59 | BBO1: DY59 | BBP1: DY59 | BBQ1: DY59 | BBR1: DY59 | BBS1: DY59 | BBT1: DY60 | BBU1: DY60 | BBV1: DY60 | BBW1: DY60 | BBX1: DY60 | BBY1: DY60 | BBZ1: DY60 | BCA1: DY60 | BCB1: DY60 | BCC1: DY60 | BCD1: DY60 | BCE1: DY60 | BCF1: DY60 | BCG1: DY60 | BCH1: DY60 | BCI1: DY60 | BCJ1: DY60 | BCK1: DY60 | BCL1: DY60 | BCM1: DY60 | BCN1: DY60 | BCO1: DY60 | BCP1: DY60 | BCQ1: DY60 | BCR1: DY61 | BCS1: DY61 | BCT1: DY61 | BCU1: DY61 | BCV1: DY61 | BCW1: DY61 | BCX1: DY61 | BCY1: DY61 | BCZ1: DY61 | BDA1: DY61 | BDB1: DY61 | BDC1: DY61 | BDD1: DY61 | BDE1: DY61 | BDF1: DY61 | BDG1: DY61 | BDH1: DY61 | BDI1: DY61 | BDJ1: DY61 | BDK1: DY61 | BDL1: DY61 | BDM1: DY61 | BDN1: DY61 | BDO1: DY61 | BDP1: DY62 | BDQ1: DY62 | BDR1: DY62 | BDS1: DY62 | BDT1: DY62 | BDU1: DY62 | BDV1: DY62 | BDW1: DY62 | BDX1: DY62 | BDY1: DY62 | BDZ1: DY62 | BEA1: DY62 | BEB1: DY62 | BEC1: DY62 | BED1: DY62 | BEE1: DY62 | BEF1: DY62 | BEG1: DY62 | BEH1: DY62 | BEI1: DY62 | BEJ1: DY62 | BEK1: DY62 | BEL1: DY62 | BEM1: DY62 | BEN1: DY63 | BEO1: DY63 | BEP1: DY63 | BEQ1: DY63 | BER1: DY63 | BES1: DY63 | BET1: DY63 | BEU1: DY63 | BEV1: DY63 | BEW1: DY63 | BEX1: DY63 | BEY1: DY63 | BEZ1: DY63 | BFA1: DY63 | BFB1: DY63 | BFC1: DY63 | BFD1: DY63 | BFE1: DY63 | BFF1: DY63 | BFG1: DY63 | BFH1: DY63 | BFI1: DY63 | BFJ1: DY63 | BFK1: DY63 | BFL1: DY64 | BFM1: DY64 | BFN1: DY64 | BFO1: DY64 | BFP1: DY64 | BFQ1: DY64 | BFR1: DY64 | BFS1: DY64 | BFT1: DY64 | BFU1: DY64 | BFV1: DY64 | BFW1: DY64 | BFX1: DY64 | BFY1: DY64 | BFZ1: DY64 | BGA1: DY64 | BGB1: DY64 | BGC1: DY64 | BGD1: DY64 | BGE1: DY64 | BGF1: DY64 | BGG1: DY64 | BGH1: DY64 | BGI1: DY64 | BGJ1: DY65 | BGK1: DY65 | BGL1: DY65 | BGM1: DY65 | BGN1: DY65 | BGO1: DY65 | BGP1: DY65 | BGQ1: DY65 | BGR1: DY65 | BGS1: DY65 | BGT1: DY65 | BGU1: DY65 | BGV1: DY65 | BGW1: DY65 | BGX1: DY65 | BGY1: DY65 | BGZ1: DY65 | BHA1: DY65 | BHB1: DY65 | BHC1: DY65 | BHD1: DY65 | BHE1: DY65 | BHF1: DY65 | BHG1: DY65 | BHH1: DY66 | BHI1: DY66 | BHJ1: DY66 | BHK1: DY66 | BHL1: DY66 | BHM1: DY66 | BHN1: DY66 | BHO1: DY66 | BHP1: DY66 | BHQ1: DY66 | BHR1: DY66 | BHS1: DY66 | BHT1: DY66 | BHU1: DY66 | BHV1: DY66 | BHW1: DY66 | BHX1: DY66 | BHY1: DY66 | BHZ1: DY66 | BIA1: DY66 | BIB1: DY66 | BIC1: DY66 | BID1: DY66 | BIE1: DY66 | BIF1: DY67 | BIG1: DY67 | BIH1: DY67 | BII1: DY67 | BIJ1: DY67 | BIK1: DY67 | BIL1: DY67 | BIM1: DY67 | BIN1: DY67 | BIO1: DY67 | BIP1: DY67 | BIQ1: DY67 | BIR1: DY67 | BIS1: DY67 | BIT1: DY67 | BIU1: DY67 | BIV1: DY67 | BIW1: DY67 | BIX1: DY67 | BIY1: DY67 | BIZ1: DY67 | BJA1: DY67 | BJB1: DY67 | BJC1: DY67 | BJD1: DY68 | BJE1: DY68 | BJF1: DY68 | BJG1: DY68 | BJH1: DY68 | BJI1: DY68 | BJJ1: DY68 | BJK1: DY68 | BJL1: DY68 | BJM1: DY68 | BJN1: DY68 | BJO1: DY68 | BJP1: DY68 | BJQ1: DY68 | BJR1: DY68 | BJS1: DY68 | BJT1: DY68 | BJU1: DY68 | BJV1: DY68 | BJW1: DY68 | BJX1: DY68 | BJY1: DY68 | BJZ1: DY68 | BKA1: DY68 | BKB1: DY69 | BKC1: DY69 | BKD1: DY69 | BKE1: DY69 | BKF1: DY69 | BKG1: DY69 | BKH1: DY69 | BKI1: DY69 | BKJ1: DY69 | BKK1: DY69 | BKL1: DY69 | BKM1: DY69 | BKN1: DY69 | BKO1: DY69 | BKP1: DY69 | BKQ1: DY69 | BKR1: DY69 | BKS1: DY69 | BKT1: DY69 | BKU1: DY69 | BKV1: DY69 | BKW1: DY69 | BKX1: DY69 | BKY1: DY69 | BKZ1: DY70 | BLA1: DY70 | BLB1: DY70 | BLC1: DY70 | BLD1: DY70 | BLE1: DY70 | BLF1: DY70 | BLG1: DY70 | BLH1: DY70 | BLI1: DY70 | BLJ1: DY70 | BLK1: DY70 | BLL1: DY70 | BLM1: DY70 | BLN1: DY70 | BLO1: DY70 | BLP1: DY70 | BLQ1: DY70 | BLR1: DY70 | BLS1: DY70 | BLT1: DY70 | BLU1: DY70 | BLV1: DY70 | BLW1: DY70 | BLX1: DY71 | BLY1: DY71 | BLZ1: DY71 | BMA1: DY71 | BMB1: DY71 | BMC1: DY71 | BMD1: DY71 | BME1: DY71 | BMF1: DY71 | BMG1: DY71 | BMH1: DY71 | BMI1: DY71 | BMJ1: DY71 | BMK1: DY71 | BML1: DY71 | BMM1: DY71 | BMN1: DY71 | BMO1: DY71 | BMP1: DY71 | BMQ1: DY71 | BMR1: DY71 | BMS1: DY71 | BMT1: DY71 | BMU1: DY71 | BMV1: DY72 | BMW1: DY72 | BMX1: DY72 | BMY1: DY72 | BMZ1: DY72 | BNA1: DY72 | BNB1: DY72 | BNC1: DY72 | BND1: DY72 | BNE1: DY72 | BNF1: DY72 | BNG1: DY72 | BNH1: DY72 | BNI1: DY72 | BNJ1: DY72 | BNK1: DY72 | BNL1: DY72 | BNM1: DY72 | BNN1: DY72 | BNO1: DY72 | BNP1: DY72 | BNQ1: DY72 | BNR1: DY72 | BNS1: DY72 | BNT1: DY73 | BNU1: DY73 | BNV1: DY73 | BNW1: DY73 | BNX1: DY73 | BNY1: DY73 | BNZ1: DY73 | BOA1: DY73 | BOB1: DY73 | BOC1: DY73 | BOD1: DY73 | BOE1: DY73 | BOF1: DY73 | BOG1: DY73 | BOH1: DY73 | BOI1: DY73 | BOJ1: DY73 | BOK1: DY73 | BOL1: DY73 | BOM1: DY73 | BON1: DY73 | BOO1: DY73 | BOP1: DY73 | BOQ1: DY73 | BOR1: DY74 | BOS1: DY74 | BOT1: DY74 | BOU1: DY74 | BOV1: DY74 | BOW1: DY74 | BOX1: DY74 | BOY1: DY74 | BOZ1: DY74 | BPA1: DY74 | BPB1: DY74 | BPC1: DY74 | BPD1: DY74 | BPE1: DY74 | BPF1: DY74 | BPG1: DY74 | BPH1: DY74 | BPI1: DY74 | BPJ1: DY74 | BPK1: DY74 | BPL1: DY74 | BPM1: DY74 | BPN1: DY74 | BPO1: DY74 | BPP1: DY75 | BPQ1: DY75 | BPR1: DY75 | BPS1: DY75 | BPT1: DY75 | BPU1: DY75 | BPV1: DY75 | BPW1: DY75 | BPX1: DY75 | BPY1: DY75 | BPZ1: DY75 | BQA1: DY75 | BQB1: DY75 | BQC1: DY75 | BQD1: DY75 | BQE1: DY75 | BQF1: DY75 | BQG1: DY75 | BQH1: DY75 | BQI1: DY75 | BQJ1: DY75 | BQK1: DY75 | BQL1: DY75 | BQM1: DY75 | BQN1: DY76 | BQO1: DY76 | BQP1: DY76 | BQQ1: DY76 | BQR1: DY76 | BQS1: DY76 | BQT1: DY76 | BQU1: DY76 | BQV1: DY76 | BQW1: DY76 | BQX1: DY76 | BQY1: DY76 | BQZ1: DY76 | BRA1: DY76 | BRB1: DY76 | BRC1: DY76 | BRD1: DY76 | BRE1: DY76 | BRF1: DY76 | BRG1: DY76 | BRH1: DY76 | BRI1: DY76 | BRJ1: DY76 | BRK1: DY76 | BRL1: DY77 | BRM1: DY77 | BRN1: DY77 | BRO1: DY77 | BRP1: DY77 | BRQ1: DY77 | BRR1: DY77 | BRS1: DY77 | BRT1: DY77 | BRU1: DY77 | BRV1: DY77 | BRW1: DY77 | BRX1: DY77 | BRY1: DY77 | BRZ1: DY77 | BSA1: DY77 | BSB1: DY77 | BSC1: DY77 | BSD1: DY77 | BSE1: DY77 | BSF1: DY77 | BSG1: DY77 | BSH1: DY77 | BSI1: DY77 | BSJ1: DY78 | BSK1: DY78 | BSL1: DY78 | BSM1: DY78 | BSN1: DY78 | BSO1: DY78 | BSP1: DY78 | BSQ1: DY78 | BSR1: DY78 | BSS1: DY78 | BST1: DY78 | BSU1: DY78 | BSV1: DY78 | BSW1: DY78 | BSX1: DY78 | BSY1: DY78 | BSZ1: DY78 | BTA1: DY78 | BTB1: DY78 | BTC1: DY78 | BTD1: DY78 | BTE1: DY78 | BTF1: DY78 | BTG1: DY78 | BTH1: DY79 | BTI1: DY79 | BTJ1: DY79 | BTK1: DY79 | BTL1: DY79 | BTM1: DY79 | BTN1: DY79 | BTO1: DY79 | BTP1: DY79 | BTQ1: DY79 | BTR1: DY79 | BTS1: DY79 | BTT1: DY79 | BTU1: DY79 | BTV1: DY79 | BTW1: DY79 | BTX1: DY79 | BTY1: DY79 | BTZ1: DY79 | BUA1: DY79 | BUB1: DY79 | BUC1: DY79 | BUD1: DY79 | BUE1: DY79 | BUF1: DY80 | BUG1: DY80 | BUH1: DY80 | BUI1: DY80 | BUJ1: DY80 | BUK1: DY80 | BUL1: DY80 | BUM1: DY80 | BUN1: DY80 | BUO1: DY80 | BUP1: DY80 | BUQ1: DY80 | BUR1: DY80 | BUS1: DY80 | BUT1: DY80 | BUU1: DY80 | BUV1: DY80 | BUW1: DY80 | BUX1: DY80 | BUY1: DY80 | BUZ1: DY80 | BVA1: DY80 | BVB1: DY80 | BVC1: DY80 | BVD1: DY81 | BVE1: DY81 | BVF1: DY81 | BVG1: DY81 | BVH1: DY81 | BVI1: DY81 | BVJ1: DY81 | BVK1: DY81 | BVL1: DY81 | BVM1: DY81 | BVN1: DY81 | BVO1: DY81 | BVP1: DY81 | BVQ1: DY81 | BVR1: DY81 | BVS1: DY81 | BVT1: DY81 | BVU1: DY81 | BVV1: DY81 | BVW1: DY81 | BVX1: DY81 | BVY1: DY81 | BVZ1: DY81 | BWA1: DY81 | BWB1: DY82 | BWC1: DY82 | BWD1: DY82 | BWE1: DY82 | BWF1: DY82 | BWG1: DY82 | BWH1: DY82 | BWI1: DY82 | BWJ1: DY82 | BWK1: DY82 | BWL1: DY82 | BWM1: DY82 | BWN1: DY82 | BWO1: DY82 | BWP1: DY82 | BWQ1: DY82 | BWR1: DY82 | BWS1: DY82 | BWT1: DY82 | BWU1: DY82 | BWV1: DY82 | BWW1: DY82 | BWX1: DY82 | BWY1: DY82 | BWZ1: DY83 | BXA1: DY83 | BXB1: DY83 | BXC1: DY83 | BXD1: DY83 | BXE1: DY83 | BXF1: DY83 | BXG1: DY83 | BXH1: DY83 | BXI1: DY83 | BXJ1: DY83 | BXK1: DY83 | BXL1: DY83 | BXM1: DY83 | BXN1: DY83 | BXO1: DY83 | BXP1: DY83 | BXQ1: DY83 | BXR1: DY83 | BXS1: DY83 | BXT1: DY83 | BXU1: DY83 | BXV1: DY83 | BXW1: DY83 | BXX1: DY84 | BXY1: DY84 | BXZ1: DY84 | BYA1: DY84 | BYB1: DY84 | BYC1: DY84 | BYD1: DY84 | BYE1: DY84 | BYF1: DY84 | BYG1: DY84 | BYH1: DY84 | BYI1: DY84 | BYJ1: DY84 | BYK1: DY84 | BYL1: DY84 | BYM1: DY84 | BYN1: DY84 | BYO1: DY84 | BYP1: DY84 | BYQ1: DY84 | BYR1: DY84 | BYS1: DY84 | BYT1: DY84 | BYU1: DY84 | BYV1: DY85 | BYW1: DY85 | BYX1: DY85 | BYY1: DY85 | BYZ1: DY85 | BZA1: DY85 | BZB1: DY85 | BZC1: DY85 | BZD1: DY85 | BZE1: DY85 | BZF1: DY85 | BZG1: DY85 | BZH1: DY85 | BZI1: DY85 | BZJ1: DY85 | BZK1: DY85 | BZL1: DY85 | BZM1: DY85 | BZN1: DY85 | BZO1: DY85 | BZP1: DY85 | BZQ1: DY85 | BZR1: DY85 | BZS1: DY85 | BZT1: DY86 | BZU1: DY86 | BZV1: DY86 | BZW1: DY86 | BZX1: DY86 | BZY1: DY86 | BZZ1: DY86 | CAA1: DY86 | CAB1: DY86 | CAC1: DY86 | CAD1: DY86 | CAE1: DY86 | CAF1: DY86 | CAG1: DY86 | CAH1: DY86 | CAI1: DY86 | CAJ1: DY86 | CAK1: DY86 | CAL1: DY86 | CAM1: DY86 | CAN1: DY86 | CAO1: DY86 | CAP1: DY86 | CAQ1: DY86 | CAR1: DY87 | CAS1: DY87 | CAT1: DY87 | CAU1: DY87 | CAV1: DY87 | CAW1: DY87 | CAX1: DY87 | CAY1: DY87 | CAZ1: DY87 | CBA1: DY87 | CBB1: DY87 | CBC1: DY87 | CBD1: DY87 | CBE1: DY87 | CBF1: DY87 | CBG1: DY87 | CBH1: DY87 | CBI1: DY87 | CBJ1: DY87 | CBK1: DY87 | CBL1: DY87 | CBM1: DY87 | CBN1: DY87 | CBO1: DY87 | CBP1: DY88 | CBQ1: DY88 | CBR1: DY88 | CBS1: DY88 | CBT1: DY88 | CBU1: DY88 | CBV1: DY88 | CBW1: DY88 | CBX1: DY88 | CBY1: DY88 | CBZ1: DY88 | CCA1: DY88 | CCB1: DY88 | CCC1: DY88 | CCD1: DY88 | CCE1: DY88 | CCF1: DY88 | CCG1: DY88 | CCH1: DY88 | CCI1: DY88 | CCJ1: DY88 | CCK1: DY88 | CCL1: DY88 | CCM1: DY88 | CCN1: DY89 | CCO1: DY89 | CCP1: DY89 | CCQ1: DY89 | CCR1: DY89 | CCS1: DY89 | CCT1: DY89 | CCU1: DY89 | CCV1: DY89 | CCW1: DY89 | CCX1: DY89 | CCY1: DY89 | CCZ1: DY89 | CDA1: DY89 | CDB1: DY89 | CDC1: DY89 | CDD1: DY89 | CDE1: DY89 | CDF1: DY89 | CDG1: DY89 | CDH1: DY89 | CDI1: DY89 | CDJ1: DY89 | CDK1: DY89 | CDL1: DY90 | CDM1: DY90 | CDN1: DY90 | CDO1: DY90 | CDP1: DY90 | CDQ1: DY90 | CDR1: DY90 | CDS1: DY90 | CDT1: DY90 | CDU1: DY90 | CDV1: DY90 | CDW1: DY90 | CDX1: DY90 | CDY1: DY90 | CDZ1: DY90 | CEA1: DY90 | CEB1: DY90 | CEC1: DY90 | CED1: DY90 | CEE1: DY90 | CEF1: DY90 | CEG1: DY90 | CEH1: DY90 | CEI1: DY90 | CEJ1: DY91 | CEK1: DY91 | CEL1: DY91 | CEM1: DY91 | CEN1: DY91 | CEO1: DY91 | CEP1: DY91 | CEQ1: DY91 | CER1: DY91 | CES1: DY91 | CET1: DY91 | CEU1: DY91 | CEV1: DY91 | CEW1: DY91 | CEX1: DY91 | CEY1: DY91 | CEZ1: DY91 | CFA1: DY91 | CFB1: DY91 | CFC1: DY91 | CFD1: DY91 | CFE1: DY91 | CFF1: DY91 | CFG1: DY91 | CFH1: DY92 | CFI1: DY92 | CFJ1: DY92 | CFK1: DY92 | CFL1: DY92 | CFM1: DY92 | CFN1: DY92 | CFO1: DY92 | CFP1: DY92 | CFQ1: DY92 | CFR1: DY92 | CFS1: DY92 | CFT1: DY92 | CFU1: DY92 | CFV1: DY92 | CFW1: DY92 | CFX1: DY92 | CFY1: DY92 | CFZ1: DY92 | CGA1: DY92 | CGB1: DY92 | CGC1: DY92 | CGD1: DY92 | CGE1: DY92 | CGF1: DY93 | CGG1: DY93 | CGH1: DY93 | CGI1: DY93 | CGJ1: DY93 | CGK1: DY93 | CGL1: DY93 | CGM1: DY93 | CGN1: DY93 | CGO1: DY93 | CGP1: DY93 | CGQ1: DY93 | CGR1: DY93 | CGS1: DY93 | CGT1: DY93 | CGU1: DY93 | CGV1: DY93 | CGW1: DY93 | CGX1: DY93 | CGY1: DY93 | CGZ1: DY93 | CHA1: DY93 | CHB1: DY93 | CHC1: DY93 | CHD1: DY94 | CHE1: DY94 | CHF1: DY94 | CHG1: DY94 | CHH1: DY94 | CHI1: DY94 | CHJ1: DY94 | CHK1: DY94 | CHL1: DY94 | CHM1: DY94 | CHN1: DY94 | CHO1: DY94 | CHP1: DY94 | CHQ1: DY94 | CHR1: DY94 | CHS1: DY94 | CHT1: DY94 | CHU1: DY94 | CHV1: DY94 | CHW1: DY94 | CHX1: DY94 | CHY1: DY94 | CHZ1: DY94 | CIA1: DY94 | CIB1: DY95 | CIC1: DY95 | CID1: DY95 | CIE1: DY95 | CIF1: DY95 | CIG1: DY95 | CIH1: DY95 | CII1: DY95 | CIJ1: DY95 | CIK1: DY95 | CIL1: DY95 | CIM1: DY95 | CIN1: DY95 | CIO1: DY95 | CIP1: DY95 | CIQ1: DY95 | CIR1: DY95 | CIS1: DY95 | CIT1: DY95 | CIU1: DY95 | CIV1: DY95 | CIW1: DY95 | CIX1: DY95 | CIY1: DY95 | CIZ1: DY96 | CJA1: DY96 | CJB1: DY96 | CJC1: DY96 | CJD1: DY96 | CJE1: DY96 | CJF1: DY96 | CJG1: DY96 | CJH1: DY96 | CJI1: DY96 | CJJ1: DY96 | CJK1: DY96 | CJL1: DY96 | CJM1: DY96 | CJN1: DY96 | CJO1: DY96 | CJP1: DY96 | CJQ1: DY96 | CJR1: DY96 | CJS1: DY96 | CJT1: DY96 | CJU1: DY96 | CJV1: DY96 | CJW1: DY96 | CJX1: DY97 | CJY1: DY97 | CJZ1: DY97 | CKA1: DY97 | CKB1: DY97 | CKC1: DY97 | CKD1: DY97 | CKE1: DY97 | CKF1: DY97 | CKG1: DY97 | CKH1: DY97 | CKI1: DY97 | CKJ1: DY97 | CKK1: DY97 | CKL1: DY97 | CKM1: DY97 | CKN1: DY97 | CKO1: DY97 | CKP1: DY97 | CKQ1: DY97 | CKR1: DY97 | CKS1: DY97 | CKT1: DY97 | CKU1: DY97 | CKV1: DY98 | CKW1: DY98 | CKX1: DY98 | CKY1: DY98 | CKZ1: DY98 | CLA1: DY98 | CLB1: DY98 | CLC1: DY98 | CLD1: DY98 | CLE1: DY98 | CLF1: DY98 | CLG1: DY98 | CLH1: DY98 | CLI1: DY98 | CLJ1: DY98 | CLK1: DY98 | CLL1: DY98 | CLM1: DY98 | CLN1: DY98 | CLO1: DY98 | CLP1: DY98 | CLQ1: DY98 | CLR1: DY98 | CLS1: DY98 | CLT1: DY99 | CLU1: DY99 | CLV1: DY99 | CLW1: DY99 | CLX1: DY99 | CLY1: DY99 | CLZ1: DY99 | CMA1: DY99 | CMB1: DY99 | CMC1: DY99 | CMD1: DY99 | CME1: DY99 | CMF1: DY99 | CMG1: DY99 | CMH1: DY99 | CMI1: DY99 | CMJ1: DY99 | CMK1: DY99 | CML1: DY99 | CMM1: DY99 | CMN1: DY99 | CMO1: DY99 | CMP1: DY99 | CMQ1: DY99 | CMR1: DY100 | CMS1: DY100 | CMT1: DY100 | CMU1: DY100 | CMV1: DY100 | CMW1: DY100 | CMX1: DY100 | CMY1: DY100 | CMZ1: DY100 | CNA1: DY100 | CNB1: DY100 | CNC1: DY100 | CND1: DY100 | CNE1: DY100 | CNF1: DY100 | CNG1: DY100 | CNH1: DY100 | CNI1: DY100 | CNJ1: DY100 | CNK1: DY100 | CNL1: DY100 | CNM1: DY100 | CNN1: DY100 | CNO1: DY100 | CNP1: DY101 | CNQ1: DY101 | CNR1: DY101 | CNS1: DY101 | CNT1: DY101 | CNU1: DY101 | CNV1: DY101 | CNW1: DY101 | CNX1: DY101 | CNY1: DY101 | CNZ1: DY101 | COA1: DY101 | COB1: DY101 | COC1: DY101 | COD1: DY101 | COE1: DY101 | COF1: DY101 | COG1: DY101 | COH1: DY101 | COI1: DY101 | COJ1: DY101 | COK1: DY101 | COL1: DY101 | COM1: DY101 | CON1: DY102 | COO1: DY102 | COP1: DY102 | COQ1: DY102 | COR1: DY102 | COS1: DY102 | COT1: DY102 | COU1: DY102 | COV1: DY102 | COW1: DY102 | COX1: DY102 | COY1: DY102 | COZ1: DY102 | CPA1: DY102 | CPB1: DY102 | CPC1: DY102 | CPD1: DY102 | CPE1: DY102 | CPF1: DY102 | CPG1: DY102 | CPH1: DY102 | CPI1: DY102 | CPJ1: DY102 | CPK1: DY102 | CPL1: DY103 | CPM1: DY103 | CPN1: DY103 | CPO1: DY103 | CPP1: DY103 | CPQ1: DY103 | CPR1: DY103 | CPS1: DY103 | CPT1: DY103 | CPU1: DY103 | CPV1: DY103 | CPW1: DY103 | CPX1: DY103 | CPY1: DY103 | CPZ1: DY103 | CQA1: DY103 | CQB1: DY103 | CQC1: DY103 | CQD1: DY103 | CQE1: DY103 | CQF1: DY103 | CQG1: DY103 | CQH1: DY103 | CQI1: DY103 | CQJ1: DY104 | CQK1: DY104 | CQL1: DY104 | CQM1: DY104 | CQN1: DY104 | CQO1: DY104 | CQP1: DY104 | CQQ1: DY104 | CQR1: DY104 | CQS1: DY104 | CQT1: DY104 | CQU1: DY104 | CQV1: DY104 | CQW1: DY104 | CQX1: DY104 | CQY1: DY104 | CQZ1: DY104 | CRA1: DY104 | CRB1: DY104 | CRC1: DY104 | CRD1: DY104 | CRE1: DY104 | CRF1: DY104 | CRG1: DY104 | CRH1: DY105 | CRI1: DY105 | CRJ1: DY105 | CRK1: DY105 | CRL1: DY105 | CRM1: DY105 | CRN1: DY105 | CRO1: DY105 | CRP1: DY105 | CRQ1: DY105 | CRR1: DY105 | CRS1: DY105 | CRT1: DY105 | CRU1: DY105 | CRV1: DY105 | CRW1: DY105 | CRX1: DY105 | CRY1: DY105 | CRZ1: DY105 | CSA1: DY105 | CSB1: DY105 | CSC1: DY105 | CSD1: DY105 | CSE1: DY105 | CSF1: DY106 | CSG1: DY106 | CSH1: DY106 | CSI1: DY106 | CSJ1: DY106 | CSK1: DY106 | CSL1: DY106 | CSM1: DY106 | CSN1: DY106 | CSO1: DY106 | CSP1: DY106 | CSQ1: DY106 | CSR1: DY106 | CSS1: DY106 | CST1: DY106 | CSU1: DY106 | CSV1: DY106 | CSW1: DY106 | CSX1: DY106 | CSY1: DY106 | CSZ1: DY106 | CTA1: DY106 | CTB1: DY106 | CTC1: DY106 | CTD1: DY107 | CTE1: DY107 | CTF1: DY107 | CTG1: DY107 | CTH1: DY107 | CTI1: DY107 | CTJ1: DY107 | CTK1: DY107 | CTL1: DY107 | CTM1: DY107 | CTN1: DY107 | CTO1: DY107 | CTP1: DY107 | CTQ1: DY107 | CTR1: DY107 | CTS1: DY107 | CTT1: DY107 | CTU1: DY107 | CTV1: DY107 | CTW1: DY107 | CTX1: DY107 | CTY1: DY107 | CTZ1: DY107 | CUA1: DY107 | CUB1: DY108 | CUC1: DY108 | CUD1: DY108 | CUE1: DY108 | CUF1: DY108 | CUG1: DY108 | CUH1: DY108 | CUI1: DY108 | CUJ1: DY108 | CUK1: DY108 | CUL1: DY108 | CUM1: DY108 | CUN1: DY108 | CUO1: DY108 | CUP1: DY108 | CUQ1: DY108 | CUR1: DY108 | CUS1: DY108 | CUT1: DY108 | CUU1: DY108 | CUV1: DY108 | CUW1: DY108 | CUX1: DY108 | CUY1: DY108 | CUZ1: DY109 | CVA1: DY109 | CVB1: DY109 | CVC1: DY109 | CVD1: DY109 | CVE1: DY109 | CVF1: DY109 | CVG1: DY109 | CVH1: DY109 | CVI1: DY109 | CVJ1: DY109 | CVK1: DY109 | CVL1: DY109 | CVM1: DY109 | CVN1: DY109 | CVO1: DY109 | CVP1: DY109 | CVQ1: DY109 | CVR1: DY109 | CVS1: DY109 | CVT1: DY109 | CVU1: DY109 | CVV1: DY109 | CVW1: DY109 | CVX1: DY110 | CVY1: DY110 | CVZ1: DY110 | CWA1: DY110 | CWB1: DY110 | CWC1: DY110 | CWD1: DY110 | CWE1: DY110 | CWF1: DY110 | CWG1: DY110 | CWH1: DY110 | CWI1: DY110 | CWJ1: DY110 | CWK1: DY110 | CWL1: DY110 | CWM1: DY110 | CWN1: DY110 | CWO1: DY110 | CWP1: DY110 | CWQ1: DY110 | CWR1: DY110 | CWS1: DY110 | CWT1: DY110 | CWU1: DY110 | CWV1: DY111 | CWW1: DY111 | CWX1: DY111 | CWY1: DY111 | CWZ1: DY111 | CXA1: DY111 | CXB1: DY111 | CXC1: DY111 | CXD1: DY111 | CXE1: DY111 | CXF1: DY111 | CXG1: DY111 | CXH1: DY111 | CXI1: DY111 | CXJ1: DY111 | CXK1: DY111 | CXL1: DY111 | CXM1: DY111 | CXN1: DY111 | CXO1: DY111 | CXP1: DY111 | CXQ1: DY111 | CXR1: DY111 | CXS1: DY111 | CXT1: DY112 | CXU1: DY112 | CXV1: DY112 | CXW1: DY112 | CXX1: DY112 | CXY1: DY112 | CXZ1: DY112 | CYA1: DY112 | CYB1: DY112 | CYC1: DY112 | CYD1: DY112 | CYE1: DY112 | CYF1: DY112 | CYG1: DY112 | CYH1: DY112 | CYI1: DY112 | CYJ1: DY112 | CYK1: DY112 | CYL1: DY112 | CYM1: DY112 | CYN1: DY112 | CYO1: DY112 | CYP1: DY112 | CYQ1: DY112 | CYR1: DY113 | CYS1: DY113 | CYT1: DY113 | CYU1: DY113 | CYV1: DY113 | CYW1: DY113 | CYX1: DY113 | CYY1: DY113 | CYZ1: DY113 | CZA1: DY113 | CZB1: DY113 | CZC1: DY113 | CZD1: DY113 | CZE1: DY113 | CZF1: DY113 | CZG1: DY113 | CZH1: DY113 | CZI1: DY113 | CZJ1: DY113 | CZK1: DY113 | CZL1: DY113 | CZM1: DY113 | CZN1: DY113 | CZO1: DY113 | CZP1: DY114 | CZQ1: DY114 | CZR1: DY114 | CZS1: DY114 | CZT1: DY114 | CZU1: DY114 | CZV1: DY114 | CZW1: DY114 | CZX1: DY114 | CZY1: DY114 | CZZ1: DY114 | DAA1: DY114 | DAB1: DY114 | DAC1: DY114 | DAD1: DY114 | DAE1: DY114 | DAF1: DY114 | DAG1: DY114 | DAH1: DY114 | DAI1: DY114 | DAJ1: DY114 | DAK1: DY114 | DAL1: DY114 | DAM1: DY114 | DAN1: DY115 | DAO1: DY115 | DAP1: DY115 | DAQ1: DY115 | DAR1: DY115 | DAS1: DY115 | DAT1: DY115 | DAU1: DY115 | DAV1: DY115 | DAW1: DY115 | DAX1: DY115 | DAY1: DY115 | DAZ1: DY115 | DBA1: DY115 | DBB1: DY115 | DBC1: DY115 | DBD1: DY115 | DBE1: DY115 | DBF1: DY115 | DBG1: DY115 | DBH1: DY115 | DBI1: DY115 | DBJ1: DY115 | DBK1: DY115 | DBL1: DY116 | DBM1: DY116 | DBN1: DY116 | DBO1: DY116 | DBP1: DY116 | DBQ1: DY116 | DBR1: DY116 | DBS1: DY116 | DBT1: DY116 | DBU1: DY116 | DBV1: DY116 | DBW1: DY116 | DBX1: DY116 | DBY1: DY116 | DBZ1: DY116 | DCA1: DY116 | DCB1: DY116 | DCC1: DY116 | DCD1: DY116 | DCE1: DY116 | DCF1: DY116 | DCG1: DY116 | DCH1: DY116 | DCI1: DY116 | DCJ1: DY117 | DCK1: DY117 | DCL1: DY117 | DCM1: DY117 | DCN1: DY117 | DCO1: DY117 | DCP1: DY117 | DCQ1: DY117 | DCR1: DY117 | DCS1: DY117 | DCT1: DY117 | DCU1: DY117 | DCV1: DY117 | DCW1: DY117 | DCX1: DY117 | DCY1: DY117 | DCZ1: DY117 | DDA1: DY117 | DDB1: DY117 | DDC1: DY117 | DDD1: DY117 | DDE1: DY117 | DDF1: DY117 | DDG1: DY117 | DDH1: DY118 | DDI1: DY118 | DDJ1: DY118 | DDK1: DY118 | DDL1: DY118 | DDM1: DY118 | DDN1: DY118 | DDO1: DY118 | DDP1: DY118 | DDQ1: DY118 | DDR1: DY118 | DDS1: DY118 | DDT1: DY118 | DDU1: DY118 | DDV1: DY118 | DDW1: DY118 | DDX1: DY118 | DDY1: DY118 | DDZ1: DY118 | DEA1: DY118 | DEB1: DY118 | DEC1: DY118 | DED1: DY118 | DEE1: DY118 | DEF1: DY119 | DEG1: DY119 | DEH1: DY119 | DEI1: DY119 | DEJ1: DY119 | DEK1: DY119 | DEL1: DY119 | DEM1: DY119 | DEN1: DY119 | DEO1: DY119 | DEP1: DY119 | DEQ1: DY119 | DER1: DY119 | DES1: DY119 | DET1: DY119 | DEU1: DY119 | DEV1: DY119 | DEW1: DY119 | DEX1: DY119 | DEY1: DY119 | DEZ1: DY119 | DFA1: DY119 | DFB1: DY119 | DFC1: DY119 | DFD1: DY120 | DFE1: DY120 | DFF1: DY120 | DFG1: DY120 | DFH1: DY120 | DFI1: DY120 | DFJ1: DY120 | DFK1: DY120 | DFL1: DY120 | DFM1: DY120 | DFN1: DY120 | DFO1: DY120 | DFP1: DY120 | DFQ1: DY120 | DFR1: DY120 | DFS1: DY120 | DFT1: DY120 | DFU1: DY120 | DFV1: DY120 | DFW1: DY120 | DFX1: DY120 | DFY1: DY120 | DFZ1: DY120 | DGA1: DY120 | DGB1: DY121 | DGC1: DY121 | DGD1: DY121 | DGE1: DY121 | DGF1: DY121 | DGG1: DY121 | DGH1: DY121 | DGI1: DY121 | DGJ1: DY121 | DGK1: DY121 | DGL1: DY121 | DGM1: DY121 | DGN1: DY121 | DGO1: DY121 | DGP1: DY121 | DGQ1: DY121 | DGR1: DY121 | DGS1: DY121 | DGT1: DY121 | DGU1: DY121 | DGV1: DY121 | DGW1: DY121 | DGX1: DY121 | DGY1: DY121 | DGZ1: DY122 | DHA1: DY122 | DHB1: DY122 | DHC1: DY122 | DHD1: DY122 | DHE1: DY122 | DHF1: DY122 | DHG1: DY122 | DHH1: DY122 | DHI1: DY122 | DHJ1: DY122 | DHK1: DY122 | DHL1: DY122 | DHM1: DY122 | DHN1: DY122 | DHO1: DY122 | DHP1: DY122 | DHQ1: DY122 | DHR1: DY122 | DHS1: DY122 | DHT1: DY122 | DHU1: DY122 | DHV1: DY122 | DHW1: DY122 | DHX1: DY123 | DHY1: DY123 | DHZ1: DY123 | DIA1: DY123 | DIB1: DY123 | DIC1: DY123 | DID1: DY123 | DIE1: DY123 | DIF1: DY123 | DIG1: DY123 | DIH1: DY123 | DII1: DY123 | DIJ1: DY123 | DIK1: DY123 | DIL1: DY123 | DIM1: DY123 | DIN1: DY123 | DIO1: DY123 | DIP1: DY123 | DIQ1: DY123 | DIR1: DY123 | DIS1: DY123 | DIT1: DY123 | DIU1: DY123 | DIV1: DY124 | DIW1: DY124 | DIX1: DY124 | DIY1: DY124 | DIZ1: DY124 | DJA1: DY124 | DJB1: DY124 | DJC1: DY124 | DJD1: DY124 | DJE1: DY124 | DJF1: DY124 | DJG1: DY124 | DJH1: DY124 | DJI1: DY124 | DJJ1: DY124 | DJK1: DY124 | DJL1: DY124 | DJM1: DY124 | DJN1: DY124 | DJO1: DY124 | DJP1: DY124 | DJQ1: DY124 | DJR1: DY124 | DJS1: DY124 | DJT1: DY125 | DJU1: DY125 | DJV1: DY125 | DJW1: DY125 | DJX1: DY125 | DJY1: DY125 | DJZ1: DY125 | DKA1: DY125 | DKB1: DY125 | DKC1: DY125 | DKD1: DY125 | DKE1: DY125 | DKF1: DY125 | DKG1: DY125 | DKH1: DY125 | DKI1: DY125 | DKJ1: DY125 | DKK1: DY125 | DKL1: DY125 | DKM1: DY125 | DKN1: DY125 | DKO1: DY125 | DKP1: DY125 | DKQ1: DY125 | DKR1: DY126 | DKS1: DY126 | DKT1: DY126 | DKU1: DY126 | DKV1: DY126 | DKW1: DY126 | DKX1: DY126 | DKY1: DY126 | DKZ1: DY126 | DLA1: DY126 | DLB1: DY126 | DLC1: DY126 | DLD1: DY126 | DLE1: DY126 | DLF1: DY126 | DLG1: DY126 | DLH1: DY126 | DLI1: DY126 | DLJ1: DY126 | DLK1: DY126 | DLL1: DY126 | DLM1: DY126 | DLN1: DY126 | DLO1: DY126 | DLP1: DY127 | DLQ1: DY127 | DLR1: DY127 | DLS1: DY127 | DLT1: DY127 | DLU1: DY127 | DLV1: DY127 | DLW1: DY127 | DLX1: DY127 | DLY1: DY127 | DLZ1: DY127 | DMA1: DY127 | DMB1: DY127 | DMC1: DY127 | DMD1: DY127 | DME1: DY127 | DMF1: DY127 | DMG1: DY127 | DMH1: DY127 | DMI1: DY127 | DMJ1: DY127 | DMK1: DY127 | DML1: DY127 | DMM1: DY127 | DMN1: DY128 | DMO1: DY128 | DMP1: DY128 | DMQ1: DY128 | DMR1: DY128 | DMS1: DY128 | DMT1: DY128 | DMU1: DY128 | DMV1: DY128 | DMW1: DY128 | DMX1: DY128 | DMY1: DY128 | DMZ1: DY128 | DNA1: DY128 | DNB1: DY128 | DNC1: DY128 | DND1: DY128 | DNE1: DY128 | DNF1: DY128 | DNG1: DY128 | DNH1: DY128 | DNI1: DY128 | DNJ1: DY128 | DNK1: DY128 | DNL1: DY129 | DNM1: DY129 | DNN1: DY129 | DNO1: DY129 | DNP1: DY129 | DNQ1: DY129 | DNR1: DY129 | DNS1: DY129 | DNT1: DY129 | DNU1: DY129 | DNV1: DY129 | DNW1: DY129 | DNX1: DY129 | DNY1: DY129 | DNZ1: DY129 | DOA1: DY129 | DOB1: DY129 | DOC1: DY129 | DOD1: DY129 | DOE1: DY129 | DOF1: DY129 | DOG1: DY129 | DOH1: DY129 | DOI1: DY129 | DOJ1: DY130 | DOK1: DY130 | DOL1: DY130 | DOM1: DY130 | DON1: DY130 | DOO1: DY130 | DOP1: DY130 | DOQ1: DY130 | DOR1: DY130 | DOS1: DY130 | DOT1: DY130 | DOU1: DY130 | DOV1: DY130 | DOW1: DY130 | DOX1: DY130 | DOY1: DY130 | DOZ1: DY130 | DPA1: DY130 | DPB1: DY130 | DPC1: DY130 | DPD1: DY130 | DPE1: DY130 | DPF1: DY130 | DPG1: DY130 | DPH1: DY131 | DPI1: DY131 | DPJ1: DY131 | DPK1: DY131 | DPL1: DY131 | DPM1: DY131 | DPN1: DY131 | DPO1: DY131 | DPP1: DY131 | DPQ1: DY131 | DPR1: DY131 | DPS1: DY131 | DPT1: DY131 | DPU1: DY131 | DPV1: DY131 | DPW1: DY131 | DPX1: DY131 | DPY1: DY131 | DPZ1: DY131 | DQA1: DY131 | DQB1: DY131 | DQC1: DY131 | DQD1: DY131 | DQE1: DY131 | DQF1: DY132 | DQG1: DY132 | DQH1: DY132 | DQI1: DY132 | DQJ1: DY132 | DQK1: DY132 | DQL1: DY132 | DQM1: DY132 | DQN1: DY132 | DQO1: DY132 | DQP1: DY132 | DQQ1: DY132 | DQR1: DY132 | DQS1: DY132 | DQT1: DY132 | DQU1: DY132 | DQV1: DY132 | DQW1: DY132 | DQX1: DY132 | DQY1: DY132 | DQZ1: DY132 | DRA1: DY132 | DRB1: DY132 | DRC1: DY132 | DRD1: DY133 | DRE1: DY133 | DRF1: DY133 | DRG1: DY133 | DRH1: DY133 | DRI1: DY133 | DRJ1: DY133 | DRK1: DY133 | DRL1: DY133 | DRM1: DY133 | DRN1: DY133 | DRO1: DY133 | DRP1: DY133 | DRQ1: DY133 | DRR1: DY133 | DRS1: DY133 | DRT1: DY133 | DRU1: DY133 | DRV1: DY133 | DRW1: DY133 | DRX1: DY133 | DRY1: DY133 | DRZ1: DY133 | DSA1: DY133 | DSB1: DY134 | DSC1: DY134 | DSD1: DY134 | DSE1: DY134 | DSF1: DY134 | DSG1: DY134 | DSH1: DY134 | DSI1: DY134 | DSJ1: DY134 | DSK1: DY134 | DSL1: DY134 | DSM1: DY134 | DSN1: DY134 | DSO1: DY134 | DSP1: DY134 | DSQ1: DY134 | DSR1: DY134 | DSS1: DY134 | DST1: DY134 | DSU1: DY134 | DSV1: DY134 | DSW1: DY134 | DSX1: DY134 | DSY1: DY134 | DSZ1: DY135 | DTA1: DY135 | DTB1: DY135 | DTC1: DY135 | DTD1: DY135 | DTE1: DY135 | DTF1: DY135 | DTG1: DY135 | DTH1: DY135 | DTI1: DY135 | DTJ1: DY135 | DTK1: DY135 | DTL1: DY135 | DTM1: DY135 | DTN1: DY135 | DTO1: DY135 | DTP1: DY135 | DTQ1: DY135 | DTR1: DY135 | DTS1: DY135 | DTT1: DY135 | DTU1: DY135 | DTV1: DY135 | DTW1: DY135 | DTX1: DY136 | DTY1: DY136 | DTZ1: DY136 | DUA1: DY136 | DUB1: DY136 | DUC1: DY136 | DUD1: DY136 | DUE1: DY136 | DUF1: DY136 | DUG1: DY136 | DUH1: DY136 | DUI1: DY136 | DUJ1: DY136 | DUK1: DY136 | DUL1: DY136 | DUM1: DY136 | DUN1: DY136 | DUO1: DY136 | DUP1: DY136 | DUQ1: DY136 | DUR1: DY136 | DUS1: DY136 | DUT1: DY136 | DUU1: DY136 | DUV1: DY137 | DUW1: DY137 | DUX1: DY137 | DUY1: DY137 | DUZ1: DY137 | DVA1: DY137 | DVB1: DY137 | DVC1: DY137 | DVD1: DY137 | DVE1: DY137 | DVF1: DY137 | DVG1: DY137 | DVH1: DY137 | DVI1: DY137 | DVJ1: DY137 | DVK1: DY137 | DVL1: DY137 | DVM1: DY137 | DVN1: DY137 | DVO1: DY137 | DVP1: DY137 | DVQ1: DY137 | DVR1: DY137 | DVS1: DY137 | DVT1: DY138 | DVU1: DY138 | DVV1: DY138 | DVW1: DY138 | DVX1: DY138 | DVY1: DY138 | DVZ1: DY138 | DWA1: DY138 | DWB1: DY138 | DWC1: DY138 | DWD1: DY138 | DWE1: DY138 | DWF1: DY138 | DWG1: DY138 | DWH1: DY138 | DWI1: DY138 | DWJ1: DY138 | DWK1: DY138 | DWL1: DY138 | DWM1: DY138 | DWN1: DY138 | DWO1: DY138 | DWP1: DY138 | DWQ1: DY138 | DWR1: DY139 | DWS1: DY139 | DWT1: DY139 | DWU1: DY139 | DWV1: DY139 | DWW1: DY139 | DWX1: DY139 | DWY1: DY139 | DWZ1: DY139 | DXA1: DY139 | DXB1: DY139 | DXC1: DY139 | DXD1: DY139 | DXE1: DY139 | DXF1: DY139 | DXG1: DY139 | DXH1: DY139 | DXI1: DY139 | DXJ1: DY139 | DXK1: DY139 | DXL1: DY139 | DXM1: DY139 | DXN1: DY139 | DXO1: DY139 | DXP1: DY140 | DXQ1: DY140 | DXR1: DY140 | DXS1: DY140 | DXT1: DY140 | DXU1: DY140 | DXV1: DY140 | DXW1: DY140 | DXX1: DY140 | DXY1: DY140 | DXZ1: DY140 | DYA1: DY140 | DYB1: DY140 | DYC1: DY140 | DYD1: DY140 | DYE1: DY140 | DYF1: DY140 | DYG1: DY140 | DYH1: DY140 | DYI1: DY140 | DYJ1: DY140 | DYK1: DY140 | DYL1: DY140 | DYM1: DY140 | DYN1: DY141 | DYO1: DY141 | DYP1: DY141 | DYQ1: DY141 | DYR1: DY141 | DYS1: DY141 | DYT1: DY141 | DYU1: DY141 | DYV1: DY141 | DYW1: DY141 | DYX1: DY141 | DYY1: DY141 | DYZ1: DY141 | DZA1: DY141 | DZB1: DY141 | DZC1: DY141 | DZD1: DY141 | DZE1: DY141 | DZF1: DY141 | DZG1: DY141 | DZH1: DY141 | DZI1: DY141 | DZJ1: DY141 | DZK1: DY141 | DZL1: DY142 | DZM1: DY142 | DZN1: DY142 | DZO1: DY142 | DZP1: DY142 | DZQ1: DY142 | DZR1: DY142 | DZS1: DY142 | DZT1: DY142 | DZU1: DY142 | DZV1: DY142 | DZW1: DY142 | DZX1: DY142 | DZY1: DY142 | DZZ1: DY142 | EAA1: DY142 | EAB1: DY142 | EAC1: DY142 | EAD1: DY142 | EAE1: DY142 | EAF1: DY142 | EAG1: DY142 | EAH1: DY142 | EAI1: DY142 | EAJ1: DY143 | EAK1: DY143 | EAL1: DY143 | EAM1: DY143 | EAN1: DY143 | EAO1: DY143 | EAP1: DY143 | EAQ1: DY143 | EAR1: DY143 | EAS1: DY143 | EAT1: DY143 | EAU1: DY143 | EAV1: DY143 | EAW1: DY143 | EAX1: DY143 | EAY1: DY143 | EAZ1: DY143 | EBA1: DY143 | EBB1: DY143 | EBC1: DY143 | EBD1: DY143 | EBE1: DY143 | EBF1: DY143 | EBG1: DY143 | EBH1: DY144 | EBI1: DY144 | EBJ1: DY144 | EBK1: DY144 | EBL1: DY144 | EBM1: DY144 | EBN1: DY144 | EBO1: DY144 | EBP1: DY144 | EBQ1: DY144 | EBR1: DY144 | EBS1: DY144 | EBT1: DY144 | EBU1: DY144 | EBV1: DY144 | EBW1: DY144 | EBX1: DY144 | EBY1: DY144 | EBZ1: DY144 | ECA1: DY144 | ECB1: DY144 | ECC1: DY144 | ECD1: DY144 | ECE1: DY144 | ECF1: DY145 | ECG1: DY145 | ECH1: DY145 | ECI1: DY145 | ECJ1: DY145 | ECK1: DY145 | ECL1: DY145 | ECM1: DY145 | ECN1: DY145 | ECO1: DY145 | ECP1: DY145 | ECQ1: DY145 | ECR1: DY145 | ECS1: DY145 | ECT1: DY145 | ECU1: DY145 | ECV1: DY145 | ECW1: DY145 | ECX1: DY145 | ECY1: DY145 | ECZ1: DY145 | EDA1: DY145 | EDB1: DY145 | EDC1: DY145 | EDD1: DY146 | EDE1: DY146 | EDF1: DY146 | EDG1: DY146 | EDH1: DY146 | EDI1: DY146 | EDJ1: DY146 | EDK1: DY146 | EDL1: DY146 | EDM1: DY146 | EDN1: DY146 | EDO1: DY146 | EDP1: DY146 | EDQ1: DY146 | EDR1: DY146 | EDS1: DY146 | EDT1: DY146 | EDU1: DY146 | EDV1: DY146 | EDW1: DY146 | EDX1: DY146 | EDY1: DY146 | EDZ1: DY146 | EEA1: DY146 | EEB1: DY147 | EEC1: DY147 | EED1: DY147 | EEE1: DY147 | EEF1: DY147 | EEG1: DY147 | EEH1: DY147 | EEI1: DY147 | EEJ1: DY147 | EEK1: DY147 | EEL1: DY147 | EEM1: DY147 | EEN1: DY147 | EEO1: DY147 | EEP1: DY147 | EEQ1: DY147 | EER1: DY147 | EES1: DY147 | EET1: DY147 | EEU1: DY147 | EEV1: DY147 | EEW1: DY147 | EEX1: DY147 | EEY1: DY147 | EEZ1: DY148 | EFA1: DY148 | EFB1: DY148 | EFC1: DY148 | EFD1: DY148 | EFE1: DY148 | EFF1: DY148 | EFG1: DY148 | EFH1: DY148 | EFI1: DY148 | EFJ1: DY148 | EFK1: DY148 | EFL1: DY148 | EFM1: DY148 | EFN1: DY148 | EFO1: DY148 | EFP1: DY148 | EFQ1: DY148 | EFR1: DY148 | EFS1: DY148 | EFT1: DY148 | EFU1: DY148 | EFV1: DY148 | EFW1: DY148 | EFX1: DY149 | EFY1: DY149 | EFZ1: DY149 | EGA1: DY149 | EGB1: DY149 | EGC1: DY149 | EGD1: DY149 | EGE1: DY149 | EGF1: DY149 | EGG1: DY149 | EGH1: DY149 | EGI1: DY149 | EGJ1: DY149 | EGK1: DY149 | EGL1: DY149 | EGM1: DY149 | EGN1: DY149 | EGO1: DY149 | EGP1: DY149 | EGQ1: DY149 | EGR1: DY149 | EGS1: DY149 | EGT1: DY149 | EGU1: DY149 | EGV1: DY150 | EGW1: DY150 | EGX1: DY150 | EGY1: DY150 | EGZ1: DY150 | EHA1: DY150 | EHB1: DY150 | EHC1: DY150 | EHD1: DY150 | EHE1: DY150 | EHF1: DY150 | EHG1: DY150 | EHH1: DY150 | EHI1: DY150 | EHJ1: DY150 | EHK1: DY150 | EHL1: DY150 | EHM1: DY150 | EHN1: DY150 | EHO1: DY150 | EHP1: DY150 | EHQ1: DY150 | EHR1: DY150 | EHS1: DY150 | EHT1: DY151 | EHU1: DY151 | EHV1: DY151 | EHW1: DY151 | EHX1: DY151 | EHY1: DY151 | EHZ1: DY151 | EIA1: DY151 | EIB1: DY151 | EIC1: DY151 | EID1: DY151 | EIE1: DY151 | EIF1: DY151 | EIG1: DY151 | EIH1: DY151 | EII1: DY151 | EIJ1: DY151 | EIK1: DY151 | EIL1: DY151 | EIM1: DY151 | EIN1: DY151 | EIO1: DY151 | EIP1: DY151 | EIQ1: DY151 | EIR1: DY152 | EIS1: DY152 | EIT1: DY152 | EIU1: DY152 | EIV1: DY152 | EIW1: DY152 | EIX1: DY152 | EIY1: DY152 | EIZ1: DY152 | EJA1: DY152 | EJB1: DY152 | EJC1: DY152 | EJD1: DY152 | EJE1: DY152 | EJF1: DY152 | EJG1: DY152 | EJH1: DY152 | EJI1: DY152 | EJJ1: DY152 | EJK1: DY152 | EJL1: DY152 | EJM1: DY152 | EJN1: DY152 | EJO1: DY152 | EJP1: DY153 | EJQ1: DY153 | EJR1: DY153 | EJS1: DY153 | EJT1: DY153 | EJU1: DY153 | EJV1: DY153 | EJW1: DY153 | EJX1: DY153 | EJY1: DY153 | EJZ1: DY153 | EKA1: DY153 | EKB1: DY153 | EKC1: DY153 | EKD1: DY153 | EKE1: DY153 | EKF1: DY153 | EKG1: DY153 | EKH1: DY153 | EKI1: DY153 | EKJ1: DY153 | EKK1: DY153 | EKL1: DY153 | EKM1: DY153 | EKN1: DY154 | EKO1: DY154 | EKP1: DY154 | EKQ1: DY154 | EKR1: DY154 | EKS1: DY154 | EKT1: DY154 | EKU1: DY154 | EKV1: DY154 | EKW1: DY154 | EKX1: DY154 | EKY1: DY154 | EKZ1: DY154 | ELA1: DY154 | ELB1: DY154 | ELC1: DY154 | ELD1: DY154 | ELE1: DY154 | ELF1: DY154 | ELG1: DY154 | ELH1: DY154 | ELI1: DY154 | ELJ1: DY154 | ELK1: DY154 | ELL1: DY155 | ELM1: DY155 | ELN1: DY155 | ELO1: DY155 | ELP1: DY155 | ELQ1: DY155 | ELR1: DY155 | ELS1: DY155 | ELT1: DY155 | ELU1: DY155 | ELV1: DY155 | ELW1: DY155 | ELX1: DY155 | ELY1: DY155 | ELZ1: DY155 | EMA1: DY155 | EMB1: DY155 | EMC1: DY155 | EMD1: DY155 | EME1: DY155 | EMF1: DY155 | EMG1: DY155 | EMH1: DY155 | EMI1: DY155 | EMJ1: DY156 | EMK1: DY156 | EML1: DY156 | EMM1: DY156 | EMN1: DY156 | EMO1: DY156 | EMP1: DY156 | EMQ1: DY156 | EMR1: DY156 | EMS1: DY156 | EMT1: DY156 | EMU1: DY156 | EMV1: DY156 | EMW1: DY156 | EMX1: DY156 | EMY1: DY156 | EMZ1: DY156 | ENA1: DY156 | ENB1: DY156 | ENC1: DY156 | END1: DY156 | ENE1: DY156 | ENF1: DY156 | ENG1: DY156 | ENH1: DY157 | ENI1: DY157 | ENJ1: DY157 | ENK1: DY157 | ENL1: DY157 | ENM1: DY157 | ENN1: DY157 | ENO1: DY157 | ENP1: DY157 | ENQ1: DY157 | ENR1: DY157 | ENS1: DY157 | ENT1: DY157 | ENU1: DY157 | ENV1: DY157 | ENW1: DY157 | ENX1: DY157 | ENY1: DY157 | ENZ1: DY157 | EOA1: DY157 | EOB1: DY157 | EOC1: DY157 | EOD1: DY157 | EOE1: DY157 | EOF1: DY158 | EOG1: DY158 | EOH1: DY158 | EOI1: DY158 | EOJ1: DY158 | EOK1: DY158 | EOL1: DY158 | EOM1: DY158 | EON1: DY158 | EOO1: DY158 | EOP1: DY158 | EOQ1: DY158 | EOR1: DY158 | EOS1: DY158 | EOT1: DY158 | EOU1: DY158 | EOV1: DY158 | EOW1: DY158 | EOX1: DY158 | EOY1: DY158 | EOZ1: DY158 | EPA1: DY158 | EPB1: DY158 | EPC1: DY158 | EPD1: DY159 | EPE1: DY159 | EPF1: DY159 | EPG1: DY159 | EPH1: DY159 | EPI1: DY159 | EPJ1: DY159 | EPK1: DY159 | EPL1: DY159 | EPM1: DY159 | EPN1: DY159 | EPO1: DY159 | EPP1: DY159 | EPQ1: DY159 | EPR1: DY159 | EPS1: DY159 | EPT1: DY159 | EPU1: DY159 | EPV1: DY159 | EPW1: DY159 | EPX1: DY159 | EPY1: DY159 | EPZ1: DY159 | EQA1: DY159 | EQB1: DY160 | EQC1: DY160 | EQD1: DY160 | EQE1: DY160 | EQF1: DY160 | EQG1: DY160 | EQH1: DY160 | EQI1: DY160 | EQJ1: DY160 | EQK1: DY160 | EQL1: DY160 | EQM1: DY160 | EQN1: DY160 | EQO1: DY160 | EQP1: DY160 | EQQ1: DY160 | EQR1: DY160 | EQS1: DY160 | EQT1: DY160 | EQU1: DY160 | EQV1: DY160 | EQW1: DY160 | EQX1: DY160 | EQY1: DY160 | EQZ1: DY161 | ERA1: DY161 | ERB1: DY161 | ERC1: DY161 | ERD1: DY161 | ERE1: DY161 | ERF1: DY161 | ERG1: DY161 | ERH1: DY161 | ERI1: DY161 | ERJ1: DY161 | ERK1: DY161 | ERL1: DY161 | ERM1: DY161 | ERN1: DY161 | ERO1: DY161 | ERP1: DY161 | ERQ1: DY161 | ERR1: DY161 | ERS1: DY161 | ERT1: DY161 | ERU1: DY161 | ERV1: DY161 | ERW1: DY161 | ERX1: DY162 | ERY1: DY162 | ERZ1: DY162 | ESA1: DY162 | ESB1: DY162 | ESC1: DY162 | ESD1: DY162 | ESE1: DY162 | ESF1: DY162 | ESG1: DY162 | ESH1: DY162 | ESI1: DY162 | ESJ1: DY162 | ESK1: DY162 | ESL1: DY162 | ESM1: DY162 | ESN1: DY162 | ESO1: DY162 | ESP1: DY162 | ESQ1: DY162 | ESR1: DY162 | ESS1: DY162 | EST1: DY162 | ESU1: DY162 | ESV1: DY163 | ESW1: DY163 | ESX1: DY163 | ESY1: DY163 | ESZ1: DY163 | ETA1: DY163 | ETB1: DY163 | ETC1: DY163 | ETD1: DY163 | ETE1: DY163 | ETF1: DY163 | ETG1: DY163 | ETH1: DY163 | ETI1: DY163 | ETJ1: DY163 | ETK1: DY163 | ETL1: DY163 | ETM1: DY163 | ETN1: DY163 | ETO1: DY163 | ETP1: DY163 | ETQ1: DY163 | ETR1: DY163 | ETS1: DY163 | ETT1: DY164 | ETU1: DY164 | ETV1: DY164 | ETW1: DY164 | ETX1: DY164 | ETY1: DY164 | ETZ1: DY164 | EUA1: DY164 | EUB1: DY164 | EUC1: DY164 | EUD1: DY164 | EUE1: DY164 | EUF1: DY164 | EUG1: DY164 | EUH1: DY164 | EUI1: DY164 | EUJ1: DY164 | EUK1: DY164 | EUL1: DY164 | EUM1: DY164 | EUN1: DY164 | EUO1: DY164 | EUP1: DY164 | EUQ1: DY164 | EUR1: DY165 | EUS1: DY165 | EUT1: DY165 | EUU1: DY165 | EUV1: DY165 | EUW1: DY165 | EUX1: DY165 | EUY1: DY165 | EUZ1: DY165 | EVA1: DY165 | EVB1: DY165 | EVC1: DY165 | EVD1: DY165 | EVE1: DY165 | EVF1: DY165 | EVG1: DY165 | EVH1: DY165 | EVI1: DY165 | EVJ1: DY165 | EVK1: DY165 | EVL1: DY165 | EVM1: DY165 | EVN1: DY165 | EVO1: DY165 | EVP1: DY166 | EVQ1: DY166 | EVR1: DY166 | EVS1: DY166 | EVT1: DY166 | EVU1: DY166 | EVV1: DY166 | EVW1: DY166 | EVX1: DY166 | EVY1: DY166 | EVZ1: DY166 | EWA1: DY166 | EWB1: DY166 | EWC1: DY166 | EWD1: DY166 | EWE1: DY166 | EWF1: DY166 | EWG1: DY166 | EWH1: DY166 | EWI1: DY166 | EWJ1: DY166 | EWK1: DY166 | EWL1: DY166 | EWM1: DY166 | EWN1: DY167 | EWO1: DY167 | EWP1: DY167 | EWQ1: DY167 | EWR1: DY167 | EWS1: DY167 | EWT1: DY167 | EWU1: DY167 | EWV1: DY167 | EWW1: DY167 | EWX1: DY167 | EWY1: DY167 | EWZ1: DY167 | EXA1: DY167 | EXB1: DY167 | EXC1: DY167 | EXD1: DY167 | EXE1: DY167 | EXF1: DY167 | EXG1: DY167 | EXH1: DY167 | EXI1: DY167 | EXJ1: DY167 | EXK1: DY167 | EXL1: DY168 | EXM1: DY168 | EXN1: DY168 | EXO1: DY168 | EXP1: DY168 | EXQ1: DY168 | EXR1: DY168 | EXS1: DY168 | EXT1: DY168 | EXU1: DY168 | EXV1: DY168 | EXW1: DY168 | EXX1: DY168 | EXY1: DY168 | EXZ1: DY168 | EYA1: DY168 | EYB1: DY168 | EYC1: DY168 | EYD1: DY168 | EYE1: DY168 | EYF1: DY168 | EYG1: DY168 | EYH1: DY168 | EYI1: DY168 | EYJ1: DY169 | EYK1: DY169 | EYL1: DY169 | EYM1: DY169 | EYN1: DY169 | EYO1: DY169 | EYP1: DY169 | EYQ1: DY169 | EYR1: DY169 | EYS1: DY169 | EYT1: DY169 | EYU1: DY169 | EYV1: DY169 | EYW1: DY169 | EYX1: DY169 | EYY1: DY169 | EYZ1: DY169 | EZA1: DY169 | EZB1: DY169 | EZC1: DY169 | EZD1: DY169 | EZE1: DY169 | EZF1: DY169 | EZG1: DY169 | EZH1: DY170 | EZI1: DY170 | EZJ1: DY170 | EZK1: DY170 | EZL1: DY170 | EZM1: DY170 | EZN1: DY170 | EZO1: DY170 | EZP1: DY170 | EZQ1: DY170 | EZR1: DY170 | EZS1: DY170 | EZT1: DY170 | EZU1: DY170 | EZV1: DY170 | EZW1: DY170 | EZX1: DY170 | EZY1: DY170 | EZZ1: DY170 | FAA1: DY170 | FAB1: DY170 | FAC1: DY170 | FAD1: DY170 | FAE1: DY170 | FAF1: DY171 | FAG1: DY171 | FAH1: DY171 | FAI1: DY171 | FAJ1: DY171 | FAK1: DY171 | FAL1: DY171 | FAM1: DY171 | FAN1: DY171 | FAO1: DY171 | FAP1: DY171 | FAQ1: DY171 | FAR1: DY171 | FAS1: DY171 | FAT1: DY171 | FAU1: DY171 | FAV1: DY171 | FAW1: DY171 | FAX1: DY171 | FAY1: DY171 | FAZ1: DY171 | FBA1: DY171 | FBB1: DY171 | FBC1: DY171 | FBD1: DY172 | FBE1: DY172 | FBF1: DY172 | FBG1: DY172 | FBH1: DY172 | FBI1: DY172 | FBJ1: DY172 | FBK1: DY172 | FBL1: DY172 | FBM1: DY172 | FBN1: DY172 | FBO1: DY172 | FBP1: DY172 | FBQ1: DY172 | FBR1: DY172 | FBS1: DY172 | FBT1: DY172 | FBU1: DY172 | FBV1: DY172 | FBW1: DY172 | FBX1: DY172 | FBY1: DY172 | FBZ1: DY172 | FCA1: DY172 | FCB1: DY173 | FCC1: DY173 | FCD1: DY173 | FCE1: DY173 | FCF1: DY173 | FCG1: DY173 | FCH1: DY173 | FCI1: DY173 | FCJ1: DY173 | FCK1: DY173 | FCL1: DY173 | FCM1: DY173 | FCN1: DY173 | FCO1: DY173 | FCP1: DY173 | FCQ1: DY173 | FCR1: DY173 | FCS1: DY173 | FCT1: DY173 | FCU1: DY173 | FCV1: DY173 | FCW1: DY173 | FCX1: DY173 | FCY1: DY173 | FCZ1: DY174 | FDA1: DY174 | FDB1: DY174 | FDC1: DY174 | FDD1: DY174 | FDE1: DY174 | FDF1: DY174 | FDG1: DY174 | FDH1: DY174 | FDI1: DY174 | FDJ1: DY174 | FDK1: DY174 | FDL1: DY174 | FDM1: DY174 | FDN1: DY174 | FDO1: DY174 | FDP1: DY174 | FDQ1: DY174 | FDR1: DY174 | FDS1: DY174 | FDT1: DY174 | FDU1: DY174 | FDV1: DY174 | FDW1: DY174 | FDX1: DY175 | FDY1: DY175 | FDZ1: DY175 | FEA1: DY175 | FEB1: DY175 | FEC1: DY175 | FED1: DY175 | FEE1: DY175 | FEF1: DY175 | FEG1: DY175 | FEH1: DY175 | FEI1: DY175 | FEJ1: DY175 | FEK1: DY175 | FEL1: DY175 | FEM1: DY175 | FEN1: DY175 | FEO1: DY175 | FEP1: DY175 | FEQ1: DY175 | FER1: DY175 | FES1: DY175 | FET1: DY175 | FEU1: DY175 | FEV1: DY176 | FEW1: DY176 | FEX1: DY176 | FEY1: DY176 | FEZ1: DY176 | FFA1: DY176 | FFB1: DY176 | FFC1: DY176 | FFD1: DY176 | FFE1: DY176 | FFF1: DY176 | FFG1: DY176 | FFH1: DY176 | FFI1: DY176 | FFJ1: DY176 | FFK1: DY176 | FFL1: DY176 | FFM1: DY176 | FFN1: DY176 | FFO1: DY176 | FFP1: DY176 | FFQ1: DY176 | FFR1: DY176 | FFS1: DY176 | FFT1: DY177 | FFU1: DY177 | FFV1: DY177 | FFW1: DY177 | FFX1: DY177 | FFY1: DY177 | FFZ1: DY177 | FGA1: DY177 | FGB1: DY177 | FGC1: DY177 | FGD1: DY177 | FGE1: DY177 | FGF1: DY177 | FGG1: DY177 | FGH1: DY177 | FGI1: DY177 | FGJ1: DY177 | FGK1: DY177 | FGL1: DY177 | FGM1: DY177 | FGN1: DY177 | FGO1: DY177 | FGP1: DY177 | FGQ1: DY177 | FGR1: DY178 | FGS1: DY178 | FGT1: DY178 | FGU1: DY178 | FGV1: DY178 | FGW1: DY178 | FGX1: DY178 | FGY1: DY178 | FGZ1: DY178 | FHA1: DY178 | FHB1: DY178 | FHC1: DY178 | FHD1: DY178 | FHE1: DY178 | FHF1: DY178 | FHG1: DY178 | FHH1: DY178 | FHI1: DY178 | FHJ1: DY178 | FHK1: DY178 | FHL1: DY178 | FHM1: DY178 | FHN1: DY178 | FHO1: DY178 | FHP1: DY179 | FHQ1: DY179 | FHR1: DY179 | FHS1: DY179 | FHT1: DY179 | FHU1: DY179 | FHV1: DY179 | FHW1: DY179 | FHX1: DY179 | FHY1: DY179 | FHZ1: DY179 | FIA1: DY179 | FIB1: DY179 | FIC1: DY179 | FID1: DY179 | FIE1: DY179 | FIF1: DY179 | FIG1: DY179 | FIH1: DY179 | FII1: DY179 | FIJ1: DY179 | FIK1: DY179 | FIL1: DY179 | FIM1: DY179 | FIN1: DY180 | FIO1: DY180 | FIP1: DY180 | FIQ1: DY180 | FIR1: DY180 | FIS1: DY180 | FIT1: DY180 | FIU1: DY180 | FIV1: DY180 | FIW1: DY180 | FIX1: DY180 | FIY1: DY180 | FIZ1: DY180 | FJA1: DY180 | FJB1: DY180 | FJC1: DY180 | FJD1: DY180 | FJE1: DY180 | FJF1: DY180 | FJG1: DY180 | FJH1: DY180 | FJI1: DY180 | FJJ1: DY180 | FJK1: DY180 | FJL1: DY181 | FJM1: DY181 | FJN1: DY181 | FJO1: DY181 | FJP1: DY181 | FJQ1: DY181 | FJR1: DY181 | FJS1: DY181 | FJT1: DY181 | FJU1: DY181 | FJV1: DY181 | FJW1: DY181 | FJX1: DY181 | FJY1: DY181 | FJZ1: DY181 | FKA1: DY181 | FKB1: DY181 | FKC1: DY181 | FKD1: DY181 | FKE1: DY181 | FKF1: DY181 | FKG1: DY181 | FKH1: DY181 | FKI1: DY181 | FKJ1: DY182 | FKK1: DY182 | FKL1: DY182 | FKM1: DY182 | FKN1: DY182 | FKO1: DY182 | FKP1: DY182 | FKQ1: DY182 | FKR1: DY182 | FKS1: DY182 | FKT1: DY182 | FKU1: DY182 | FKV1: DY182 | FKW1: DY182 | FKX1: DY182 | FKY1: DY182 | FKZ1: DY182 | FLA1: DY182 | FLB1: DY182 | FLC1: DY182 | FLD1: DY182 | FLE1: DY182 | FLF1: DY182 | FLG1: DY182 | FLH1: DY183 | FLI1: DY183 | FLJ1: DY183 | FLK1: DY183 | FLL1: DY183 | FLM1: DY183 | FLN1: DY183 | FLO1: DY183 | FLP1: DY183 | FLQ1: DY183 | FLR1: DY183 | FLS1: DY183 | FLT1: DY183 | FLU1: DY183 | FLV1: DY183 | FLW1: DY183 | FLX1: DY183 | FLY1: DY183 | FLZ1: DY183 | FMA1: DY183 | FMB1: DY183 | FMC1: DY183 | FMD1: DY183 | FME1: DY183 | FMF1: DY184 | FMG1: DY184 | FMH1: DY184 | FMI1: DY184 | FMJ1: DY184 | FMK1: DY184 | FML1: DY184 | FMM1: DY184 | FMN1: DY184 | FMO1: DY184 | FMP1: DY184 | FMQ1: DY184 | FMR1: DY184 | FMS1: DY184 | FMT1: DY184 | FMU1: DY184 | FMV1: DY184 | FMW1: DY184 | FMX1: DY184 | FMY1: DY184 | FMZ1: DY184 | FNA1: DY184 | FNB1: DY184 | FNC1: DY184 | FND1: DY185 | FNE1: DY185 | FNF1: DY185 | FNG1: DY185 | FNH1: DY185 | FNI1: DY185 | FNJ1: DY185 | FNK1: DY185 | FNL1: DY185 | FNM1: DY185 | FNN1: DY185 | FNO1: DY185 | FNP1: DY185 | FNQ1: DY185 | FNR1: DY185 | FNS1: DY185 | FNT1: DY185 | FNU1: DY185 | FNV1: DY185 | FNW1: DY185 | FNX1: DY185 | FNY1: DY185 | FNZ1: DY185 | FOA1: DY185 | FOB1: DY186 | FOC1: DY186 | FOD1: DY186 | FOE1: DY186 | FOF1: DY186 | FOG1: DY186 | FOH1: DY186 | FOI1: DY186 | FOJ1: DY186 | FOK1: DY186 | FOL1: DY186 | FOM1: DY186 | FON1: DY186 | FOO1: DY186 | FOP1: DY186 | FOQ1: DY186 | FOR1: DY186 | FOS1: DY186 | FOT1: DY186 | FOU1: DY186 | FOV1: DY186 | FOW1: DY186 | FOX1: DY186 | FOY1: DY186 | FOZ1: DY187 | FPA1: DY187 | FPB1: DY187 | FPC1: DY187 | FPD1: DY187 | FPE1: DY187 | FPF1: DY187 | FPG1: DY187 | FPH1: DY187 | FPI1: DY187 | FPJ1: DY187 | FPK1: DY187 | FPL1: DY187 | FPM1: DY187 | FPN1: DY187 | FPO1: DY187 | FPP1: DY187 | FPQ1: DY187 | FPR1: DY187 | FPS1: DY187 | FPT1: DY187 | FPU1: DY187 | FPV1: DY187 | FPW1: DY187 | FPX1: DY188 | FPY1: DY188 | FPZ1: DY188 | FQA1: DY188 | FQB1: DY188 | FQC1: DY188 | FQD1: DY188 | FQE1: DY188 | FQF1: DY188 | FQG1: DY188 | FQH1: DY188 | FQI1: DY188 | FQJ1: DY188 | FQK1: DY188 | FQL1: DY188 | FQM1: DY188 | FQN1: DY188 | FQO1: DY188 | FQP1: DY188 | FQQ1: DY188 | FQR1: DY188 | FQS1: DY188 | FQT1: DY188 | FQU1: DY188 | FQV1: DY189 | FQW1: DY189 | FQX1: DY189 | FQY1: DY189 | FQZ1: DY189 | FRA1: DY189 | FRB1: DY189 | FRC1: DY189 | FRD1: DY189 | FRE1: DY189 | FRF1: DY189 | FRG1: DY189 | FRH1: DY189 | FRI1: DY189 | FRJ1: DY189 | FRK1: DY189 | FRL1: DY189 | FRM1: DY189 | FRN1: DY189 | FRO1: DY189 | FRP1: DY189 | FRQ1: DY189 | FRR1: DY189 | FRS1: DY189 | FRT1: DY190 | FRU1: DY190 | FRV1: DY190 | FRW1: DY190 | FRX1: DY190 | FRY1: DY190 | FRZ1: DY190 | FSA1: DY190 | FSB1: DY190 | FSC1: DY190 | FSD1: DY190 | FSE1: DY190 | FSF1: DY190 | FSG1: DY190 | FSH1: DY190 | FSI1: DY190 | FSJ1: DY190 | FSK1: DY190 | FSL1: DY190 | FSM1: DY190 | FSN1: DY190 | FSO1: DY190 | FSP1: DY190 | FSQ1: DY190 | FSR1: DY191 | FSS1: DY191 | FST1: DY191 | FSU1: DY191 | FSV1: DY191 | FSW1: DY191 | FSX1: DY191 | FSY1: DY191 | FSZ1: DY191 | FTA1: DY191 | FTB1: DY191 | FTC1: DY191 | FTD1: DY191 | FTE1: DY191 | FTF1: DY191 | FTG1: DY191 | FTH1: DY191 | FTI1: DY191 | FTJ1: DY191 | FTK1: DY191 | FTL1: DY191 | FTM1: DY191 | FTN1: DY191 | FTO1: DY191 | FTP1: DY192 | FTQ1: DY192 | FTR1: DY192 | FTS1: DY192 | FTT1: DY192 | FTU1: DY192 | FTV1: DY192 | FTW1: DY192 | FTX1: DY192 | FTY1: DY192 | FTZ1: DY192 | FUA1: DY192 | FUB1: DY192 | FUC1: DY192 | FUD1: DY192 | FUE1: DY192 | FUF1: DY192 | FUG1: DY192 | FUH1: DY192 | FUI1: DY192 | FUJ1: DY192 | FUK1: DY192 | FUL1: DY192 | FUM1: DY192 | FUN1: DY193 | FUO1: DY193 | FUP1: DY193 | FUQ1: DY193 | FUR1: DY193 | FUS1: DY193 | FUT1: DY193 | FUU1: DY193 | FUV1: DY193 | FUW1: DY193 | FUX1: DY193 | FUY1: DY193 | FUZ1: DY193 | FVA1: DY193 | FVB1: DY193 | FVC1: DY193 | FVD1: DY193 | FVE1: DY193 | FVF1: DY193 | FVG1: DY193 | FVH1: DY193 | FVI1: DY193 | FVJ1: DY193 | FVK1: DY193 | FVL1: DY194 | FVM1: DY194 | FVN1: DY194 | FVO1: DY194 | FVP1: DY194 | FVQ1: DY194 | FVR1: DY194 | FVS1: DY194 | FVT1: DY194 | FVU1: DY194 | FVV1: DY194 | FVW1: DY194 | FVX1: DY194 | FVY1: DY194 | FVZ1: DY194 | FWA1: DY194 | FWB1: DY194 | FWC1: DY194 | FWD1: DY194 | FWE1: DY194 | FWF1: DY194 | FWG1: DY194 | FWH1: DY194 | FWI1: DY194 | FWJ1: DY195 | FWK1: DY195 | FWL1: DY195 | FWM1: DY195 | FWN1: DY195 | FWO1: DY195 | FWP1: DY195 | FWQ1: DY195 | FWR1: DY195 | FWS1: DY195 | FWT1: DY195 | FWU1: DY195 | FWV1: DY195 | FWW1: DY195 | FWX1: DY195 | FWY1: DY195 | FWZ1: DY195 | FXA1: DY195 | FXB1: DY195 | FXC1: DY195 | FXD1: DY195 | FXE1: DY195 | FXF1: DY195 | FXG1: DY195 | FXH1: DY196 | FXI1: DY196 | FXJ1: DY196 | FXK1: DY196 | FXL1: DY196 | FXM1: DY196 | FXN1: DY196 | FXO1: DY196 | FXP1: DY196 | FXQ1: DY196 | FXR1: DY196 | FXS1: DY196 | FXT1: DY196 | FXU1: DY196 | FXV1: DY196 | FXW1: DY196 | FXX1: DY196 | FXY1: DY196 | FXZ1: DY196 | FYA1: DY196 | FYB1: DY196 | FYC1: DY196 | FYD1: DY196 | FYE1: DY196 | FYF1: DY197 | FYG1: DY197 | FYH1: DY197 | FYI1: DY197 | FYJ1: DY197 | FYK1: DY197 | FYL1: DY197 | FYM1: DY197 | FYN1: DY197 | FYO1: DY197 | FYP1: DY197 | FYQ1: DY197 | FYR1: DY197 | FYS1: DY197 | FYT1: DY197 | FYU1: DY197 | FYV1: DY197 | FYW1: DY197 | FYX1: DY197 | FYY1: DY197 | FYZ1: DY197 | FZA1: DY197 | FZB1: DY197 | FZC1: DY197 | FZD1: DY198 | FZE1: DY198 | FZF1: DY198 | FZG1: DY198 | FZH1: DY198 | FZI1: DY198 | FZJ1: DY198 | FZK1: DY198 | FZL1: DY198 | FZM1: DY198 | FZN1: DY198 | FZO1: DY198 | FZP1: DY198 | FZQ1: DY198 | FZR1: DY198 | FZS1: DY198 | FZT1: DY198 | FZU1: DY198 | FZV1: DY198 | FZW1: DY198 | FZX1: DY198 | FZY1: DY198 | FZZ1: DY198 | GAA1: DY198 | GAB1: DY199 | GAC1: DY199 | GAD1: DY199 | GAE1: DY199 | GAF1: DY199 | GAG1: DY199 | GAH1: DY199 | GAI1: DY199 | GAJ1: DY199 | GAK1: DY199 | GAL1: DY199 | GAM1: DY199 | GAN1: DY199 | GAO1: DY199 | GAP1: DY199 | GAQ1: DY199 | GAR1: DY199 | GAS1: DY199 | GAT1: DY199 | GAU1: DY199 | GAV1: DY199 | GAW1: DY199 | GAX1: DY199 | GAY1: DY199 | GAZ1: DY200 | GBA1: DY200 | GBB1: DY200 | GBC1: DY200 | GBD1: DY200 | GBE1: DY200 | GBF1: DY200 | GBG1: DY200 | GBH1: DY200 | GBI1: DY200 | GBJ1: DY200 | GBK1: DY200 | GBL1: DY200 | GBM1: DY200 | GBN1: DY200 | GBO1: DY200 | GBP1: DY200 | GBQ1: DY200 | GBR1: DY200 | GBS1: DY200 | GBT1: DY200 | GBU1: DY200 | GBV1: DY200 | GBW1: DY200 | GBX1: DY201 | GBY1: DY201 | GBZ1: DY201 | GCA1: DY201 | GCB1: DY201 | GCC1: DY201 | GCD1: DY201 | GCE1: DY201 | GCF1: DY201 | GCG1: DY201 | GCH1: DY201 | GCI1: DY201 | GCJ1: DY201 | GCK1: DY201 | GCL1: DY201 | GCM1: DY201 | GCN1: DY201 | GCO1: DY201 | GCP1: DY201 | GCQ1: DY201 | GCR1: DY201 | GCS1: DY201 | GCT1: DY201 | GCU1: DY201 | GCV1: DY202 | GCW1: DY202 | GCX1: DY202 | GCY1: DY202 | GCZ1: DY202 | GDA1: DY202 | GDB1: DY202 | GDC1: DY202 | GDD1: DY202 | GDE1: DY202 | GDF1: DY202 | GDG1: DY202 | GDH1: DY202 | GDI1: DY202 | GDJ1: DY202 | GDK1: DY202 | GDL1: DY202 | GDM1: DY202 | GDN1: DY202 | GDO1: DY202 | GDP1: DY202 | GDQ1: DY202 | GDR1: DY202 | GDS1: DY202 | GDT1: DY203 | GDU1: DY203 | GDV1: DY203 | GDW1: DY203 | GDX1: DY203 | GDY1: DY203 | GDZ1: DY203 | GEA1: DY203 | GEB1: DY203 | GEC1: DY203 | GED1: DY203 | GEE1: DY203 | GEF1: DY203 | GEG1: DY203 | GEH1: DY203 | GEI1: DY203 | GEJ1: DY203 | GEK1: DY203 | GEL1: DY203 | GEM1: DY203 | GEN1: DY203 | GEO1: DY203 | GEP1: DY203 | GEQ1: DY203 | GER1: DY204 | GES1: DY204 | GET1: DY204 | GEU1: DY204 | GEV1: DY204 | GEW1: DY204 | GEX1: DY204 | GEY1: DY204 | GEZ1: DY204 | GFA1: DY204 | GFB1: DY204 | GFC1: DY204 | GFD1: DY204 | GFE1: DY204 | GFF1: DY204 | GFG1: DY204 | GFH1: DY204 | GFI1: DY204 | GFJ1: DY204 | GFK1: DY204 | GFL1: DY204 | GFM1: DY204 | GFN1: DY204 | GFO1: DY204 | GFP1: DY205 | GFQ1: DY205 | GFR1: DY205 | GFS1: DY205 | GFT1: DY205 | GFU1: DY205 | GFV1: DY205 | GFW1: DY205 | GFX1: DY205 | GFY1: DY205 | GFZ1: DY205 | GGA1: DY205 | GGB1: DY205 | GGC1: DY205 | GGD1: DY205 | GGE1: DY205 | GGF1: DY205 | GGG1: DY205 | GGH1: DY205 | GGI1: DY205 | GGJ1: DY205 | GGK1: DY205 | GGL1: DY205 | GGM1: DY205 | GGN1: DY206 | GGO1: DY206 | GGP1: DY206 | GGQ1: DY206 | GGR1: DY206 | GGS1: DY206 | GGT1: DY206 | GGU1: DY206 | GGV1: DY206 | GGW1: DY206 | GGX1: DY206 | GGY1: DY206 | GGZ1: DY206 | GHA1: DY206 | GHB1: DY206 | GHC1: DY206 | GHD1: DY206 | GHE1: DY206 | GHF1: DY206 | GHG1: DY206 | GHH1: DY206 | GHI1: DY206 | GHJ1: DY206 | GHK1: DY206 | GHL1: DY207 | GHM1: DY207 | GHN1: DY207 | GHO1: DY207 | GHP1: DY207 | GHQ1: DY207 | GHR1: DY207 | GHS1: DY207 | GHT1: DY207 | GHU1: DY207 | GHV1: DY207 | GHW1: DY207 | GHX1: DY207 | GHY1: DY207 | GHZ1: DY207 | GIA1: DY207 | GIB1: DY207 | GIC1: DY207 | GID1: DY207 | GIE1: DY207 | GIF1: DY207 | GIG1: DY207 | GIH1: DY207 | GII1: DY207 | GIJ1: DY208 | GIK1: DY208 | GIL1: DY208 | GIM1: DY208 | GIN1: DY208 | GIO1: DY208 | GIP1: DY208 | GIQ1: DY208 | GIR1: DY208 | GIS1: DY208 | GIT1: DY208 | GIU1: DY208 | GIV1: DY208 | GIW1: DY208 | GIX1: DY208 | GIY1: DY208 | GIZ1: DY208 | GJA1: DY208 | GJB1: DY208 | GJC1: DY208 | GJD1: DY208 | GJE1: DY208 | GJF1: DY208 | GJG1: DY208 | GJH1: DY209 | GJI1: DY209 | GJJ1: DY209 | GJK1: DY209 | GJL1: DY209 | GJM1: DY209 | GJN1: DY209 | GJO1: DY209 | GJP1: DY209 | GJQ1: DY209 | GJR1: DY209 | GJS1: DY209 | GJT1: DY209 | GJU1: DY209 | GJV1: DY209 | GJW1: DY209 | GJX1: DY209 | GJY1: DY209 | GJZ1: DY209 | GKA1: DY209 | GKB1: DY209 | GKC1: DY209 | GKD1: DY209 | GKE1: DY209 | GKF1: DY210 | GKG1: DY210 | GKH1: DY210 | GKI1: DY210 | GKJ1: DY210 | GKK1: DY210 | GKL1: DY210 | GKM1: DY210 | GKN1: DY210 | GKO1: DY210 | GKP1: DY210 | GKQ1: DY210 | GKR1: DY210 | GKS1: DY210 | GKT1: DY210 | GKU1: DY210 | GKV1: DY210 | GKW1: DY210 | GKX1: DY210 | GKY1: DY210 | GKZ1: DY210 | GLA1: DY210 | GLB1: DY210 | GLC1: DY210 | GLD1: DY211 | GLE1: DY211 | GLF1: DY211 | GLG1: DY211 | GLH1: DY211 | GLI1: DY211 | GLJ1: DY211 | GLK1: DY211 | GLL1: DY211 | GLM1: DY211 | GLN1: DY211 | GLO1: DY211 | GLP1: DY211 | GLQ1: DY211 | GLR1: DY211 | GLS1: DY211 | GLT1: DY211 | GLU1: DY211 | GLV1: DY211 | GLW1: DY211 | GLX1: DY211 | GLY1: DY211 | GLZ1: DY211 | GMA1: DY211 | GMB1: DY212 | GMC1: DY212 | GMD1: DY212 | GME1: DY212 | GMF1: DY212 | GMG1: DY212 | GMH1: DY212 | GMI1: DY212 | GMJ1: DY212 | GMK1: DY212 | GML1: DY212 | GMM1: DY212 | GMN1: DY212 | GMO1: DY212 | GMP1: DY212 | GMQ1: DY212 | GMR1: DY212 | GMS1: DY212 | GMT1: DY212 | GMU1: DY212 | GMV1: DY212 | GMW1: DY212 | GMX1: DY212 | GMY1: DY212 | GMZ1: DY213 | GNA1: DY213 | GNB1: DY213 | GNC1: DY213 | GND1: DY213 | GNE1: DY213 | GNF1: DY213 | GNG1: DY213 | GNH1: DY213 | GNI1: DY213 | GNJ1: DY213 | GNK1: DY213 | GNL1: DY213 | GNM1: DY213 | GNN1: DY213 | GNO1: DY213 | GNP1: DY213 | GNQ1: DY213 | GNR1: DY213 | GNS1: DY213 | GNT1: DY213 | GNU1: DY213 | GNV1: DY213 | GNW1: DY213 | GNX1: DY214 | GNY1: DY214 | GNZ1: DY214 | GOA1: DY214 | GOB1: DY214 | GOC1: DY214 | GOD1: DY214 | GOE1: DY214 | GOF1: DY214 | GOG1: DY214 | GOH1: DY214 | GOI1: DY214 | GOJ1: DY214 | GOK1: DY214 | GOL1: DY214 | GOM1: DY214 | GON1: DY214 | GOO1: DY214 | GOP1: DY214 | GOQ1: DY214 | GOR1: DY214 | GOS1: DY214 | GOT1: DY214 | GOU1: DY214 | GOV1: DY215 | GOW1: DY215 | GOX1: DY215 | GOY1: DY215 | GOZ1: DY215 | GPA1: DY215 | GPB1: DY215 | GPC1: DY215 | GPD1: DY215 | GPE1: DY215 | GPF1: DY215 | GPG1: DY215 | GPH1: DY215 | GPI1: DY215 | GPJ1: DY215 | GPK1: DY215 | GPL1: DY215 | GPM1: DY215 | GPN1: DY215 | GPO1: DY215 | GPP1: DY215 | GPQ1: DY215 | GPR1: DY215 | GPS1: DY215 | GPT1: DY216 | GPU1: DY216 | GPV1: DY216 | GPW1: DY216 | GPX1: DY216 | GPY1: DY216 | GPZ1: DY216 | GQA1: DY216 | GQB1: DY216 | GQC1: DY216 | GQD1: DY216 | GQE1: DY216 | GQF1: DY216 | GQG1: DY216 | GQH1: DY216 | GQI1: DY216 | GQJ1: DY216 | GQK1: DY216 | GQL1: DY216 | GQM1: DY216 | GQN1: DY216 | GQO1: DY216 | GQP1: DY216 | GQQ1: DY216 | GQR1: DY217 | GQS1: DY217 | GQT1: DY217 | GQU1: DY217 | GQV1: DY217 | GQW1: DY217 | GQX1: DY217 | GQY1: DY217 | GQZ1: DY217 | GRA1: DY217 | GRB1: DY217 | GRC1: DY217 | GRD1: DY217 | GRE1: DY217 | GRF1: DY217 | GRG1: DY217 | GRH1: DY217 | GRI1: DY217 | GRJ1: DY217 | GRK1: DY217 | GRL1: DY217 | GRM1: DY217 | GRN1: DY217 | GRO1: DY217 | GRP1: DY218 | GRQ1: DY218 | GRR1: DY218 | GRS1: DY218 | GRT1: DY218 | GRU1: DY218 | GRV1: DY218 | GRW1: DY218 | GRX1: DY218 | GRY1: DY218 | GRZ1: DY218 | GSA1: DY218 | GSB1: DY218 | GSC1: DY218 | GSD1: DY218 | GSE1: DY218 | GSF1: DY218 | GSG1: DY218 | GSH1: DY218 | GSI1: DY218 | GSJ1: DY218 | GSK1: DY218 | GSL1: DY218 | GSM1: DY218 | GSN1: DY219 | GSO1: DY219 | GSP1: DY219 | GSQ1: DY219 | GSR1: DY219 | GSS1: DY219 | GST1: DY219 | GSU1: DY219 | GSV1: DY219 | GSW1: DY219 | GSX1: DY219 | GSY1: DY219 | GSZ1: DY219 | GTA1: DY219 | GTB1: DY219 | GTC1: DY219 | GTD1: DY219 | GTE1: DY219 | GTF1: DY219 | GTG1: DY219 | GTH1: DY219 | GTI1: DY219 | GTJ1: DY219 | GTK1: DY219 | GTL1: DY220 | GTM1: DY220 | GTN1: DY220 | GTO1: DY220 | GTP1: DY220 | GTQ1: DY220 | GTR1: DY220 | GTS1: DY220 | GTT1: DY220 | GTU1: DY220 | GTV1: DY220 | GTW1: DY220 | GTX1: DY220 | GTY1: DY220 | GTZ1: DY220 | GUA1: DY220 | GUB1: DY220 | GUC1: DY220 | GUD1: DY220 | GUE1: DY220 | GUF1: DY220 | GUG1: DY220 | GUH1: DY220 | GUI1: DY220 | GUJ1: DY221 | GUK1: DY221 | GUL1: DY221 | GUM1: DY221 | GUN1: DY221 | GUO1: DY221 | GUP1: DY221 | GUQ1: DY221 | GUR1: DY221 | GUS1: DY221 | GUT1: DY221 | GUU1: DY221 | GUV1: DY221 | GUW1: DY221 | GUX1: DY221 | GUY1: DY221 | GUZ1: DY221 | GVA1: DY221 | GVB1: DY221 | GVC1: DY221 | GVD1: DY221 | GVE1: DY221 | GVF1: DY221 | GVG1: DY221 | GVH1: DY222 | GVI1: DY222 | GVJ1: DY222 | GVK1: DY222 | GVL1: DY222 | GVM1: DY222 | GVN1: DY222 | GVO1: DY222 | GVP1: DY222 | GVQ1: DY222 | GVR1: DY222 | GVS1: DY222 | GVT1: DY222 | GVU1: DY222 | GVV1: DY222 | GVW1: DY222 | GVX1: DY222 | GVY1: DY222 | GVZ1: DY222 | GWA1: DY222 | GWB1: DY222 | GWC1: DY222 | GWD1: DY222 | GWE1: DY222 | GWF1: DY223 | GWG1: DY223 | GWH1: DY223 | GWI1: DY223 | GWJ1: DY223 | GWK1: DY223 | GWL1: DY223 | GWM1: DY223 | GWN1: DY223 | GWO1: DY223 | GWP1: DY223 | GWQ1: DY223 | GWR1: DY223 | GWS1: DY223 | GWT1: DY223 | GWU1: DY223 | GWV1: DY223 | GWW1: DY223 | GWX1: DY223 | GWY1: DY223 | GWZ1: DY223 | GXA1: DY223 | GXB1: DY223 | GXC1: DY223 | GXD1: DY224 | GXE1: DY224 | GXF1: DY224 | GXG1: DY224 | GXH1: DY224 | GXI1: DY224 | GXJ1: DY224 | GXK1: DY224 | GXL1: DY224 | GXM1: DY224 | GXN1: DY224 | GXO1: DY224 | GXP1: DY224 | GXQ1: DY224 | GXR1: DY224 | GXS1: DY224 | GXT1: DY224 | GXU1: DY224 | GXV1: DY224 | GXW1: DY224 | GXX1: DY224 | GXY1: DY224 | GXZ1: DY224 | GYA1: DY224 | GYB1: DY225 | GYC1: DY225 | GYD1: DY225 | GYE1: DY225 | GYF1: DY225 | GYG1: DY225 | GYH1: DY225 | GYI1: DY225 | GYJ1: DY225 | GYK1: DY225 | GYL1: DY225 | GYM1: DY225 | GYN1: DY225 | GYO1: DY225 | GYP1: DY225 | GYQ1: DY225 | GYR1: DY225 | GYS1: DY225 | GYT1: DY225 | GYU1: DY225 | GYV1: DY225 | GYW1: DY225 | GYX1: DY225 | GYY1: DY225 | GYZ1: DY226 | GZA1: DY226 | GZB1: DY226 | GZC1: DY226 | GZD1: DY226 | GZE1: DY226 | GZF1: DY226 | GZG1: DY226 | GZH1: DY226 | GZI1: DY226 | GZJ1: DY226 | GZK1: DY226 | GZL1: DY226 | GZM1: DY226 | GZN1: DY226 | GZO1: DY226 | GZP1: DY226 | GZQ1: DY226 | GZR1: DY226 | GZS1: DY226 | GZT1: DY226 | GZU1: DY226 | GZV1: DY226 | GZW1: DY226 | GZX1: DY227 | GZY1: DY227 | GZZ1: DY227 | HAA1: DY227 | HAB1: DY227 | HAC1: DY227 | HAD1: DY227 | HAE1: DY227 | HAF1: DY227 | HAG1: DY227 | HAH1: DY227 | HAI1: DY227 | HAJ1: DY227 | HAK1: DY227 | HAL1: DY227 | HAM1: DY227 | HAN1: DY227 | HAO1: DY227 | HAP1: DY227 | HAQ1: DY227 | HAR1: DY227 | HAS1: DY227 | HAT1: DY227 | HAU1: DY227 | HAV1: DY228 | HAW1: DY228 | HAX1: DY228 | HAY1: DY228 | HAZ1: DY228 | HBA1: DY228 | HBB1: DY228 | HBC1: DY228 | HBD1: DY228 | HBE1: DY228 | HBF1: DY228 | HBG1: DY228 | HBH1: DY228 | HBI1: DY228 | HBJ1: DY228 | HBK1: DY228 | HBL1: DY228 | HBM1: DY228 | HBN1: DY228 | HBO1: DY228 | HBP1: DY228 | HBQ1: DY228 | HBR1: DY228 | HBS1: DY228 | HBT1: DY229 | HBU1: DY229 | HBV1: DY229 | HBW1: DY229 | HBX1: DY229 | HBY1: DY229 | HBZ1: DY229 | HCA1: DY229 | HCB1: DY229 | HCC1: DY229 | HCD1: DY229 | HCE1: DY229 | HCF1: DY229 | HCG1: DY229 | HCH1: DY229 | HCI1: DY229 | HCJ1: DY229 | HCK1: DY229 | HCL1: DY229 | HCM1: DY229 | HCN1: DY229 | HCO1: DY229 | HCP1: DY229 | HCQ1: DY229 | HCR1: DY230 | HCS1: DY230 | HCT1: DY230 | HCU1: DY230 | HCV1: DY230 | HCW1: DY230 | HCX1: DY230 | HCY1: DY230 | HCZ1: DY230 | HDA1: DY230 | HDB1: DY230 | HDC1: DY230 | HDD1: DY230 | HDE1: DY230 | HDF1: DY230 | HDG1: DY230 | HDH1: DY230 | HDI1: DY230 | HDJ1: DY230 | HDK1: DY230 | HDL1: DY230 | HDM1: DY230 | HDN1: DY230 | HDO1: DY230 | HDP1: DY231 | HDQ1: DY231 | HDR1: DY231 | HDS1: DY231 | HDT1: DY231 | HDU1: DY231 | HDV1: DY231 | HDW1: DY231 | HDX1: DY231 | HDY1: DY231 | HDZ1: DY231 | HEA1: DY231 | HEB1: DY231 | HEC1: DY231 | HED1: DY231 | HEE1: DY231 | HEF1: DY231 | HEG1: DY231 | HEH1: DY231 | HEI1: DY231 | HEJ1: DY231 | HEK1: DY231 | HEL1: DY231 | HEM1: DY231 | HEN1: DY232 | HEO1: DY232 | HEP1: DY232 | HEQ1: DY232 | HER1: DY232 | HES1: DY232 | HET1: DY232 | HEU1: DY232 | HEV1: DY232 | HEW1: DY232 | HEX1: DY232 | HEY1: DY232 | HEZ1: DY232 | HFA1: DY232 | HFB1: DY232 | HFC1: DY232 | HFD1: DY232 | HFE1: DY232 | HFF1: DY232 | HFG1: DY232 | HFH1: DY232 | HFI1: DY232 | HFJ1: DY232 | HFK1: DY232 | HFL1: DY233 | HFM1: DY233 | HFN1: DY233 | HFO1: DY233 | HFP1: DY233 | HFQ1: DY233 | HFR1: DY233 | HFS1: DY233 | HFT1: DY233 | HFU1: DY233 | HFV1: DY233 | HFW1: DY233 | HFX1: DY233 | HFY1: DY233 | HFZ1: DY233 | HGA1: DY233 | HGB1: DY233 | HGC1: DY233 | HGD1: DY233 | HGE1: DY233 | HGF1: DY233 | HGG1: DY233 | HGH1: DY233 | HGI1: DY233 | HGJ1: DY234 | HGK1: DY234 | HGL1: DY234 | HGM1: DY234 | HGN1: DY234 | HGO1: DY234 | HGP1: DY234 | HGQ1: DY234 | HGR1: DY234 | HGS1: DY234 | HGT1: DY234 | HGU1: DY234 | HGV1: DY234 | HGW1: DY234 | HGX1: DY234 | HGY1: DY234 | HGZ1: DY234 | HHA1: DY234 | HHB1: DY234 | HHC1: DY234 | HHD1: DY234 | HHE1: DY234 | HHF1: DY234 | HHG1: DY234 | HHH1: DY235 | HHI1: DY235 | HHJ1: DY235 | HHK1: DY235 | HHL1: DY235 | HHM1: DY235 | HHN1: DY235 | HHO1: DY235 | HHP1: DY235 | HHQ1: DY235 | HHR1: DY235 | HHS1: DY235 | HHT1: DY235 | HHU1: DY235 | HHV1: DY235 | HHW1: DY235 | HHX1: DY235 | HHY1: DY235 | HHZ1: DY235 | HIA1: DY235 | HIB1: DY235 | HIC1: DY235 | HID1: DY235 | HIE1: DY235 | HIF1: DY236 | HIG1: DY236 | HIH1: DY236 | HII1: DY236 | HIJ1: DY236 | HIK1: DY236 | HIL1: DY236 | HIM1: DY236 | HIN1: DY236 | HIO1: DY236 | HIP1: DY236 | HIQ1: DY236 | HIR1: DY236 | HIS1: DY236 | HIT1: DY236 | HIU1: DY236 | HIV1: DY236 | HIW1: DY236 | HIX1: DY236 | HIY1: DY236 | HIZ1: DY236 | HJA1: DY236 | HJB1: DY236 | HJC1: DY236 | HJD1: DY237 | HJE1: DY237 | HJF1: DY237 | HJG1: DY237 | HJH1: DY237 | HJI1: DY237 | HJJ1: DY237 | HJK1: DY237 | HJL1: DY237 | HJM1: DY237 | HJN1: DY237 | HJO1: DY237 | HJP1: DY237 | HJQ1: DY237 | HJR1: DY237 | HJS1: DY237 | HJT1: DY237 | HJU1: DY237 | HJV1: DY237 | HJW1: DY237 | HJX1: DY237 | HJY1: DY237 | HJZ1: DY237 | HKA1: DY237 | HKB1: DY238 | HKC1: DY238 | HKD1: DY238 | HKE1: DY238 | HKF1: DY238 | HKG1: DY238 | HKH1: DY238 | HKI1: DY238 | HKJ1: DY238 | HKK1: DY238 | HKL1: DY238 | HKM1: DY238 | HKN1: DY238 | HKO1: DY238 | HKP1: DY238 | HKQ1: DY238 | HKR1: DY238 | HKS1: DY238 | HKT1: DY238 | HKU1: DY238 | HKV1: DY238 | HKW1: DY238 | HKX1: DY238 | HKY1: DY238 | HKZ1: DY239 | HLA1: DY239 | HLB1: DY239 | HLC1: DY239 | HLD1: DY239 | HLE1: DY239 | HLF1: DY239 | HLG1: DY239 | HLH1: DY239 | HLI1: DY239 | HLJ1: DY239 | HLK1: DY239 | HLL1: DY239 | HLM1: DY239 | HLN1: DY239 | HLO1: DY239 | HLP1: DY239 | HLQ1: DY239 | HLR1: DY239 | HLS1: DY239 | HLT1: DY239 | HLU1: DY239 | HLV1: DY239 | HLW1: DY239 | HLX1: DY240 | HLY1: DY240 | HLZ1: DY240 | HMA1: DY240 | HMB1: DY240 | HMC1: DY240 | HMD1: DY240 | HME1: DY240 | HMF1: DY240 | HMG1: DY240 | HMH1: DY240 | HMI1: DY240 | HMJ1: DY240 | HMK1: DY240 | HML1: DY240 | HMM1: DY240 | HMN1: DY240 | HMO1: DY240 | HMP1: DY240 | HMQ1: DY240 | HMR1: DY240 | HMS1: DY240 | HMT1: DY240 | HMU1: DY240 | HMV1: DY241 | HMW1: DY241 | HMX1: DY241 | HMY1: DY241 | HMZ1: DY241 | HNA1: DY241 | HNB1: DY241 | HNC1: DY241 | HND1: DY241 | HNE1: DY241 | HNF1: DY241 | HNG1: DY241 | HNH1: DY241 | HNI1: DY241 | HNJ1: DY241 | HNK1: DY241 | HNL1: DY241 | HNM1: DY241 | HNN1: DY241 | HNO1: DY241 | HNP1: DY241 | HNQ1: DY241 | HNR1: DY241 | HNS1: DY241 | HNT1: DY242 | HNU1: DY242 | HNV1: DY242 | HNW1: DY242 | HNX1: DY242 | HNY1: DY242 | HNZ1: DY242 | HOA1: DY242 | HOB1: DY242 | HOC1: DY242 | HOD1: DY242 | HOE1: DY242 | HOF1: DY242 | HOG1: DY242 | HOH1: DY242 | HOI1: DY242 | HOJ1: DY242 | HOK1: DY242 | HOL1: DY242 | HOM1: DY242 | HON1: DY242 | HOO1: DY242 | HOP1: DY242 | HOQ1: DY242 | HOR1: DY243 | HOS1: DY243 | HOT1: DY243 | HOU1: DY243 | HOV1: DY243 | HOW1: DY243 | HOX1: DY243 | HOY1: DY243 | HOZ1: DY243 | HPA1: DY243 | HPB1: DY243 | HPC1: DY243 | HPD1: DY243 | HPE1: DY243 | HPF1: DY243 | HPG1: DY243 | HPH1: DY243 | HPI1: DY243 | HPJ1: DY243 | HPK1: DY243 | HPL1: DY243 | HPM1: DY243 | HPN1: DY243 | HPO1: DY243 | HPP1: DY244 | HPQ1: DY244 | HPR1: DY244 | HPS1: DY244 | HPT1: DY244 | HPU1: DY244 | HPV1: DY244 | HPW1: DY244 | HPX1: DY244 | HPY1: DY244 | HPZ1: DY244 | HQA1: DY244 | HQB1: DY244 | HQC1: DY244 | HQD1: DY244 | HQE1: DY244 | HQF1: DY244 | HQG1: DY244 | HQH1: DY244 | HQI1: DY244 | HQJ1: DY244 | HQK1: DY244 | HQL1: DY244 | HQM1: DY244 | HQN1: DY245 | HQO1: DY245 | HQP1: DY245 | HQQ1: DY245 | HQR1: DY245 | HQS1: DY245 | HQT1: DY245 | HQU1: DY245 | HQV1: DY245 | HQW1: DY245 | HQX1: DY245 | HQY1: DY245 | HQZ1: DY245 | HRA1: DY245 | HRB1: DY245 | HRC1: DY245 | HRD1: DY245 | HRE1: DY245 | HRF1: DY245 | HRG1: DY245 | HRH1: DY245 | HRI1: DY245 | HRJ1: DY245 | HRK1: DY245 | HRL1: DY246 | HRM1: DY246 | HRN1: DY246 | HRO1: DY246 | HRP1: DY246 | HRQ1: DY246 | HRR1: DY246 | HRS1: DY246 | HRT1: DY246 | HRU1: DY246 | HRV1: DY246 | HRW1: DY246 | HRX1: DY246 | HRY1: DY246 | HRZ1: DY246 | HSA1: DY246 | HSB1: DY246 | HSC1: DY246 | HSD1: DY246 | HSE1: DY246 | HSF1: DY246 | HSG1: DY246 | HSH1: DY246 | HSI1: DY246 | HSJ1: DY247 | HSK1: DY247 | HSL1: DY247 | HSM1: DY247 | HSN1: DY247 | HSO1: DY247 | HSP1: DY247 | HSQ1: DY247 | HSR1: DY247 | HSS1: DY247 | HST1: DY247 | HSU1: DY247 | HSV1: DY247 | HSW1: DY247 | HSX1: DY247 | HSY1: DY247 | HSZ1: DY247 | HTA1: DY247 | HTB1: DY247 | HTC1: DY247 | HTD1: DY247 | HTE1: DY247 | HTF1: DY247 | HTG1: DY247 | HTH1: DY248 | HTI1: DY248 | HTJ1: DY248 | HTK1: DY248 | HTL1: DY248 | HTM1: DY248 | HTN1: DY248 | HTO1: DY248 | HTP1: DY248 | HTQ1: DY248 | HTR1: DY248 | HTS1: DY248 | HTT1: DY248 | HTU1: DY248 | HTV1: DY248 | HTW1: DY248 | HTX1: DY248 | HTY1: DY248 | HTZ1: DY248 | HUA1: DY248 | HUB1: DY248 | HUC1: DY248 | HUD1: DY248 | HUE1: DY248 | HUF1: DY249 | HUG1: DY249 | HUH1: DY249 | HUI1: DY249 | HUJ1: DY249 | HUK1: DY249 | HUL1: DY249 | HUM1: DY249 | HUN1: DY249 | HUO1: DY249 | HUP1: DY249 | HUQ1: DY249 | HUR1: DY249 | HUS1: DY249 | HUT1: DY249 | HUU1: DY249 | HUV1: DY249 | HUW1: DY249 | HUX1: DY249 | HUY1: DY249 | HUZ1: DY249 | HVA1: DY249 | HVB1: DY249 | HVC1: DY249 | HVD1: DY250 | HVE1: DY250 | HVF1: DY250 | HVG1: DY250 | HVH1: DY250 | HVI1: DY250 | HVJ1: DY250 | HVK1: DY250 | HVL1: DY250 | HVM1: DY250 | HVN1: DY250 | HVO1: DY250 | HVP1: DY250 | HVQ1: DY250 | HVR1: DY250 | HVS1: DY250 | HVT1: DY250 | HVU1: DY250 | HVV1: DY250 | HVW1: DY250 | HVX1: DY250 | HVY1: DY250 | HVZ1: DY250 | HWA1: DY250 | HWB1: DY251 | HWC1: DY251 | HWD1: DY251 | HWE1: DY251 | HWF1: DY251 | HWG1: DY251 | HWH1: DY251 | HWI1: DY251 | HWJ1: DY251 | HWK1: DY251 | HWL1: DY251 | HWM1: DY251 | HWN1: DY251 | HWO1: DY251 | HWP1: DY251 | HWQ1: DY251 | HWR1: DY251 | HWS1: DY251 | HWT1: DY251 | HWU1: DY251 | HWV1: DY251 | HWW1: DY251 | HWX1: DY251 | HWY1: DY251 | HWZ1: DY252 | HXA1: DY252 | HXB1: DY252 | HXC1: DY252 | HXD1: DY252 | HXE1: DY252 | HXF1: DY252 | HXG1: DY252 | HXH1: DY252 | HXI1: DY252 | HXJ1: DY252 | HXK1: DY252 | HXL1: DY252 | HXM1: DY252 | HXN1: DY252 | HXO1: DY252 | HXP1: DY252 | HXQ1: DY252 | HXR1: DY252 | HXS1: DY252 | HXT1: DY252 | HXU1: DY252 | HXV1: DY252 | HXW1: DY252 | HXX1: DY253 | HXY1: DY253 | HXZ1: DY253 | HYA1: DY253 | HYB1: DY253 | HYC1: DY253 | HYD1: DY253 | HYE1: DY253 | HYF1: DY253 | HYG1: DY253 | HYH1: DY253 | HYI1: DY253 | HYJ1: DY253 | HYK1: DY253 | HYL1: DY253 | HYM1: DY253 | HYN1: DY253 | HYO1: DY253 | HYP1: DY253 | HYQ1: DY253 | HYR1: DY253 | HYS1: DY253 | HYT1: DY253 | HYU1: DY253 | HYV1: DY254 | HYW1: DY254 | HYX1: DY254 | HYY1: DY254 | HYZ1: DY254 | HZA1: DY254 | HZB1: DY254 | HZC1: DY254 | HZD1: DY254 | HZE1: DY254 | HZF1: DY254 | HZG1: DY254 | HZH1: DY254 | HZI1: DY254 | HZJ1: DY254 | HZK1: DY254 | HZL1: DY254 | HZM1: DY254 | HZN1: DY254 | HZO1: DY254 | HZP1: DY254 | HZQ1: DY254 | HZR1: DY254 | HZS1: DY254 | HZT1: DY255 | HZU1: DY255 | HZV1: DY255 | HZW1: DY255 | HZX1: DY255 | HZY1: DY255 | HZZ1: DY255 | IAA1: DY255 | IAB1: DY255 | IAC1: DY255 | IAD1: DY255 | IAE1: DY255 | IAF1: DY255 | IAG1: DY255 | IAH1: DY255 | IAI1: DY255 | IAJ1: DY255 | IAK1: DY255 | IAL1: DY255 | IAM1: DY255 | IAN1: DY255 | IAO1: DY255 | IAP1: DY255 | IAQ1: DY255 | IAR1: DY256 | IAS1: DY256 | IAT1: DY256 | IAU1: DY256 | IAV1: DY256 | IAW1: DY256 | IAX1: DY256 | IAY1: DY256 | IAZ1: DY256 | IBA1: DY256 | IBB1: DY256 | IBC1: DY256 | IBD1: DY256 | IBE1: DY256 | IBF1: DY256 | IBG1: DY256 | IBH1: DY256 | IBI1: DY256 | IBJ1: DY256 | IBK1: DY256 | IBL1: DY256 | IBM1: DY256 | IBN1: DY256 | IBO1: DY256 | IBP1: DY257 | IBQ1: DY257 | IBR1: DY257 | IBS1: DY257 | IBT1: DY257 | IBU1: DY257 | IBV1: DY257 | IBW1: DY257 | IBX1: DY257 | IBY1: DY257 | IBZ1: DY257 | ICA1: DY257 | ICB1: DY257 | ICC1: DY257 | ICD1: DY257 | ICE1: DY257 | ICF1: DY257 | ICG1: DY257 | ICH1: DY257 | ICI1: DY257 | ICJ1: DY257 | ICK1: DY257 | ICL1: DY257 | ICM1: DY257 | ICN1: DY258 | ICO1: DY258 | ICP1: DY258 | ICQ1: DY258 | ICR1: DY258 | ICS1: DY258 | ICT1: DY258 | ICU1: DY258 | ICV1: DY258 | ICW1: DY258 | ICX1: DY258 | ICY1: DY258 | ICZ1: DY258 | IDA1: DY258 | IDB1: DY258 | IDC1: DY258 | IDD1: DY258 | IDE1: DY258 | IDF1: DY258 | IDG1: DY258 | IDH1: DY258 | IDI1: DY258 | IDJ1: DY258 | IDK1: DY258 | IDL1: DY259 | IDM1: DY259 | IDN1: DY259 | IDO1: DY259 | IDP1: DY259 | IDQ1: DY259 | IDR1: DY259 | IDS1: DY259 | IDT1: DY259 | IDU1: DY259 | IDV1: DY259 | IDW1: DY259 | IDX1: DY259 | IDY1: DY259 | IDZ1: DY259 | IEA1: DY259 | IEB1: DY259 | IEC1: DY259 | IED1: DY259 | IEE1: DY259 | IEF1: DY259 | IEG1: DY259 | IEH1: DY259 | IEI1: DY259 | IEJ1: DY260 | IEK1: DY260 | IEL1: DY260 | IEM1: DY260 | IEN1: DY260 | IEO1: DY260 | IEP1: DY260 | IEQ1: DY260 | IER1: DY260 | IES1: DY260 | IET1: DY260 | IEU1: DY260 | IEV1: DY260 | IEW1: DY260 | IEX1: DY260 | IEY1: DY260 | IEZ1: DY260 | IFA1: DY260 | IFB1: DY260 | IFC1: DY260 | IFD1: DY260 | IFE1: DY260 | IFF1: DY260 | IFG1: DY260 | IFH1: DY261 | IFI1: DY261 | IFJ1: DY261 | IFK1: DY261 | IFL1: DY261 | IFM1: DY261 | IFN1: DY261 | IFO1: DY261 | IFP1: DY261 | IFQ1: DY261 | IFR1: DY261 | IFS1: DY261 | IFT1: DY261 | IFU1: DY261 | IFV1: DY261 | IFW1: DY261 | IFX1: DY261 | IFY1: DY261 | IFZ1: DY261 | IGA1: DY261 | IGB1: DY261 | IGC1: DY261 | IGD1: DY261 | IGE1: DY261 | IGF1: DY262 | IGG1: DY262 | IGH1: DY262 | IGI1: DY262 | IGJ1: DY262 | IGK1: DY262 | IGL1: DY262 | IGM1: DY262 | IGN1: DY262 | IGO1: DY262 | IGP1: DY262 | IGQ1: DY262 | IGR1: DY262 | IGS1: DY262 | IGT1: DY262 | IGU1: DY262 | IGV1: DY262 | IGW1: DY262 | IGX1: DY262 | IGY1: DY262 | IGZ1: DY262 | IHA1: DY262 | IHB1: DY262 | IHC1: DY262 | IHD1: DY263 | IHE1: DY263 | IHF1: DY263 | IHG1: DY263 | IHH1: DY263 | IHI1: DY263 | IHJ1: DY263 | IHK1: DY263 | IHL1: DY263 | IHM1: DY263 | IHN1: DY263 | IHO1: DY263 | IHP1: DY263 | IHQ1: DY263 | IHR1: DY263 | IHS1: DY263 | IHT1: DY263 | IHU1: DY263 | IHV1: DY263 | IHW1: DY263 | IHX1: DY263 | IHY1: DY263 | IHZ1: DY263 | IIA1: DY263 | IIB1: DY264 | IIC1: DY264 | IID1: DY264 | IIE1: DY264 | IIF1: DY264 | IIG1: DY264 | IIH1: DY264 | III1: DY264 | IIJ1: DY264 | IIK1: DY264 | IIL1: DY264 | IIM1: DY264 | IIN1: DY264 | IIO1: DY264 | IIP1: DY264 | IIQ1: DY264 | IIR1: DY264 | IIS1: DY264 | IIT1: DY264 | IIU1: DY264 | IIV1: DY264 | IIW1: DY264 | IIX1: DY264 | IIY1: DY264 | IIZ1: DY265 | IJA1: DY265 | IJB1: DY265 | IJC1: DY265 | IJD1: DY265 | IJE1: DY265 | IJF1: DY265 | IJG1: DY265 | IJH1: DY265 | IJI1: DY265 | IJJ1: DY265 | IJK1: DY265 | IJL1: DY265 | IJM1: DY265 | IJN1: DY265 | IJO1: DY265 | IJP1: DY265 | IJQ1: DY265 | IJR1: DY265 | IJS1: DY265 | IJT1: DY265 | IJU1: DY265 | IJV1: DY265 | IJW1: DY265 | IJX1: DY266 | IJY1: DY266 | IJZ1: DY266 | IKA1: DY266 | IKB1: DY266 | IKC1: DY266 | IKD1: DY266 | IKE1: DY266 | IKF1: DY266 | IKG1: DY266 | IKH1: DY266 | IKI1: DY266 | IKJ1: DY266 | IKK1: DY266 | IKL1: DY266 | IKM1: DY266 | IKN1: DY266 | IKO1: DY266 | IKP1: DY266 | IKQ1: DY266 | IKR1: DY266 | IKS1: DY266 | IKT1: DY266 | IKU1: DY266 | IKV1: DY267 | IKW1: DY267 | IKX1: DY267 | IKY1: DY267 | IKZ1: DY267 | ILA1: DY267 | ILB1: DY267 | ILC1: DY267 | ILD1: DY267 | ILE1: DY267 | ILF1: DY267 | ILG1: DY267 | ILH1: DY267 | ILI1: DY267 | ILJ1: DY267 | ILK1: DY267 | ILL1: DY267 | ILM1: DY267 | ILN1: DY267 | ILO1: DY267 | ILP1: DY267 | ILQ1: DY267 | ILR1: DY267 | ILS1: DY267 | ILT1: DY268 | ILU1: DY268 | ILV1: DY268 | ILW1: DY268 | ILX1: DY268 | ILY1: DY268 | ILZ1: DY268 | IMA1: DY268 | IMB1: DY268 | IMC1: DY268 | IMD1: DY268 | IME1: DY268 | IMF1: DY268 | IMG1: DY268 | IMH1: DY268 | IMI1: DY268 | IMJ1: DY268 | IMK1: DY268 | IML1: DY268 | IMM1: DY268 | IMN1: DY268 | IMO1: DY268 | IMP1: DY268 | IMQ1: DY268 | IMR1: DY269 | IMS1: DY269 | IMT1: DY269 | IMU1: DY269 | IMV1: DY269 | IMW1: DY269 | IMX1: DY269 | IMY1: DY269 | IMZ1: DY269 | INA1: DY269 | INB1: DY269 | INC1: DY269 | IND1: DY269 | INE1: DY269 | INF1: DY269 | ING1: DY269 | INH1: DY269 | INI1: DY269 | INJ1: DY269 | INK1: DY269 | INL1: DY269 | INM1: DY269 | INN1: DY269 | INO1: DY269 | INP1: DY270 | INQ1: DY270 | INR1: DY270 | INS1: DY270 | INT1: DY270 | INU1: DY270 | INV1: DY270 | INW1: DY270 | INX1: DY270 | INY1: DY270 | INZ1: DY270 | IOA1: DY270 | IOB1: DY270 | IOC1: DY270 | IOD1: DY270 | IOE1: DY270 | IOF1: DY270 | IOG1: DY270 | IOH1: DY270 | IOI1: DY270 | IOJ1: DY270 | IOK1: DY270 | IOL1: DY270 | IOM1: DY270 | ION1: DY271 | IOO1: DY271 | IOP1: DY271 | IOQ1: DY271 | IOR1: DY271 | IOS1: DY271 | IOT1: DY271 | IOU1: DY271 | IOV1: DY271 | IOW1: DY271 | IOX1: DY271 | IOY1: DY271 | IOZ1: DY271 | IPA1: DY271 | IPB1: DY271 | IPC1: DY271 | IPD1: DY271 | IPE1: DY271 | IPF1: DY271 | IPG1: DY271 | IPH1: DY271 | IPI1: DY271 | IPJ1: DY271 | IPK1: DY271 | IPL1: DY272 | IPM1: DY272 | IPN1: DY272 | IPO1: DY272 | IPP1: DY272 | IPQ1: DY272 | IPR1: DY272 | IPS1: DY272 | IPT1: DY272 | IPU1: DY272 | IPV1: DY272 | IPW1: DY272 | IPX1: DY272 | IPY1: DY272 | IPZ1: DY272 | IQA1: DY272 | IQB1: DY272 | IQC1: DY272 | IQD1: DY272 | IQE1: DY272 | IQF1: DY272 | IQG1: DY272 | IQH1: DY272 | IQI1: DY272 | IQJ1: DY273 | IQK1: DY273 | IQL1: DY273 | IQM1: DY273 | IQN1: DY273 | IQO1: DY273 | IQP1: DY273 | IQQ1: DY273 | IQR1: DY273 | IQS1: DY273 | IQT1: DY273 | IQU1: DY273 | IQV1: DY273 | IQW1: DY273 | IQX1: DY273 | IQY1: DY273 | IQZ1: DY273 | IRA1: DY273 | IRB1: DY273 | IRC1: DY273 | IRD1: DY273 | IRE1: DY273 | IRF1: DY273 | IRG1: DY273 | IRH1: DY274 | IRI1: DY274 | IRJ1: DY274 | IRK1: DY274 | IRL1: DY274 | IRM1: DY274 | IRN1: DY274 | IRO1: DY274 | IRP1: DY274 | IRQ1: DY274 | IRR1: DY274 | IRS1: DY274 | IRT1: DY274 | IRU1: DY274 | IRV1: DY274 | IRW1: DY274 | IRX1: DY274 | IRY1: DY274 | IRZ1: DY274 | ISA1: DY274 | ISB1: DY274 | ISC1: DY274 | ISD1: DY274 | ISE1: DY274 | ISF1: DY275 | ISG1: DY275 | ISH1: DY275 | ISI1: DY275 | ISJ1: DY275 | ISK1: DY275 | ISL1: DY275 | ISM1: DY275 | ISN1: DY275 | ISO1: DY275 | ISP1: DY275 | ISQ1: DY275 | ISR1: DY275 | ISS1: DY275 | IST1: DY275 | ISU1: DY275 | ISV1: DY275 | ISW1: DY275 | ISX1: DY275 | ISY1: DY275 | ISZ1: DY275 | ITA1: DY275 | ITB1: DY275 | ITC1: DY275 | ITD1: DY276 | ITE1: DY276 | ITF1: DY276 | ITG1: DY276 | ITH1: DY276 | ITI1: DY276 | ITJ1: DY276 | ITK1: DY276 | ITL1: DY276 | ITM1: DY276 | ITN1: DY276 | ITO1: DY276 | ITP1: DY276 | ITQ1: DY276 | ITR1: DY276 | ITS1: DY276 | ITT1: DY276 | ITU1: DY276 | ITV1: DY276 | ITW1: DY276 | ITX1: DY276 | ITY1: DY276 | ITZ1: DY276 | IUA1: DY276 | IUB1: DY277 | IUC1: DY277 | IUD1: DY277 | IUE1: DY277 | IUF1: DY277 | IUG1: DY277 | IUH1: DY277 | IUI1: DY277 | IUJ1: DY277 | IUK1: DY277 | IUL1: DY277 | IUM1: DY277 | IUN1: DY277 | IUO1: DY277 | IUP1: DY277 | IUQ1: DY277 | IUR1: DY277 | IUS1: DY277 | IUT1: DY277 | IUU1: DY277 | IUV1: DY277 | IUW1: DY277 | IUX1: DY277 | IUY1: DY277 | IUZ1: DY278 | IVA1: DY278 | IVB1: DY278 | IVC1: DY278 | IVD1: DY278 | IVE1: DY278 | IVF1: DY278 | IVG1: DY278 | IVH1: DY278 | IVI1: DY278 | IVJ1: DY278 | IVK1: DY278 | IVL1: DY278 | IVM1: DY278 | IVN1: DY278 | IVO1: DY278 | IVP1: DY278 | IVQ1: DY278 | IVR1: DY278 | IVS1: DY278 | IVT1: DY278 | IVU1: DY278 | IVV1: DY278 | IVW1: DY278 | IVX1: DY279 | IVY1: DY279 | IVZ1: DY279 | IWA1: DY279 | IWB1: DY279 | IWC1: DY279 | IWD1: DY279 | IWE1: DY279 | IWF1: DY279 | IWG1: DY279 | IWH1: DY279 | IWI1: DY279 | IWJ1: DY279 | IWK1: DY279 | IWL1: DY279 | IWM1: DY279 | IWN1: DY279 | IWO1: DY279 | IWP1: DY279 | IWQ1: DY279 | IWR1: DY279 | IWS1: DY279 | IWT1: DY279 | IWU1: DY279 | IWV1: DY280 | IWW1: DY280 | IWX1: DY280 | IWY1: DY280 | IWZ1: DY280 | IXA1: DY280 | IXB1: DY280 | IXC1: DY280 | IXD1: DY280 | IXE1: DY280 | IXF1: DY280 | IXG1: DY280 | IXH1: DY280 | IXI1: DY280 | IXJ1: DY280 | IXK1: DY280 | IXL1: DY280 | IXM1: DY280 | IXN1: DY280 | IXO1: DY280 | IXP1: DY280 | IXQ1: DY280 | IXR1: DY280 | IXS1: DY280 | IXT1: DY281 | IXU1: DY281 | IXV1: DY281 | IXW1: DY281 | IXX1: DY281 | IXY1: DY281 | IXZ1: DY281 | IYA1: DY281 | IYB1: DY281 | IYC1: DY281 | IYD1: DY281 | IYE1: DY281 | IYF1: DY281 | IYG1: DY281 | IYH1: DY281 | IYI1: DY281 | IYJ1: DY281 | IYK1: DY281 | IYL1: DY281 | IYM1: DY281 | IYN1: DY281 | IYO1: DY281 | IYP1: DY281 | IYQ1: DY281 | IYR1: DY282 | IYS1: DY282 | IYT1: DY282 | IYU1: DY282 | IYV1: DY282 | IYW1: DY282 | IYX1: DY282 | IYY1: DY282 | IYZ1: DY282 | IZA1: DY282 | IZB1: DY282 | IZC1: DY282 | IZD1: DY282 | IZE1: DY282 | IZF1: DY282 | IZG1: DY282 | IZH1: DY282 | IZI1: DY282 | IZJ1: DY282 | IZK1: DY282 | IZL1: DY282 | IZM1: DY282 | IZN1: DY282 | IZO1: DY282 | IZP1: DY283 | IZQ1: DY283 | IZR1: DY283 | IZS1: DY283 | IZT1: DY283 | IZU1: DY283 | IZV1: DY283 | IZW1: DY283 | IZX1: DY283 | IZY1: DY283 | IZZ1: DY283 | JAA1: DY283 | JAB1: DY283 | JAC1: DY283 | JAD1: DY283 | JAE1: DY283 | JAF1: DY283 | JAG1: DY283 | JAH1: DY283 | JAI1: DY283 | JAJ1: DY283 | JAK1: DY283 | JAL1: DY283 | JAM1: DY283 | JAN1: DY284 | JAO1: DY284 | JAP1: DY284 | JAQ1: DY284 | JAR1: DY284 | JAS1: DY284 | JAT1: DY284 | JAU1: DY284 | JAV1: DY284 | JAW1: DY284 | JAX1: DY284 | JAY1: DY284 | JAZ1: DY284 | JBA1: DY284 | JBB1: DY284 | JBC1: DY284 | JBD1: DY284 | JBE1: DY284 | JBF1: DY284 | JBG1: DY284 | JBH1: DY284 | JBI1: DY284 | JBJ1: DY284 | JBK1: DY284 | JBL1: DY285 | JBM1: DY285 | JBN1: DY285 | JBO1: DY285 | JBP1: DY285 | JBQ1: DY285 | JBR1: DY285 | JBS1: DY285 | JBT1: DY285 | JBU1: DY285 | JBV1: DY285 | JBW1: DY285 | JBX1: DY285 | JBY1: DY285 | JBZ1: DY285 | JCA1: DY285 | JCB1: DY285 | JCC1: DY285 | JCD1: DY285 | JCE1: DY285 | JCF1: DY285 | JCG1: DY285 | JCH1: DY285 | JCI1: DY285 | JCJ1: DY286 | JCK1: DY286 | JCL1: DY286 | JCM1: DY286 | JCN1: DY286 | JCO1: DY286 | JCP1: DY286 | JCQ1: DY286 | JCR1: DY286 | JCS1: DY286 | JCT1: DY286 | JCU1: DY286 | JCV1: DY286 | JCW1: DY286 | JCX1: DY286 | JCY1: DY286 | JCZ1: DY286 | JDA1: DY286 | JDB1: DY286 | JDC1: DY286 | JDD1: DY286 | JDE1: DY286 | JDF1: DY286 | JDG1: DY286 | JDH1: DY287 | JDI1: DY287 | JDJ1: DY287 | JDK1: DY287 | JDL1: DY287 | JDM1: DY287 | JDN1: DY287 | JDO1: DY287 | JDP1: DY287 | JDQ1: DY287 | JDR1: DY287 | JDS1: DY287 | JDT1: DY287 | JDU1: DY287 | JDV1: DY287 | JDW1: DY287 | JDX1: DY287 | JDY1: DY287 | JDZ1: DY287 | JEA1: DY287 | JEB1: DY287 | JEC1: DY287 | JED1: DY287 | JEE1: DY287 | JEF1: DY288 | JEG1: DY288 | JEH1: DY288 | JEI1: DY288 | JEJ1: DY288 | JEK1: DY288 | JEL1: DY288 | JEM1: DY288 | JEN1: DY288 | JEO1: DY288 | JEP1: DY288 | JEQ1: DY288 | JER1: DY288 | JES1: DY288 | JET1: DY288 | JEU1: DY288 | JEV1: DY288 | JEW1: DY288 | JEX1: DY288 | JEY1: DY288 | JEZ1: DY288 | JFA1: DY288 | JFB1: DY288 | JFC1: DY288 | JFD1: DY289 | JFE1: DY289 | JFF1: DY289 | JFG1: DY289 | JFH1: DY289 | JFI1: DY289 | JFJ1: DY289 | JFK1: DY289 | JFL1: DY289 | JFM1: DY289 | JFN1: DY289 | JFO1: DY289 | JFP1: DY289 | JFQ1: DY289 | JFR1: DY289 | JFS1: DY289 | JFT1: DY289 | JFU1: DY289 | JFV1: DY289 | JFW1: DY289 | JFX1: DY289 | JFY1: DY289 | JFZ1: DY289 | JGA1: DY289 | JGB1: DY290 | JGC1: DY290 | JGD1: DY290 | JGE1: DY290 | JGF1: DY290 | JGG1: DY290 | JGH1: DY290 | JGI1: DY290 | JGJ1: DY290 | JGK1: DY290 | JGL1: DY290 | JGM1: DY290 | JGN1: DY290 | JGO1: DY290 | JGP1: DY290 | JGQ1: DY290 | JGR1: DY290 | JGS1: DY290 | JGT1: DY290 | JGU1: DY290 | JGV1: DY290 | JGW1: DY290 | JGX1: DY290 | JGY1: DY290 | JGZ1: DY291 | JHA1: DY291 | JHB1: DY291 | JHC1: DY291 | JHD1: DY291 | JHE1: DY291 | JHF1: DY291 | JHG1: DY291 | JHH1: DY291 | JHI1: DY291 | JHJ1: DY291 | JHK1: DY291 | JHL1: DY291 | JHM1: DY291 | JHN1: DY291 | JHO1: DY291 | JHP1: DY291 | JHQ1: DY291 | JHR1: DY291 | JHS1: DY291 | JHT1: DY291 | JHU1: DY291 | JHV1: DY291 | JHW1: DY291 | JHX1: DY292 | JHY1: DY292 | JHZ1: DY292 | JIA1: DY292 | JIB1: DY292 | JIC1: DY292 | JID1: DY292 | JIE1: DY292 | JIF1: DY292 | JIG1: DY292 | JIH1: DY292 | JII1: DY292 | JIJ1: DY292 | JIK1: DY292 | JIL1: DY292 | JIM1: DY292 | JIN1: DY292 | JIO1: DY292 | JIP1: DY292 | JIQ1: DY292 | JIR1: DY292 | JIS1: DY292 | JIT1: DY292 | JIU1: DY292 | JIV1: DY293 | JIW1: DY293 | JIX1: DY293 | JIY1: DY293 | JIZ1: DY293 | JJA1: DY293 | JJB1: DY293 | JJC1: DY293 | JJD1: DY293 | JJE1: DY293 | JJF1: DY293 | JJG1: DY293 | JJH1: DY293 | JJI1: DY293 | JJJ1: DY293 | JJK1: DY293 | JJL1: DY293 | JJM1: DY293 | JJN1: DY293 | JJO1: DY293 | JJP1: DY293 | JJQ1: DY293 | JJR1: DY293 | JJS1: DY293 | JJT1: DY294 | JJU1: DY294 | JJV1: DY294 | JJW1: DY294 | JJX1: DY294 | JJY1: DY294 | JJZ1: DY294 | JKA1: DY294 | JKB1: DY294 | JKC1: DY294 | JKD1: DY294 | JKE1: DY294 | JKF1: DY294 | JKG1: DY294 | JKH1: DY294 | JKI1: DY294 | JKJ1: DY294 | JKK1: DY294 | JKL1: DY294 | JKM1: DY294 | JKN1: DY294 | JKO1: DY294 | JKP1: DY294 | JKQ1: DY294 | JKR1: DY295 | JKS1: DY295 | JKT1: DY295 | JKU1: DY295 | JKV1: DY295 | JKW1: DY295 | JKX1: DY295 | JKY1: DY295 | JKZ1: DY295 | JLA1: DY295 | JLB1: DY295 | JLC1: DY295 | JLD1: DY295 | JLE1: DY295 | JLF1: DY295 | JLG1: DY295 | JLH1: DY295 | JLI1: DY295 | JLJ1: DY295 | JLK1: DY295 | JLL1: DY295 | JLM1: DY295 | JLN1: DY295 | JLO1: DY295 | JLP1: DY296 | JLQ1: DY296 | JLR1: DY296 | JLS1: DY296 | JLT1: DY296 | JLU1: DY296 | JLV1: DY296 | JLW1: DY296 | JLX1: DY296 | JLY1: DY296 | JLZ1: DY296 | JMA1: DY296 | JMB1: DY296 | JMC1: DY296 | JMD1: DY296 | JME1: DY296 | JMF1: DY296 | JMG1: DY296 | JMH1: DY296 | JMI1: DY296 | JMJ1: DY296 | JMK1: DY296 | JML1: DY296 | JMM1: DY296 | JMN1: DY297 | JMO1: DY297 | JMP1: DY297 | JMQ1: DY297 | JMR1: DY297 | JMS1: DY297 | JMT1: DY297 | JMU1: DY297 | JMV1: DY297 | JMW1: DY297 | JMX1: DY297 | JMY1: DY297 | JMZ1: DY297 | JNA1: DY297 | JNB1: DY297 | JNC1: DY297 | JND1: DY297 | JNE1: DY297 | JNF1: DY297 | JNG1: DY297 | JNH1: DY297 | JNI1: DY297 | JNJ1: DY297 | JNK1: DY297 | JNL1: DY298 | JNM1: DY298 | JNN1: DY298 | JNO1: DY298 | JNP1: DY298 | JNQ1: DY298 | JNR1: DY298 | JNS1: DY298 | JNT1: DY298 | JNU1: DY298 | JNV1: DY298 | JNW1: DY298 | JNX1: DY298 | JNY1: DY298 | JNZ1: DY298 | JOA1: DY298 | JOB1: DY298 | JOC1: DY298 | JOD1: DY298 | JOE1: DY298 | JOF1: DY298 | JOG1: DY298 | JOH1: DY298 | JOI1: DY298 | JOJ1: DY299 | JOK1: DY299 | JOL1: DY299 | JOM1: DY299 | JON1: DY299 | JOO1: DY299 | JOP1: DY299 | JOQ1: DY299 | JOR1: DY299 | JOS1: DY299 | JOT1: DY299 | JOU1: DY299 | JOV1: DY299 | JOW1: DY299 | JOX1: DY299 | JOY1: DY299 | JOZ1: DY299 | JPA1: DY299 | JPB1: DY299 | JPC1: DY299 | JPD1: DY299 | JPE1: DY299 | JPF1: DY299 | JPG1: DY299 | JPH1: DY300 | JPI1: DY300 | JPJ1: DY300 | JPK1: DY300 | JPL1: DY300 | JPM1: DY300 | JPN1: DY300 | JPO1: DY300 | JPP1: DY300 | JPQ1: DY300 | JPR1: DY300 | JPS1: DY300 | JPT1: DY300 | JPU1: DY300 | JPV1: DY300 | JPW1: DY300 | JPX1: DY300 | JPY1: DY300 | JPZ1: DY300 | JQA1: DY300 | JQB1: DY300 | JQC1: DY300 | JQD1: DY300 | JQE1: DY300 | JQF1: DY301 | JQG1: DY301 | JQH1: DY301 | JQI1: DY301 | JQJ1: DY301 | JQK1: DY301 | JQL1: DY301 | JQM1: DY301 | JQN1: DY301 | JQO1: DY301 | JQP1: DY301 | JQQ1: DY301 | JQR1: DY301 | JQS1: DY301 | JQT1: DY301 | JQU1: DY301 | JQV1: DY301 | JQW1: DY301 | JQX1: DY301 | JQY1: DY301 | JQZ1: DY301 | JRA1: DY301 | JRB1: DY301 | JRC1: DY301 | JRD1: DY302 | JRE1: DY302 | JRF1: DY302 | JRG1: DY302 | JRH1: DY302 | JRI1: DY302 | JRJ1: DY302 | JRK1: DY302 | JRL1: DY302 | JRM1: DY302 | JRN1: DY302 | JRO1: DY302 | JRP1: DY302 | JRQ1: DY302 | JRR1: DY302 | JRS1: DY302 | JRT1: DY302 | JRU1: DY302 | JRV1: DY302 | JRW1: DY302 | JRX1: DY302 | JRY1: DY302 | JRZ1: DY302 | JSA1: DY302 | JSB1: DY303 | JSC1: DY303 | JSD1: DY303 | JSE1: DY303 | JSF1: DY303 | JSG1: DY303 | JSH1: DY303 | JSI1: DY303 | JSJ1: DY303 | JSK1: DY303 | JSL1: DY303 | JSM1: DY303 | JSN1: DY303 | JSO1: DY303 | JSP1: DY303 | JSQ1: DY303 | JSR1: DY303 | JSS1: DY303 | JST1: DY303 | JSU1: DY303 | JSV1: DY303 | JSW1: DY303 | JSX1: DY303 | JSY1: DY303 | JSZ1: DY304 | JTA1: DY304 | JTB1: DY304 | JTC1: DY304 | JTD1: DY304 | JTE1: DY304 | JTF1: DY304 | JTG1: DY304 | JTH1: DY304 | JTI1: DY304 | JTJ1: DY304 | JTK1: DY304 | JTL1: DY304 | JTM1: DY304 | JTN1: DY304 | JTO1: DY304 | JTP1: DY304 | JTQ1: DY304 | JTR1: DY304 | JTS1: DY304 | JTT1: DY304 | JTU1: DY304 | JTV1: DY304 | JTW1: DY304 | JTX1: DY305 | JTY1: DY305 | JTZ1: DY305 | JUA1: DY305 | JUB1: DY305 | JUC1: DY305 | JUD1: DY305 | JUE1: DY305 | JUF1: DY305 | JUG1: DY305 | JUH1: DY305 | JUI1: DY305 | JUJ1: DY305 | JUK1: DY305 | JUL1: DY305 | JUM1: DY305 | JUN1: DY305 | JUO1: DY305 | JUP1: DY305 | JUQ1: DY305 | JUR1: DY305 | JUS1: DY305 | JUT1: DY305 | JUU1: DY305 | JUV1: DY306 | JUW1: DY306 | JUX1: DY306 | JUY1: DY306 | JUZ1: DY306 | JVA1: DY306 | JVB1: DY306 | JVC1: DY306 | JVD1: DY306 | JVE1: DY306 | JVF1: DY306 | JVG1: DY306 | JVH1: DY306 | JVI1: DY306 | JVJ1: DY306 | JVK1: DY306 | JVL1: DY306 | JVM1: DY306 | JVN1: DY306 | JVO1: DY306 | JVP1: DY306 | JVQ1: DY306 | JVR1: DY306 | JVS1: DY306 | JVT1: DY307 | JVU1: DY307 | JVV1: DY307 | JVW1: DY307 | JVX1: DY307 | JVY1: DY307 | JVZ1: DY307 | JWA1: DY307 | JWB1: DY307 | JWC1: DY307 | JWD1: DY307 | JWE1: DY307 | JWF1: DY307 | JWG1: DY307 | JWH1: DY307 | JWI1: DY307 | JWJ1: DY307 | JWK1: DY307 | JWL1: DY307 | JWM1: DY307 | JWN1: DY307 | JWO1: DY307 | JWP1: DY307 | JWQ1: DY307 | JWR1: DY308 | JWS1: DY308 | JWT1: DY308 | JWU1: DY308 | JWV1: DY308 | JWW1: DY308 | JWX1: DY308 | JWY1: DY308 | JWZ1: DY308 | JXA1: DY308 | JXB1: DY308 | JXC1: DY308 | JXD1: DY308 | JXE1: DY308 | JXF1: DY308 | JXG1: DY308 | JXH1: DY308 | JXI1: DY308 | JXJ1: DY308 | JXK1: DY308 | JXL1: DY308 | JXM1: DY308 | JXN1: DY308 | JXO1: DY308 | JXP1: DY309 | JXQ1: DY309 | JXR1: DY309 | JXS1: DY309 | JXT1: DY309 | JXU1: DY309 | JXV1: DY309 | JXW1: DY309 | JXX1: DY309 | JXY1: DY309 | JXZ1: DY309 | JYA1: DY309 | JYB1: DY309 | JYC1: DY309 | JYD1: DY309 | JYE1: DY309 | JYF1: DY309 | JYG1: DY309 | JYH1: DY309 | JYI1: DY309 | JYJ1: DY309 | JYK1: DY309 | JYL1: DY309 | JYM1: DY309 | JYN1: DY310 | JYO1: DY310 | JYP1: DY310 | JYQ1: DY310 | JYR1: DY310 | JYS1: DY310 | JYT1: DY310 | JYU1: DY310 | JYV1: DY310 | JYW1: DY310 | JYX1: DY310 | JYY1: DY310 | JYZ1: DY310 | JZA1: DY310 | JZB1: DY310 | JZC1: DY310 | JZD1: DY310 | JZE1: DY310 | JZF1: DY310 | JZG1: DY310 | JZH1: DY310 | JZI1: DY310 | JZJ1: DY310 | JZK1: DY310 | JZL1: DY311 | JZM1: DY311 | JZN1: DY311 | JZO1: DY311 | JZP1: DY311 | JZQ1: DY311 | JZR1: DY311 | JZS1: DY311 | JZT1: DY311 | JZU1: DY311 | JZV1: DY311 | JZW1: DY311 | JZX1: DY311 | JZY1: DY311 | JZZ1: DY311 | KAA1: DY311 | KAB1: DY311 | KAC1: DY311 | KAD1: DY311 | KAE1: DY311 | KAF1: DY311 | KAG1: DY311 | KAH1: DY311 | KAI1: DY311 | KAJ1: DY312 | KAK1: DY312 | KAL1: DY312 | KAM1: DY312 | KAN1: DY312 | KAO1: DY312 | KAP1: DY312 | KAQ1: DY312 | KAR1: DY312 | KAS1: DY312 | KAT1: DY312 | KAU1: DY312 | KAV1: DY312 | KAW1: DY312 | KAX1: DY312 | KAY1: DY312 | KAZ1: DY312 | KBA1: DY312 | KBB1: DY312 | KBC1: DY312 | KBD1: DY312 | KBE1: DY312 | KBF1: DY312 | KBG1: DY312 | KBH1: DY313 | KBI1: DY313 | KBJ1: DY313 | KBK1: DY313 | KBL1: DY313 | KBM1: DY313 | KBN1: DY313 | KBO1: DY313 | KBP1: DY313 | KBQ1: DY313 | KBR1: DY313 | KBS1: DY313 | KBT1: DY313 | KBU1: DY313 | KBV1: DY313 | KBW1: DY313 | KBX1: DY313 | KBY1: DY313 | KBZ1: DY313 | KCA1: DY313 | KCB1: DY313 | KCC1: DY313 | KCD1: DY313 | KCE1: DY313 | KCF1: DY314 | KCG1: DY314 | KCH1: DY314 | KCI1: DY314 | KCJ1: DY314 | KCK1: DY314 | KCL1: DY314 | KCM1: DY314 | KCN1: DY314 | KCO1: DY314 | KCP1: DY314 | KCQ1: DY314 | KCR1: DY314 | KCS1: DY314 | KCT1: DY314 | KCU1: DY314 | KCV1: DY314 | KCW1: DY314 | KCX1: DY314 | KCY1: DY314 | KCZ1: DY314 | KDA1: DY314 | KDB1: DY314 | KDC1: DY314 | KDD1: DY315 | KDE1: DY315 | KDF1: DY315 | KDG1: DY315 | KDH1: DY315 | KDI1: DY315 | KDJ1: DY315 | KDK1: DY315 | KDL1: DY315 | KDM1: DY315 | KDN1: DY315 | KDO1: DY315 | KDP1: DY315 | KDQ1: DY315 | KDR1: DY315 | KDS1: DY315 | KDT1: DY315 | KDU1: DY315 | KDV1: DY315 | KDW1: DY315 | KDX1: DY315 | KDY1: DY315 | KDZ1: DY315 | KEA1: DY315 | KEB1: DY316 | KEC1: DY316 | KED1: DY316 | KEE1: DY316 | KEF1: DY316 | KEG1: DY316 | KEH1: DY316 | KEI1: DY316 | KEJ1: DY316 | KEK1: DY316 | KEL1: DY316 | KEM1: DY316 | KEN1: DY316 | KEO1: DY316 | KEP1: DY316 | KEQ1: DY316 | KER1: DY316 | KES1: DY316 | KET1: DY316 | KEU1: DY316 | KEV1: DY316 | KEW1: DY316 | KEX1: DY316 | KEY1: DY316 | KEZ1: DY317 | KFA1: DY317 | KFB1: DY317 | KFC1: DY317 | KFD1: DY317 | KFE1: DY317 | KFF1: DY317 | KFG1: DY317 | KFH1: DY317 | KFI1: DY317 | KFJ1: DY317 | KFK1: DY317 | KFL1: DY317 | KFM1: DY317 | KFN1: DY317 | KFO1: DY317 | KFP1: DY317 | KFQ1: DY317 | KFR1: DY317 | KFS1: DY317 | KFT1: DY317 | KFU1: DY317 | KFV1: DY317 | KFW1: DY317 | KFX1: DY318 | KFY1: DY318 | KFZ1: DY318 | KGA1: DY318 | KGB1: DY318 | KGC1: DY318 | KGD1: DY318 | KGE1: DY318 | KGF1: DY318 | KGG1: DY318 | KGH1: DY318 | KGI1: DY318 | KGJ1: DY318 | KGK1: DY318 | KGL1: DY318 | KGM1: DY318 | KGN1: DY318 | KGO1: DY318 | KGP1: DY318 | KGQ1: DY318 | KGR1: DY318 | KGS1: DY318 | KGT1: DY318 | KGU1: DY318 | KGV1: DY319 | KGW1: DY319 | KGX1: DY319 | KGY1: DY319 | KGZ1: DY319 | KHA1: DY319 | KHB1: DY319 | KHC1: DY319 | KHD1: DY319 | KHE1: DY319 | KHF1: DY319 | KHG1: DY319 | KHH1: DY319 | KHI1: DY319 | KHJ1: DY319 | KHK1: DY319 | KHL1: DY319 | KHM1: DY319 | KHN1: DY319 | KHO1: DY319 | KHP1: DY319 | KHQ1: DY319 | KHR1: DY319 | KHS1: DY319 | KHT1: DY320 | KHU1: DY320 | KHV1: DY320 | KHW1: DY320 | KHX1: DY320 | KHY1: DY320 | KHZ1: DY320 | KIA1: DY320 | KIB1: DY320 | KIC1: DY320 | KID1: DY320 | KIE1: DY320 | KIF1: DY320 | KIG1: DY320 | KIH1: DY320 | KII1: DY320 | KIJ1: DY320 | KIK1: DY320 | KIL1: DY320 | KIM1: DY320 | KIN1: DY320 | KIO1: DY320 | KIP1: DY320 | KIQ1: DY320 | KIR1: DY321 | KIS1: DY321 | KIT1: DY321 | KIU1: DY321 | KIV1: DY321 | KIW1: DY321 | KIX1: DY321 | KIY1: DY321 | KIZ1: DY321 | KJA1: DY321 | KJB1: DY321 | KJC1: DY321 | KJD1: DY321 | KJE1: DY321 | KJF1: DY321 | KJG1: DY321 | KJH1: DY321 | KJI1: DY321 | KJJ1: DY321 | KJK1: DY321 | KJL1: DY321 | KJM1: DY321 | KJN1: DY321 | KJO1: DY321 | KJP1: DY322 | KJQ1: DY322 | KJR1: DY322 | KJS1: DY322 | KJT1: DY322 | KJU1: DY322 | KJV1: DY322 | KJW1: DY322 | KJX1: DY322 | KJY1: DY322 | KJZ1: DY322 | KKA1: DY322 | KKB1: DY322 | KKC1: DY322 | KKD1: DY322 | KKE1: DY322 | KKF1: DY322 | KKG1: DY322 | KKH1: DY322 | KKI1: DY322 | KKJ1: DY322 | KKK1: DY322 | KKL1: DY322 | KKM1: DY322 | KKN1: DY323 | KKO1: DY323 | KKP1: DY323 | KKQ1: DY323 | KKR1: DY323 | KKS1: DY323 | KKT1: DY323 | KKU1: DY323 | KKV1: DY323 | KKW1: DY323 | KKX1: DY323 | KKY1: DY323 | KKZ1: DY323 | KLA1: DY323 | KLB1: DY323 | KLC1: DY323 | KLD1: DY323 | KLE1: DY323 | KLF1: DY323 | KLG1: DY323 | KLH1: DY323 | KLI1: DY323 | KLJ1: DY323 | KLK1: DY323 | KLL1: DY324 | KLM1: DY324 | KLN1: DY324 | KLO1: DY324 | KLP1: DY324 | KLQ1: DY324 | KLR1: DY324 | KLS1: DY324 | KLT1: DY324 | KLU1: DY324 | KLV1: DY324 | KLW1: DY324 | KLX1: DY324 | KLY1: DY324 | KLZ1: DY324 | KMA1: DY324 | KMB1: DY324 | KMC1: DY324 | KMD1: DY324 | KME1: DY324 | KMF1: DY324 | KMG1: DY324 | KMH1: DY324 | KMI1: DY324 | KMJ1: DY325 | KMK1: DY325 | KML1: DY325 | KMM1: DY325 | KMN1: DY325 | KMO1: DY325 | KMP1: DY325 | KMQ1: DY325 | KMR1: DY325 | KMS1: DY325 | KMT1: DY325 | KMU1: DY325 | KMV1: DY325 | KMW1: DY325 | KMX1: DY325 | KMY1: DY325 | KMZ1: DY325 | KNA1: DY325 | KNB1: DY325 | KNC1: DY325 | KND1: DY325 | KNE1: DY325 | KNF1: DY325 | KNG1: DY325 | KNH1: DY326 | KNI1: DY326 | KNJ1: DY326 | KNK1: DY326 | KNL1: DY326 | KNM1: DY326 | KNN1: DY326 | KNO1: DY326 | KNP1: DY326 | KNQ1: DY326 | KNR1: DY326 | KNS1: DY326 | KNT1: DY326 | KNU1: DY326 | KNV1: DY326 | KNW1: DY326 | KNX1: DY326 | KNY1: DY326 | KNZ1: DY326 | KOA1: DY326 | KOB1: DY326 | KOC1: DY326 | KOD1: DY326 | KOE1: DY326 | KOF1: DY327 | KOG1: DY327 | KOH1: DY327 | KOI1: DY327 | KOJ1: DY327 | KOK1: DY327 | KOL1: DY327 | KOM1: DY327 | KON1: DY327 | KOO1: DY327 | KOP1: DY327 | KOQ1: DY327 | KOR1: DY327 | KOS1: DY327 | KOT1: DY327 | KOU1: DY327 | KOV1: DY327 | KOW1: DY327 | KOX1: DY327 | KOY1: DY327 | KOZ1: DY327 | KPA1: DY327 | KPB1: DY327 | KPC1: DY327 | KPD1: DY328 | KPE1: DY328 | KPF1: DY328 | KPG1: DY328 | KPH1: DY328 | KPI1: DY328 | KPJ1: DY328 | KPK1: DY328 | KPL1: DY328 | KPM1: DY328 | KPN1: DY328 | KPO1: DY328 | KPP1: DY328 | KPQ1: DY328 | KPR1: DY328 | KPS1: DY328 | KPT1: DY328 | KPU1: DY328 | KPV1: DY328 | KPW1: DY328 | KPX1: DY328 | KPY1: DY328 | KPZ1: DY328 | KQA1: DY328 | KQB1: DY329 | KQC1: DY329 | KQD1: DY329 | KQE1: DY329 | KQF1: DY329 | KQG1: DY329 | KQH1: DY329 | KQI1: DY329 | KQJ1: DY329 | KQK1: DY329 | KQL1: DY329 | KQM1: DY329 | KQN1: DY329 | KQO1: DY329 | KQP1: DY329 | KQQ1: DY329 | KQR1: DY329 | KQS1: DY329 | KQT1: DY329 | KQU1: DY329 | KQV1: DY329 | KQW1: DY329 | KQX1: DY329 | KQY1: DY329 | KQZ1: DY330 | KRA1: DY330 | KRB1: DY330 | KRC1: DY330 | KRD1: DY330 | KRE1: DY330 | KRF1: DY330 | KRG1: DY330 | KRH1: DY330 | KRI1: DY330 | KRJ1: DY330 | KRK1: DY330 | KRL1: DY330 | KRM1: DY330 | KRN1: DY330 | KRO1: DY330 | KRP1: DY330 | KRQ1: DY330 | KRR1: DY330 | KRS1: DY330 | KRT1: DY330 | KRU1: DY330 | KRV1: DY330 | KRW1: DY330 | KRX1: DY331 | KRY1: DY331 | KRZ1: DY331 | KSA1: DY331 | KSB1: DY331 | KSC1: DY331 | KSD1: DY331 | KSE1: DY331 | KSF1: DY331 | KSG1: DY331 | KSH1: DY331 | KSI1: DY331 | KSJ1: DY331 | KSK1: DY331 | KSL1: DY331 | KSM1: DY331 | KSN1: DY331 | KSO1: DY331 | KSP1: DY331 | KSQ1: DY331 | KSR1: DY331 | KSS1: DY331 | KST1: DY331 | KSU1: DY331 | KSV1: DY332 | KSW1: DY332 | KSX1: DY332 | KSY1: DY332 | KSZ1: DY332 | KTA1: DY332 | KTB1: DY332 | KTC1: DY332 | KTD1: DY332 | KTE1: DY332 | KTF1: DY332 | KTG1: DY332 | KTH1: DY332 | KTI1: DY332 | KTJ1: DY332 | KTK1: DY332 | KTL1: DY332 | KTM1: DY332 | KTN1: DY332 | KTO1: DY332 | KTP1: DY332 | KTQ1: DY332 | KTR1: DY332 | KTS1: DY332 | KTT1: DY333 | KTU1: DY333 | KTV1: DY333 | KTW1: DY333 | KTX1: DY333 | KTY1: DY333 | KTZ1: DY333 | KUA1: DY333 | KUB1: DY333 | KUC1: DY333 | KUD1: DY333 | KUE1: DY333 | KUF1: DY333 | KUG1: DY333 | KUH1: DY333 | KUI1: DY333 | KUJ1: DY333 | KUK1: DY333 | KUL1: DY333 | KUM1: DY333 | KUN1: DY333 | KUO1: DY333 | KUP1: DY333 | KUQ1: DY333 | KUR1: DY334 | KUS1: DY334 | KUT1: DY334 | KUU1: DY334 | KUV1: DY334 | KUW1: DY334 | KUX1: DY334 | KUY1: DY334 | KUZ1: DY334 | KVA1: DY334 | KVB1: DY334 | KVC1: DY334 | KVD1: DY334 | KVE1: DY334 | KVF1: DY334 | KVG1: DY334 | KVH1: DY334 | KVI1: DY334 | KVJ1: DY334 | KVK1: DY334 | KVL1: DY334 | KVM1: DY334 | KVN1: DY334 | KVO1: DY334 | KVP1: DY335 | KVQ1: DY335 | KVR1: DY335 | KVS1: DY335 | KVT1: DY335 | KVU1: DY335 | KVV1: DY335 | KVW1: DY335 | KVX1: DY335 | KVY1: DY335 | KVZ1: DY335 | KWA1: DY335 | KWB1: DY335 | KWC1: DY335 | KWD1: DY335 | KWE1: DY335 | KWF1: DY335 | KWG1: DY335 | KWH1: DY335 | KWI1: DY335 | KWJ1: DY335 | KWK1: DY335 | KWL1: DY335 | KWM1: DY335 | KWN1: DY336 | KWO1: DY336 | KWP1: DY336 | KWQ1: DY336 | KWR1: DY336 | KWS1: DY336 | KWT1: DY336 | KWU1: DY336 | KWV1: DY336 | KWW1: DY336 | KWX1: DY336 | KWY1: DY336 | KWZ1: DY336 | KXA1: DY336 | KXB1: DY336 | KXC1: DY336 | KXD1: DY336 | KXE1: DY336 | KXF1: DY336 | KXG1: DY336 | KXH1: DY336 | KXI1: DY336 | KXJ1: DY336 | KXK1: DY336 | KXL1: DY337 | KXM1: DY337 | KXN1: DY337 | KXO1: DY337 | KXP1: DY337 | KXQ1: DY337 | KXR1: DY337 | KXS1: DY337 | KXT1: DY337 | KXU1: DY337 | KXV1: DY337 | KXW1: DY337 | KXX1: DY337 | KXY1: DY337 | KXZ1: DY337 | KYA1: DY337 | KYB1: DY337 | KYC1: DY337 | KYD1: DY337 | KYE1: DY337 | KYF1: DY337 | KYG1: DY337 | KYH1: DY337 | KYI1: DY337 | KYJ1: DY338 | KYK1: DY338 | KYL1: DY338 | KYM1: DY338 | KYN1: DY338 | KYO1: DY338 | KYP1: DY338 | KYQ1: DY338 | KYR1: DY338 | KYS1: DY338 | KYT1: DY338 | KYU1: DY338 | KYV1: DY338 | KYW1: DY338 | KYX1: DY338 | KYY1: DY338 | KYZ1: DY338 | KZA1: DY338 | KZB1: DY338 | KZC1: DY338 | KZD1: DY338 | KZE1: DY338 | KZF1: DY338 | KZG1: DY338 | KZH1: DY339 | KZI1: DY339 | KZJ1: DY339 | KZK1: DY339 | KZL1: DY339 | KZM1: DY339 | KZN1: DY339 | KZO1: DY339 | KZP1: DY339 | KZQ1: DY339 | KZR1: DY339 | KZS1: DY339 | KZT1: DY339 | KZU1: DY339 | KZV1: DY339 | KZW1: DY339 | KZX1: DY339 | KZY1: DY339 | KZZ1: DY339 | LAA1: DY339 | LAB1: DY339 | LAC1: DY339 | LAD1: DY339 | LAE1: DY339 | LAF1: DY340 | LAG1: DY340 | LAH1: DY340 | LAI1: DY340 | LAJ1: DY340 | LAK1: DY340 | LAL1: DY340 | LAM1: DY340 | LAN1: DY340 | LAO1: DY340 | LAP1: DY340 | LAQ1: DY340 | LAR1: DY340 | LAS1: DY340 | LAT1: DY340 | LAU1: DY340 | LAV1: DY340 | LAW1: DY340 | LAX1: DY340 | LAY1: DY340 | LAZ1: DY340 | LBA1: DY340 | LBB1: DY340 | LBC1: DY340 | LBD1: DY341 | LBE1: DY341 | LBF1: DY341 | LBG1: DY341 | LBH1: DY341 | LBI1: DY341 | LBJ1: DY341 | LBK1: DY341 | LBL1: DY341 | LBM1: DY341 | LBN1: DY341 | LBO1: DY341 | LBP1: DY341 | LBQ1: DY341 | LBR1: DY341 | LBS1: DY341 | LBT1: DY341 | LBU1: DY341 | LBV1: DY341 | LBW1: DY341 | LBX1: DY341 | LBY1: DY341 | LBZ1: DY341 | LCA1: DY341 | LCB1: DY342 | LCC1: DY342 | LCD1: DY342 | LCE1: DY342 | LCF1: DY342 | LCG1: DY342 | LCH1: DY342 | LCI1: DY342 | LCJ1: DY342 | LCK1: DY342 | LCL1: DY342 | LCM1: DY342 | LCN1: DY342 | LCO1: DY342 | LCP1: DY342 | LCQ1: DY342 | LCR1: DY342 | LCS1: DY342 | LCT1: DY342 | LCU1: DY342 | LCV1: DY342 | LCW1: DY342 | LCX1: DY342 | LCY1: DY342 | LCZ1: DY343 | LDA1: DY343 | LDB1: DY343 | LDC1: DY343 | LDD1: DY343 | LDE1: DY343 | LDF1: DY343 | LDG1: DY343 | LDH1: DY343 | LDI1: DY343 | LDJ1: DY343 | LDK1: DY343 | LDL1: DY343 | LDM1: DY343 | LDN1: DY343 | LDO1: DY343 | LDP1: DY343 | LDQ1: DY343 | LDR1: DY343 | LDS1: DY343 | LDT1: DY343 | LDU1: DY343 | LDV1: DY343 | LDW1: DY343 | LDX1: DY344 | LDY1: DY344 | LDZ1: DY344 | LEA1: DY344 | LEB1: DY344 | LEC1: DY344 | LED1: DY344 | LEE1: DY344 | LEF1: DY344 | LEG1: DY344 | LEH1: DY344 | LEI1: DY344 | LEJ1: DY344 | LEK1: DY344 | LEL1: DY344 | LEM1: DY344 | LEN1: DY344 | LEO1: DY344 | LEP1: DY344 | LEQ1: DY344 | LER1: DY344 | LES1: DY344 | LET1: DY344 | LEU1: DY344 | LEV1: DY345 | LEW1: DY345 | LEX1: DY345 | LEY1: DY345 | LEZ1: DY345 | LFA1: DY345 | LFB1: DY345 | LFC1: DY345 | LFD1: DY345 | LFE1: DY345 | LFF1: DY345 | LFG1: DY345 | LFH1: DY345 | LFI1: DY345 | LFJ1: DY345 | LFK1: DY345 | LFL1: DY345 | LFM1: DY345 | LFN1: DY345 | LFO1: DY345 | LFP1: DY345 | LFQ1: DY345 | LFR1: DY345 | LFS1: DY345 | LFT1: DY346 | LFU1: DY346 | LFV1: DY346 | LFW1: DY346 | LFX1: DY346 | LFY1: DY346 | LFZ1: DY346 | LGA1: DY346 | LGB1: DY346 | LGC1: DY346 | LGD1: DY346 | LGE1: DY346 | LGF1: DY346 | LGG1: DY346 | LGH1: DY346 | LGI1: DY346 | LGJ1: DY346 | LGK1: DY346 | LGL1: DY346 | LGM1: DY346 | LGN1: DY346 | LGO1: DY346 | LGP1: DY346 | LGQ1: DY346 | LGR1: DY347 | LGS1: DY347 | LGT1: DY347 | LGU1: DY347 | LGV1: DY347 | LGW1: DY347 | LGX1: DY347 | LGY1: DY347 | LGZ1: DY347 | LHA1: DY347 | LHB1: DY347 | LHC1: DY347 | LHD1: DY347 | LHE1: DY347 | LHF1: DY347 | LHG1: DY347 | LHH1: DY347 | LHI1: DY347 | LHJ1: DY347 | LHK1: DY347 | LHL1: DY347 | LHM1: DY347 | LHN1: DY347 | LHO1: DY347 | LHP1: DY348 | LHQ1: DY348 | LHR1: DY348 | LHS1: DY348 | LHT1: DY348 | LHU1: DY348 | LHV1: DY348 | LHW1: DY348 | LHX1: DY348 | LHY1: DY348 | LHZ1: DY348 | LIA1: DY348 | LIB1: DY348 | LIC1: DY348 | LID1: DY348 | LIE1: DY348 | LIF1: DY348 | LIG1: DY348 | LIH1: DY348 | LII1: DY348 | LIJ1: DY348 | LIK1: DY348 | LIL1: DY348 | LIM1: DY348 | LIN1: DY349 | LIO1: DY349 | LIP1: DY349 | LIQ1: DY349 | LIR1: DY349 | LIS1: DY349 | LIT1: DY349 | LIU1: DY349 | LIV1: DY349 | LIW1: DY349 | LIX1: DY349 | LIY1: DY349 | LIZ1: DY349 | LJA1: DY349 | LJB1: DY349 | LJC1: DY349 | LJD1: DY349 | LJE1: DY349 | LJF1: DY349 | LJG1: DY349 | LJH1: DY349 | LJI1: DY349 | LJJ1: DY349 | LJK1: DY349 | LJL1: DY350 | LJM1: DY350 | LJN1: DY350 | LJO1: DY350 | LJP1: DY350 | LJQ1: DY350 | LJR1: DY350 | LJS1: DY350 | LJT1: DY350 | LJU1: DY350 | LJV1: DY350 | LJW1: DY350 | LJX1: DY350 | LJY1: DY350 | LJZ1: DY350 | LKA1: DY350 | LKB1: DY350 | LKC1: DY350 | LKD1: DY350 | LKE1: DY350 | LKF1: DY350 | LKG1: DY350 | LKH1: DY350 | LKI1: DY350 | LKJ1: DY351 | LKK1: DY351 | LKL1: DY351 | LKM1: DY351 | LKN1: DY351 | LKO1: DY351 | LKP1: DY351 | LKQ1: DY351 | LKR1: DY351 | LKS1: DY351 | LKT1: DY351 | LKU1: DY351 | LKV1: DY351 | LKW1: DY351 | LKX1: DY351 | LKY1: DY351 | LKZ1: DY351 | LLA1: DY351 | LLB1: DY351 | LLC1: DY351 | LLD1: DY351 | LLE1: DY351 | LLF1: DY351 | LLG1: DY351 | LLH1: DY352 | LLI1: DY352 | LLJ1: DY352 | LLK1: DY352 | LLL1: DY352 | LLM1: DY352 | LLN1: DY352 | LLO1: DY352 | LLP1: DY352 | LLQ1: DY352 | LLR1: DY352 | LLS1: DY352 | LLT1: DY352 | LLU1: DY352 | LLV1: DY352 | LLW1: DY352 | LLX1: DY352 | LLY1: DY352 | LLZ1: DY352 | LMA1: DY352 | LMB1: DY352 | LMC1: DY352 | LMD1: DY352 | LME1: DY352 | LMF1: DY353 | LMG1: DY353 | LMH1: DY353 | LMI1: DY353 | LMJ1: DY353 | LMK1: DY353 | LML1: DY353 | LMM1: DY353 | LMN1: DY353 | LMO1: DY353 | LMP1: DY353 | LMQ1: DY353 | LMR1: DY353 | LMS1: DY353 | LMT1: DY353 | LMU1: DY353 | LMV1: DY353 | LMW1: DY353 | LMX1: DY353 | LMY1: DY353 | LMZ1: DY353 | LNA1: DY353 | LNB1: DY353 | LNC1: DY353 | LND1: DY354 | LNE1: DY354 | LNF1: DY354 | LNG1: DY354 | LNH1: DY354 | LNI1: DY354 | LNJ1: DY354 | LNK1: DY354 | LNL1: DY354 | LNM1: DY354 | LNN1: DY354 | LNO1: DY354 | LNP1: DY354 | LNQ1: DY354 | LNR1: DY354 | LNS1: DY354 | LNT1: DY354 | LNU1: DY354 | LNV1: DY354 | LNW1: DY354 | LNX1: DY354 | LNY1: DY354 | LNZ1: DY354 | LOA1: DY354 | LOB1: DY355 | LOC1: DY355 | LOD1: DY355 | LOE1: DY355 | LOF1: DY355 | LOG1: DY355 | LOH1: DY355 | LOI1: DY355 | LOJ1: DY355 | LOK1: DY355 | LOL1: DY355 | LOM1: DY355 | LON1: DY355 | LOO1: DY355 | LOP1: DY355 | LOQ1: DY355 | LOR1: DY355 | LOS1: DY355 | LOT1: DY355 | LOU1: DY355 | LOV1: DY355 | LOW1: DY355 | LOX1: DY355 | LOY1: DY355 | LOZ1: DY356 | LPA1: DY356 | LPB1: DY356 | LPC1: DY356 | LPD1: DY356 | LPE1: DY356 | LPF1: DY356 | LPG1: DY356 | LPH1: DY356 | LPI1: DY356 | LPJ1: DY356 | LPK1: DY356 | LPL1: DY356 | LPM1: DY356 | LPN1: DY356 | LPO1: DY356 | LPP1: DY356 | LPQ1: DY356 | LPR1: DY356 | LPS1: DY356 | LPT1: DY356 | LPU1: DY356 | LPV1: DY356 | LPW1: DY356 | LPX1: DY357 | LPY1: DY357 | LPZ1: DY357 | LQA1: DY357 | LQB1: DY357 | LQC1: DY357 | LQD1: DY357 | LQE1: DY357 | LQF1: DY357 | LQG1: DY357 | LQH1: DY357 | LQI1: DY357 | LQJ1: DY357 | LQK1: DY357 | LQL1: DY357 | LQM1: DY357 | LQN1: DY357 | LQO1: DY357 | LQP1: DY357 | LQQ1: DY357 | LQR1: DY357 | LQS1: DY357 | LQT1: DY357 | LQU1: DY357 | LQV1: DY358 | LQW1: DY358 | LQX1: DY358 | LQY1: DY358 | LQZ1: DY358 | LRA1: DY358 | LRB1: DY358 | LRC1: DY358 | LRD1: DY358 | LRE1: DY358 | LRF1: DY358 | LRG1: DY358 | LRH1: DY358 | LRI1: DY358 | LRJ1: DY358 | LRK1: DY358 | LRL1: DY358 | LRM1: DY358 | LRN1: DY358 | LRO1: DY358 | LRP1: DY358 | LRQ1: DY358 | LRR1: DY358 | LRS1: DY358 | LRT1: DY359 | LRU1: DY359 | LRV1: DY359 | LRW1: DY359 | LRX1: DY359 | LRY1: DY359 | LRZ1: DY359 | LSA1: DY359 | LSB1: DY359 | LSC1: DY359 | LSD1: DY359 | LSE1: DY359 | LSF1: DY359 | LSG1: DY359 | LSH1: DY359 | LSI1: DY359 | LSJ1: DY359 | LSK1: DY359 | LSL1: DY359 | LSM1: DY359 | LSN1: DY359 | LSO1: DY359 | LSP1: DY359 | LSQ1: DY359 | LSR1: DY360 | LSS1: DY360 | LST1: DY360 | LSU1: DY360 | LSV1: DY360 | LSW1: DY360 | LSX1: DY360 | LSY1: DY360 | LSZ1: DY360 | LTA1: DY360 | LTB1: DY360 | LTC1: DY360 | LTD1: DY360 | LTE1: DY360 | LTF1: DY360 | LTG1: DY360 | LTH1: DY360 | LTI1: DY360 | LTJ1: DY360 | LTK1: DY360 | LTL1: DY360 | LTM1: DY360 | LTN1: DY360 | LTO1: DY360 | LTP1: DY361 | LTQ1: DY361 | LTR1: DY361 | LTS1: DY361 | LTT1: DY361 | LTU1: DY361 | LTV1: DY361 | LTW1: DY361 | LTX1: DY361 | LTY1: DY361 | LTZ1: DY361 | LUA1: DY361 | LUB1: DY361 | LUC1: DY361 | LUD1: DY361 | LUE1: DY361 | LUF1: DY361 | LUG1: DY361 | LUH1: DY361 | LUI1: DY361 | LUJ1: DY361 | LUK1: DY361 | LUL1: DY361 | LUM1: DY361 | LUN1: DY362 | LUO1: DY362 | LUP1: DY362 | LUQ1: DY362 | LUR1: DY362 | LUS1: DY362 | LUT1: DY362 | LUU1: DY362 | LUV1: DY362 | LUW1: DY362 | LUX1: DY362 | LUY1: DY362 | LUZ1: DY362 | LVA1: DY362 | LVB1: DY362 | LVC1: DY362 | LVD1: DY362 | LVE1: DY362 | LVF1: DY362 | LVG1: DY362 | LVH1: DY362 | LVI1: DY362 | LVJ1: DY362 | LVK1: DY362 | LVL1: DY363 | LVM1: DY363 | LVN1: DY363 | LVO1: DY363 | LVP1: DY363 | LVQ1: DY363 | LVR1: DY363 | LVS1: DY363 | LVT1: DY363 | LVU1: DY363 | LVV1: DY363 | LVW1: DY363 | LVX1: DY363 | LVY1: DY363 | LVZ1: DY363 | LWA1: DY363 | LWB1: DY363 | LWC1: DY363 | LWD1: DY363 | LWE1: DY363 | LWF1: DY363 | LWG1: DY363 | LWH1: DY363 | LWI1: DY363 | LWJ1: DY364 | LWK1: DY364 | LWL1: DY364 | LWM1: DY364 | LWN1: DY364 | LWO1: DY364 | LWP1: DY364 | LWQ1: DY364 | LWR1: DY364 | LWS1: DY364 | LWT1: DY364 | LWU1: DY364 | LWV1: DY364 | LWW1: DY364 | LWX1: DY364 | LWY1: DY364 | LWZ1: DY364 | LXA1: DY364 | LXB1: DY364 | LXC1: DY364 | LXD1: DY364 | LXE1: DY364 | LXF1: DY364 | LXG1: DY364 | LXH1: DY365 | LXI1: DY365 | LXJ1: DY365 | LXK1: DY365 | LXL1: DY365 | LXM1: DY365 | LXN1: DY365 | LXO1: DY365 | LXP1: DY365 | LXQ1: DY365 | LXR1: DY365 | LXS1: DY365 | LXT1: DY365 | LXU1: DY365 | LXV1: DY365 | LXW1: DY365 | LXX1: DY365 | LXY1: DY365 | LXZ1: DY365 | LYA1: DY365 | LYB1: DY365 | LYC1: DY365 | LYD1: DY365 | LYE1: DY365
